Workbook

Sheet Dashboard
A1: Overall Portfolio
A2: As of | B2: =OFFSET('Historical NAV'!A1,COUNT('Historical NAV'!B:B),,,) -> 45852
A3: Current Month | B3: =DATE(YEAR(B2), MONTH(B2), 1) -> 45839
A4: WTD | B4: =OFFSET('Historical NAV'!I1,COUNT('Historical NAV'!A:A),,,) -> -0.6851328
A5: MTD | B5: =OFFSET('Historical NAV'!K1,COUNT('Historical NAV'!A:A),,,) -> -0.68349276
A6: YTD | B6: =OFFSET('Historical NAV'!N1,COUNT('Historical NAV'!A:A),,,) -> -0.66335391
A8: Key Perf. Metrics | D8: Key Execution Metrics
A9: Daily Return | B9: =OFFSET('Historical NAV'!G1,COUNT('Historical NAV'!A:A),,,) -> -0.6851328 | D9: NAV (Net Liquidity) | E9: =OFFSET('Historical NAV'!B1,COUNT('Historical NAV'!A:A),,,) -> 20985069
A10: Leverage | B10: =E13/E9 -> 0.9961162 | D10: Excess Liquidity | E10: 41571526
A11: Return (30days) | B11: =OFFSET('Historical NAV'!R1,COUNT('Historical NAV'!A:A),,,) -> -0.67384436 | D11: Excess Liquidity/NAV | E11: =E10/E9 -> 1.9810049
A12: Return (90days) | B12: =OFFSET('Historical NAV'!T1,COUNT('Historical NAV'!A:A),,,) -> -0.74527735
A13: Return (365days) | B13: =OFFSET('Historical NAV'!V1,COUNT('Historical NAV'!A:A),,,) -> -0.3631342 | D13: To Allocate | E13: =K25 -> 20903567
A14: Sharpe Ratio | B14: =OFFSET('Historical NAV'!W1,COUNT('Historical NAV'!A:A),,,) -> -2.2529051 | D14: 0.005 | E14: =(D14*$E$13)/(1-D14) -> 105043.05
A15: Sotino Ratio | B15: =OFFSET('Historical NAV'!AB1,COUNT('Historical NAV'!A:A),,,) -> -0.33076595 | D15: 0.01 | E15: =(D15*$E$13)/(1-D15) -> 211147.14
A16: Volatility | B16: =OFFSET('Historical NAV'!P1,COUNT('Historical NAV'!A:A),,,) -> 1.8356923 | D16: 0.015 | E16: =(D16*$E$13)/(1-D16) -> 318328.44
A17: VaR 95% (30days) | B17: =OFFSET('Historical NAV'!AC1,COUNT('Historical NAV'!A:A),,,) -> -0.22973362 | D17: 0.05 | E17: =(D17*$E$13)/(1-D17) -> 1100187.8
A18: VaR 95% (90days) | B18: =OFFSET('Historical NAV'!AD1,COUNT('Historical NAV'!A:A),,,) -> -0.13175215
A19: VaR 95% (365days) | B19: =OFFSET('Historical NAV'!AE1,COUNT('Historical NAV'!A:A),,,) -> -0.077202934
A21: Performance by Asset Class
A23: Asset Class | B23: ETFs | C23: Stocks | D23: Stocks_int | E23: Bonds | F23: Commodities | G23: Future | H23: Option | I23: Crypto | J23: Others | K23: Total | L23: QQQ+TSM+NVDA | M23: Commodities | N23: gld
A24: No of investment | B24: =COUNTIF('Mark to Market'!$B$3:$B$1028,B23) -> 0 | C24: =COUNTIF('Mark to Market'!$B$3:$B$1028,C23) -> 0 | D24: =COUNTIF('Mark to Market'!$B$3:$B$1028,D23) -> 0 | E24: =COUNTIF('Mark to Market'!$B$3:$B$1028,E23) -> 1 | F24: =COUNTIF('Mark to Market'!$B$3:$B$1028,F23) -> 0 | G24: =COUNTIF('Mark to Market'!$B$3:$B$1028,G23) -> 0 | H24: =COUNTIF('Mark to Market'!$B$3:$B$1028,H23) -> 0 | I24: =COUNTIF('Mark to Market'!$B$3:$B$1028,I23) -> 0 | J24: =COUNTIF('Mark to Market'!$B$3:$B$1028,J23) -> 0 | K24: =SUM(B24:J24) -> 1 | L24: 3 | M24: 4
A25: Total Value (USD) | B25: =SUMIF('Mark to Market'!$B$3:$B$1028,B23,'Mark to Market'!$H$3:$H$1028) -> 0 | C25: =SUMIF('Mark to Market'!$B$3:$B$1028,C23,'Mark to Market'!$H$3:$H$1028) -> 0 | D25: =SUMIF('Mark to Market'!$B$3:$B$1028,D23,'Mark to Market'!$H$3:$H$1028) -> 0 | E25: =SUMIF('Mark to Market'!$B$3:$B$1028,E23,'Mark to Market'!$H$3:$H$1028) -> 20903567 | F25: =SUMIF('Mark to Market'!$B$3:$B$1028,F23,'Mark to Market'!$H$3:$H$1028) -> 0 | G25: =SUMIF('Mark to Market'!$B$3:$B$1028,G23,'Mark to Market'!$H$3:$H$1028) -> 0 | H25: =SUMIF('Mark to Market'!$B$3:$B$1028,H23,'Mark to Market'!$H$3:$H$1028) -> 0 | I25: =SUMIF('Mark to Market'!$B$3:$B$1028,I23,'Mark to Market'!$H$3:$H$1028) -> 0 | J25: =SUMIF('Mark to Market'!$B$3:$B$1028,J23,'Mark to Market'!$H$3:$H$1028) -> 0 | K25: =SUM(B25:J25) -> 20903567 | L25: =SUMIF('Mark to Market'!$A$3:$A$1028,"QQQ",'Mark to Market'!$H$3:$H$1028)+SUMIF('Mark to Market'!$A$3:$A$1028,"TSM",'Mark to Market'!$H$3:$H$1028)+SUMIF('Mark to Market'!$A$3:$A$1028,"NVDA",'Mark to Market'!$H$3:$H$1028) -> 0 | M25: =SUMIF('Mark to Market'!$B$3:$B$1028,M23,'Mark to Market'!$H$3:$H$1028)-(SUMIF('Mark to Market'!$A$3:$A$1028,"GLD",'Mark to Market'!$H$3:$H$1028)-SUMIF('Mark to Market'!$A$3:$A$1028,"IAUM",'Mark to Market'!$H$3:$H$1028))-SUMIF('Mark to Market'!$A$3:$A$1028,"2899",'Mark to Market'!$H$3:$H$1028) -> 0 | N25: =F25-M25 -> 0
A26: Total Weightage | B26: =B25/$K$25 -> 0 | C26: =C25/$K$25 -> 0 | D26: =D25/$K$25 -> 0 | E26: =E25/$K$25 -> 1 | F26: =F25/$K$25 -> 0 | G26: =G25/$K$25 -> 0 | H26: =H25/$K$25 -> 0 | I26: =I25/$K$25 -> 0 | J26: =J25/$K$25 -> 0 | K26: =SUM(B26:J26) -> 1 | L26: =L25/$K$25 -> 0 | M26: =M25/$K$25 -> 0 | N26: =F26-M26 -> 0
A27: Total Leverage | B27: =B25/$E$9 -> 0 | C27: =C25/$E$9 -> 0 | D27: =D25/$E$9 -> 0 | E27: =E25/$E$9 -> 0.9961162 | F27: =F25/$E$9 -> 0 | G27: =G25/$E$9 -> 0 | H27: =H25/$E$9 -> 0 | I27: =I25/$E$9 -> 0 | ... K27: =K25/$E$9 -> 0.9961162
A28: Target Allocation | L28: 0.35 | N28: 0.1
A29: Daily Return | B29: =OFFSET('Daily P&L breakdown'!B1,COUNT('Daily P&L breakdown'!$A:$A),,,) -> 0 | C29: =OFFSET('Daily P&L breakdown'!D1,COUNT('Daily P&L breakdown'!$A:$A),,,) -> 789.6 | D29: =OFFSET('Daily P&L breakdown'!C1,COUNT('Daily P&L breakdown'!$A:$A),,,) -> 0 | E29: =OFFSET('Daily P&L breakdown'!E1,COUNT('Daily P&L breakdown'!$A:$A),,,) -> 12500 | F29: =OFFSET('Daily P&L breakdown'!F1,COUNT('Daily P&L breakdown'!$A:$A),,,) -> 0 | G29: =OFFSET('Daily P&L breakdown'!G1,COUNT('Daily P&L breakdown'!$A:$A),,,) -> 0 | H29: =OFFSET('Daily P&L breakdown'!H1,COUNT('Daily P&L breakdown'!$A:$A),,,) -> 636.1 | I29: =OFFSET('Daily P&L breakdown'!I1,COUNT('Daily P&L breakdown'!$A:$A),,,) -> 0 | J29: =OFFSET('Daily P&L breakdown'!J1,COUNT('Daily P&L breakdown'!$A:$A),,,) -> 0 | K29: =SUM(B29:J29) -> 13925.7
A31: Monthly Attribution (Gross USD)
A32: Month | B32: ETFs | C32: Stocks | D32: Stocks_int | E32: Bonds | F32: Commodities | G32: Future | H32: Option | I32: Others | J32: Interest and Dividend | K32: Total | L32: checking
A33: 45658 | B33: =SUMIFS('Daily P&L breakdown'!B:B, 'Daily P&L breakdown'!$A:$A, ">=" & EOMONTH($A33, -1) + 1, 'Daily P&L breakdown'!$A:$A, "<=" & EOMONTH($A33, 0)) -> 1616679.8 | C33: =SUMIFS('Daily P&L breakdown'!D:D, 'Daily P&L breakdown'!$A:$A, ">=" & EOMONTH($A33, -1) + 1, 'Daily P&L breakdown'!$A:$A, "<=" & EOMONTH($A33, 0)) -> 227838.66 | D33: =SUMIFS('Daily P&L breakdown'!C:C, 'Daily P&L breakdown'!$A:$A, ">=" & EOMONTH($A33, -1) + 1, 'Daily P&L breakdown'!$A:$A, "<=" & EOMONTH($A33, 0)) -> 174582.75 | E33: =SUMIFS('Daily P&L breakdown'!E:E, 'Daily P&L breakdown'!$A:$A, ">=" & EOMONTH($A33, -1) + 1, 'Daily P&L breakdown'!$A:$A, "<=" & EOMONTH($A33, 0)) -> 149244.63 | F33: =SUMIFS('Daily P&L breakdown'!F:F, 'Daily P&L breakdown'!$A:$A, ">=" & EOMONTH($A33, -1) + 1, 'Daily P&L breakdown'!$A:$A, "<=" & EOMONTH($A33, 0)) -> 1307091.6 | G33: =SUMIFS('Daily P&L breakdown'!G:G, 'Daily P&L breakdown'!$A:$A, ">=" & EOMONTH($A33, -1) + 1, 'Daily P&L breakdown'!$A:$A, "<=" & EOMONTH($A33, 0)) -> 270528.75 | H33: =SUMIFS('Daily P&L breakdown'!H:H, 'Daily P&L breakdown'!$A:$A, ">=" & EOMONTH($A33, -1) + 1, 'Daily P&L breakdown'!$A:$A, "<=" & EOMONTH($A33, 0)) -> 894127.31 | I33: =SUMIFS('Daily P&L breakdown'!I:I, 'Daily P&L breakdown'!$A:$A, ">=" & EOMONTH($A33, -1) + 1, 'Daily P&L breakdown'!$A:$A, "<=" & EOMONTH($A33, 0)) -> 0 | K33: =SUM(B33:J33) -> 4640093.5 | L33: =SUM(Email!$T$9:$T$11)-K33 -> -4317812.9
A34: 45689 | B34: =SUMIFS('Daily P&L breakdown'!B:B, 'Daily P&L breakdown'!$A:$A, ">=" & EOMONTH($A34, -1) + 1, 'Daily P&L breakdown'!$A:$A, "<=" & EOMONTH($A34, 0)) -> 227.37 | C34: =SUMIFS('Daily P&L breakdown'!D:D, 'Daily P&L breakdown'!$A:$A, ">=" & EOMONTH($A34, -1) + 1, 'Daily P&L breakdown'!$A:$A, "<=" & EOMONTH($A34, 0)) -> 6715.93 | D34: =SUMIFS('Daily P&L breakdown'!C:C, 'Daily P&L breakdown'!$A:$A, ">=" & EOMONTH($A34, -1) + 1, 'Daily P&L breakdown'!$A:$A, "<=" & EOMONTH($A34, 0)) -> 0 | E34: =SUMIFS('Daily P&L breakdown'!E:E, 'Daily P&L breakdown'!$A:$A, ">=" & EOMONTH($A34, -1) + 1, 'Daily P&L breakdown'!$A:$A, "<=" & EOMONTH($A34, 0)) -> 286856.76 | F34: =SUMIFS('Daily P&L breakdown'!F:F, 'Daily P&L breakdown'!$A:$A, ">=" & EOMONTH($A34, -1) + 1, 'Daily P&L breakdown'!$A:$A, "<=" & EOMONTH($A34, 0)) -> 0 | G34: =SUMIFS('Daily P&L breakdown'!G:G, 'Daily P&L breakdown'!$A:$A, ">=" & EOMONTH($A34, -1) + 1, 'Daily P&L breakdown'!$A:$A, "<=" & EOMONTH($A34, 0)) -> 0 | H34: =SUMIFS('Daily P&L breakdown'!H:H, 'Daily P&L breakdown'!$A:$A, ">=" & EOMONTH($A34, -1) + 1, 'Daily P&L breakdown'!$A:$A, "<=" & EOMONTH($A34, 0)) -> 20303.14 | I34: =SUMIFS('Daily P&L breakdown'!I:I, 'Daily P&L breakdown'!$A:$A, ">=" & EOMONTH($A34, -1) + 1, 'Daily P&L breakdown'!$A:$A, "<=" & EOMONTH($A34, 0)) -> 0 | K34: =SUM(B34:J34) -> 314103.2
A35: 45717 | B35: =SUMIFS('Daily P&L breakdown'!B:B, 'Daily P&L breakdown'!$A:$A, ">=" & EOMONTH($A35, -1) + 1, 'Daily P&L breakdown'!$A:$A, "<=" & EOMONTH($A35, 0)) -> 0 | C35: =SUMIFS('Daily P&L breakdown'!D:D, 'Daily P&L breakdown'!$A:$A, ">=" & EOMONTH($A35, -1) + 1, 'Daily P&L breakdown'!$A:$A, "<=" & EOMONTH($A35, 0)) -> 0 | D35: =SUMIFS('Daily P&L breakdown'!C:C, 'Daily P&L breakdown'!$A:$A, ">=" & EOMONTH($A35, -1) + 1, 'Daily P&L breakdown'!$A:$A, "<=" & EOMONTH($A35, 0)) -> 0 | E35: =SUMIFS('Daily P&L breakdown'!E:E, 'Daily P&L breakdown'!$A:$A, ">=" & EOMONTH($A35, -1) + 1, 'Daily P&L breakdown'!$A:$A, "<=" & EOMONTH($A35, 0)) -> 0 | F35: =SUMIFS('Daily P&L breakdown'!F:F, 'Daily P&L breakdown'!$A:$A, ">=" & EOMONTH($A35, -1) + 1, 'Daily P&L breakdown'!$A:$A, "<=" & EOMONTH($A35, 0)) -> 0 | G35: =SUMIFS('Daily P&L breakdown'!G:G, 'Daily P&L breakdown'!$A:$A, ">=" & EOMONTH($A35, -1) + 1, 'Daily P&L breakdown'!$A:$A, "<=" & EOMONTH($A35, 0)) -> 0 | H35: =SUMIFS('Daily P&L breakdown'!H:H, 'Daily P&L breakdown'!$A:$A, ">=" & EOMONTH($A35, -1) + 1, 'Daily P&L breakdown'!$A:$A, "<=" & EOMONTH($A35, 0)) -> 0 | I35: =SUMIFS('Daily P&L breakdown'!I:I, 'Daily P&L breakdown'!$A:$A, ">=" & EOMONTH($A35, -1) + 1, 'Daily P&L breakdown'!$A:$A, "<=" & EOMONTH($A35, 0)) -> 0 | K35: =SUM(B35:J35) -> 0
A36: 45748 | B36: =SUMIFS('Daily P&L breakdown'!B:B, 'Daily P&L breakdown'!$A:$A, ">=" & EOMONTH($A36, -1) + 1, 'Daily P&L breakdown'!$A:$A, "<=" & EOMONTH($A36, 0)) -> 0 | C36: =SUMIFS('Daily P&L breakdown'!D:D, 'Daily P&L breakdown'!$A:$A, ">=" & EOMONTH($A36, -1) + 1, 'Daily P&L breakdown'!$A:$A, "<=" & EOMONTH($A36, 0)) -> 0 | D36: =SUMIFS('Daily P&L breakdown'!C:C, 'Daily P&L breakdown'!$A:$A, ">=" & EOMONTH($A36, -1) + 1, 'Daily P&L breakdown'!$A:$A, "<=" & EOMONTH($A36, 0)) -> 0 | E36: =SUMIFS('Daily P&L breakdown'!E:E, 'Daily P&L breakdown'!$A:$A, ">=" & EOMONTH($A36, -1) + 1, 'Daily P&L breakdown'!$A:$A, "<=" & EOMONTH($A36, 0)) -> 0 | F36: =SUMIFS('Daily P&L breakdown'!F:F, 'Daily P&L breakdown'!$A:$A, ">=" & EOMONTH($A36, -1) + 1, 'Daily P&L breakdown'!$A:$A, "<=" & EOMONTH($A36, 0)) -> 0 | G36: =SUMIFS('Daily P&L breakdown'!G:G, 'Daily P&L breakdown'!$A:$A, ">=" & EOMONTH($A36, -1) + 1, 'Daily P&L breakdown'!$A:$A, "<=" & EOMONTH($A36, 0)) -> 0 | H36: =SUMIFS('Daily P&L breakdown'!H:H, 'Daily P&L breakdown'!$A:$A, ">=" & EOMONTH($A36, -1) + 1, 'Daily P&L breakdown'!$A:$A, "<=" & EOMONTH($A36, 0)) -> 0 | I36: =SUMIFS('Daily P&L breakdown'!I:I, 'Daily P&L breakdown'!$A:$A, ">=" & EOMONTH($A36, -1) + 1, 'Daily P&L breakdown'!$A:$A, "<=" & EOMONTH($A36, 0)) -> 0 | K36: =SUM(B36:J36) -> 0
A37: 45778 | B37: =SUMIFS('Daily P&L breakdown'!B:B, 'Daily P&L breakdown'!$A:$A, ">=" & EOMONTH($A37, -1) + 1, 'Daily P&L breakdown'!$A:$A, "<=" & EOMONTH($A37, 0)) -> 0 | C37: =SUMIFS('Daily P&L breakdown'!D:D, 'Daily P&L breakdown'!$A:$A, ">=" & EOMONTH($A37, -1) + 1, 'Daily P&L breakdown'!$A:$A, "<=" & EOMONTH($A37, 0)) -> 0 | D37: =SUMIFS('Daily P&L breakdown'!C:C, 'Daily P&L breakdown'!$A:$A, ">=" & EOMONTH($A37, -1) + 1, 'Daily P&L breakdown'!$A:$A, "<=" & EOMONTH($A37, 0)) -> 0 | E37: =SUMIFS('Daily P&L breakdown'!E:E, 'Daily P&L breakdown'!$A:$A, ">=" & EOMONTH($A37, -1) + 1, 'Daily P&L breakdown'!$A:$A, "<=" & EOMONTH($A37, 0)) -> 0 | F37: =SUMIFS('Daily P&L breakdown'!F:F, 'Daily P&L breakdown'!$A:$A, ">=" & EOMONTH($A37, -1) + 1, 'Daily P&L breakdown'!$A:$A, "<=" & EOMONTH($A37, 0)) -> 0 | G37: =SUMIFS('Daily P&L breakdown'!G:G, 'Daily P&L breakdown'!$A:$A, ">=" & EOMONTH($A37, -1) + 1, 'Daily P&L breakdown'!$A:$A, "<=" & EOMONTH($A37, 0)) -> 0 | H37: =SUMIFS('Daily P&L breakdown'!H:H, 'Daily P&L breakdown'!$A:$A, ">=" & EOMONTH($A37, -1) + 1, 'Daily P&L breakdown'!$A:$A, "<=" & EOMONTH($A37, 0)) -> 0 | I37: =SUMIFS('Daily P&L breakdown'!I:I, 'Daily P&L breakdown'!$A:$A, ">=" & EOMONTH($A37, -1) + 1, 'Daily P&L breakdown'!$A:$A, "<=" & EOMONTH($A37, 0)) -> 0 | K37: =SUM(B37:J37) -> 0
A38: 45809 | B38: =SUMIFS('Daily P&L breakdown'!B:B, 'Daily P&L breakdown'!$A:$A, ">=" & EOMONTH($A38, -1) + 1, 'Daily P&L breakdown'!$A:$A, "<=" & EOMONTH($A38, 0)) -> 0 | C38: =SUMIFS('Daily P&L breakdown'!D:D, 'Daily P&L breakdown'!$A:$A, ">=" & EOMONTH($A38, -1) + 1, 'Daily P&L breakdown'!$A:$A, "<=" & EOMONTH($A38, 0)) -> 0 | D38: =SUMIFS('Daily P&L breakdown'!C:C, 'Daily P&L breakdown'!$A:$A, ">=" & EOMONTH($A38, -1) + 1, 'Daily P&L breakdown'!$A:$A, "<=" & EOMONTH($A38, 0)) -> 0 | E38: =SUMIFS('Daily P&L breakdown'!E:E, 'Daily P&L breakdown'!$A:$A, ">=" & EOMONTH($A38, -1) + 1, 'Daily P&L breakdown'!$A:$A, "<=" & EOMONTH($A38, 0)) -> 0 | F38: =SUMIFS('Daily P&L breakdown'!F:F, 'Daily P&L breakdown'!$A:$A, ">=" & EOMONTH($A38, -1) + 1, 'Daily P&L breakdown'!$A:$A, "<=" & EOMONTH($A38, 0)) -> 0 | G38: =SUMIFS('Daily P&L breakdown'!G:G, 'Daily P&L breakdown'!$A:$A, ">=" & EOMONTH($A38, -1) + 1, 'Daily P&L breakdown'!$A:$A, "<=" & EOMONTH($A38, 0)) -> 0 | H38: =SUMIFS('Daily P&L breakdown'!H:H, 'Daily P&L breakdown'!$A:$A, ">=" & EOMONTH($A38, -1) + 1, 'Daily P&L breakdown'!$A:$A, "<=" & EOMONTH($A38, 0)) -> 0 | I38: =SUMIFS('Daily P&L breakdown'!I:I, 'Daily P&L breakdown'!$A:$A, ">=" & EOMONTH($A38, -1) + 1, 'Daily P&L breakdown'!$A:$A, "<=" & EOMONTH($A38, 0)) -> 0 | K38: =SUM(B38:J38) -> 0
A39: 45839 | B39: =SUMIFS('Daily P&L breakdown'!B:B, 'Daily P&L breakdown'!$A:$A, ">=" & EOMONTH($A39, -1) + 1, 'Daily P&L breakdown'!$A:$A, "<=" & EOMONTH($A39, 0)) -> 0 | C39: =SUMIFS('Daily P&L breakdown'!D:D, 'Daily P&L breakdown'!$A:$A, ">=" & EOMONTH($A39, -1) + 1, 'Daily P&L breakdown'!$A:$A, "<=" & EOMONTH($A39, 0)) -> 0 | D39: =SUMIFS('Daily P&L breakdown'!C:C, 'Daily P&L breakdown'!$A:$A, ">=" & EOMONTH($A39, -1) + 1, 'Daily P&L breakdown'!$A:$A, "<=" & EOMONTH($A39, 0)) -> 0 | E39: =SUMIFS('Daily P&L breakdown'!E:E, 'Daily P&L breakdown'!$A:$A, ">=" & EOMONTH($A39, -1) + 1, 'Daily P&L breakdown'!$A:$A, "<=" & EOMONTH($A39, 0)) -> 0 | F39: =SUMIFS('Daily P&L breakdown'!F:F, 'Daily P&L breakdown'!$A:$A, ">=" & EOMONTH($A39, -1) + 1, 'Daily P&L breakdown'!$A:$A, "<=" & EOMONTH($A39, 0)) -> 0 | G39: =SUMIFS('Daily P&L breakdown'!G:G, 'Daily P&L breakdown'!$A:$A, ">=" & EOMONTH($A39, -1) + 1, 'Daily P&L breakdown'!$A:$A, "<=" & EOMONTH($A39, 0)) -> 0 | H39: =SUMIFS('Daily P&L breakdown'!H:H, 'Daily P&L breakdown'!$A:$A, ">=" & EOMONTH($A39, -1) + 1, 'Daily P&L breakdown'!$A:$A, "<=" & EOMONTH($A39, 0)) -> 0 | I39: =SUMIFS('Daily P&L breakdown'!I:I, 'Daily P&L breakdown'!$A:$A, ">=" & EOMONTH($A39, -1) + 1, 'Daily P&L breakdown'!$A:$A, "<=" & EOMONTH($A39, 0)) -> 0 | K39: =SUM(B39:J39) -> 0
A40: 45870 | B40: =SUMIFS('Daily P&L breakdown'!B:B, 'Daily P&L breakdown'!$A:$A, ">=" & EOMONTH($A40, -1) + 1, 'Daily P&L breakdown'!$A:$A, "<=" & EOMONTH($A40, 0)) -> 0 | C40: =SUMIFS('Daily P&L breakdown'!D:D, 'Daily P&L breakdown'!$A:$A, ">=" & EOMONTH($A40, -1) + 1, 'Daily P&L breakdown'!$A:$A, "<=" & EOMONTH($A40, 0)) -> 0 | D40: =SUMIFS('Daily P&L breakdown'!C:C, 'Daily P&L breakdown'!$A:$A, ">=" & EOMONTH($A40, -1) + 1, 'Daily P&L breakdown'!$A:$A, "<=" & EOMONTH($A40, 0)) -> 0 | E40: =SUMIFS('Daily P&L breakdown'!E:E, 'Daily P&L breakdown'!$A:$A, ">=" & EOMONTH($A40, -1) + 1, 'Daily P&L breakdown'!$A:$A, "<=" & EOMONTH($A40, 0)) -> 0 | F40: =SUMIFS('Daily P&L breakdown'!F:F, 'Daily P&L breakdown'!$A:$A, ">=" & EOMONTH($A40, -1) + 1, 'Daily P&L breakdown'!$A:$A, "<=" & EOMONTH($A40, 0)) -> 0 | G40: =SUMIFS('Daily P&L breakdown'!G:G, 'Daily P&L breakdown'!$A:$A, ">=" & EOMONTH($A40, -1) + 1, 'Daily P&L breakdown'!$A:$A, "<=" & EOMONTH($A40, 0)) -> 0 | H40: =SUMIFS('Daily P&L breakdown'!H:H, 'Daily P&L breakdown'!$A:$A, ">=" & EOMONTH($A40, -1) + 1, 'Daily P&L breakdown'!$A:$A, "<=" & EOMONTH($A40, 0)) -> 0 | I40: =SUMIFS('Daily P&L breakdown'!I:I, 'Daily P&L breakdown'!$A:$A, ">=" & EOMONTH($A40, -1) + 1, 'Daily P&L breakdown'!$A:$A, "<=" & EOMONTH($A40, 0)) -> 0 | K40: =SUM(B40:J40) -> 0
A41: 45901 | B41: =SUMIFS('Daily P&L breakdown'!B:B, 'Daily P&L breakdown'!$A:$A, ">=" & EOMONTH($A41, -1) + 1, 'Daily P&L breakdown'!$A:$A, "<=" & EOMONTH($A41, 0)) -> 0 | C41: =SUMIFS('Daily P&L breakdown'!D:D, 'Daily P&L breakdown'!$A:$A, ">=" & EOMONTH($A41, -1) + 1, 'Daily P&L breakdown'!$A:$A, "<=" & EOMONTH($A41, 0)) -> 0 | D41: =SUMIFS('Daily P&L breakdown'!C:C, 'Daily P&L breakdown'!$A:$A, ">=" & EOMONTH($A41, -1) + 1, 'Daily P&L breakdown'!$A:$A, "<=" & EOMONTH($A41, 0)) -> 0 | E41: =SUMIFS('Daily P&L breakdown'!E:E, 'Daily P&L breakdown'!$A:$A, ">=" & EOMONTH($A41, -1) + 1, 'Daily P&L breakdown'!$A:$A, "<=" & EOMONTH($A41, 0)) -> 0 | F41: =SUMIFS('Daily P&L breakdown'!F:F, 'Daily P&L breakdown'!$A:$A, ">=" & EOMONTH($A41, -1) + 1, 'Daily P&L breakdown'!$A:$A, "<=" & EOMONTH($A41, 0)) -> 0 | G41: =SUMIFS('Daily P&L breakdown'!G:G, 'Daily P&L breakdown'!$A:$A, ">=" & EOMONTH($A41, -1) + 1, 'Daily P&L breakdown'!$A:$A, "<=" & EOMONTH($A41, 0)) -> 0 | H41: =SUMIFS('Daily P&L breakdown'!H:H, 'Daily P&L breakdown'!$A:$A, ">=" & EOMONTH($A41, -1) + 1, 'Daily P&L breakdown'!$A:$A, "<=" & EOMONTH($A41, 0)) -> 0 | I41: =SUMIFS('Daily P&L breakdown'!I:I, 'Daily P&L breakdown'!$A:$A, ">=" & EOMONTH($A41, -1) + 1, 'Daily P&L breakdown'!$A:$A, "<=" & EOMONTH($A41, 0)) -> 0 | K41: =SUM(B41:J41) -> 0
A42: 45931 | B42: =SUMIFS('Daily P&L breakdown'!B:B, 'Daily P&L breakdown'!$A:$A, ">=" & EOMONTH($A42, -1) + 1, 'Daily P&L breakdown'!$A:$A, "<=" & EOMONTH($A42, 0)) -> 0 | C42: =SUMIFS('Daily P&L breakdown'!D:D, 'Daily P&L breakdown'!$A:$A, ">=" & EOMONTH($A42, -1) + 1, 'Daily P&L breakdown'!$A:$A, "<=" & EOMONTH($A42, 0)) -> 0 | D42: =SUMIFS('Daily P&L breakdown'!C:C, 'Daily P&L breakdown'!$A:$A, ">=" & EOMONTH($A42, -1) + 1, 'Daily P&L breakdown'!$A:$A, "<=" & EOMONTH($A42, 0)) -> 0 | E42: =SUMIFS('Daily P&L breakdown'!E:E, 'Daily P&L breakdown'!$A:$A, ">=" & EOMONTH($A42, -1) + 1, 'Daily P&L breakdown'!$A:$A, "<=" & EOMONTH($A42, 0)) -> 0 | F42: =SUMIFS('Daily P&L breakdown'!F:F, 'Daily P&L breakdown'!$A:$A, ">=" & EOMONTH($A42, -1) + 1, 'Daily P&L breakdown'!$A:$A, "<=" & EOMONTH($A42, 0)) -> 0 | G42: =SUMIFS('Daily P&L breakdown'!G:G, 'Daily P&L breakdown'!$A:$A, ">=" & EOMONTH($A42, -1) + 1, 'Daily P&L breakdown'!$A:$A, "<=" & EOMONTH($A42, 0)) -> 0 | H42: =SUMIFS('Daily P&L breakdown'!H:H, 'Daily P&L breakdown'!$A:$A, ">=" & EOMONTH($A42, -1) + 1, 'Daily P&L breakdown'!$A:$A, "<=" & EOMONTH($A42, 0)) -> 0 | I42: =SUMIFS('Daily P&L breakdown'!I:I, 'Daily P&L breakdown'!$A:$A, ">=" & EOMONTH($A42, -1) + 1, 'Daily P&L breakdown'!$A:$A, "<=" & EOMONTH($A42, 0)) -> 0 | K42: =SUM(B42:J42) -> 0
A43: 45962 | B43: =SUMIFS('Daily P&L breakdown'!B:B, 'Daily P&L breakdown'!$A:$A, ">=" & EOMONTH($A43, -1) + 1, 'Daily P&L breakdown'!$A:$A, "<=" & EOMONTH($A43, 0)) -> 0 | C43: =SUMIFS('Daily P&L breakdown'!D:D, 'Daily P&L breakdown'!$A:$A, ">=" & EOMONTH($A43, -1) + 1, 'Daily P&L breakdown'!$A:$A, "<=" & EOMONTH($A43, 0)) -> 0 | D43: =SUMIFS('Daily P&L breakdown'!C:C, 'Daily P&L breakdown'!$A:$A, ">=" & EOMONTH($A43, -1) + 1, 'Daily P&L breakdown'!$A:$A, "<=" & EOMONTH($A43, 0)) -> 0 | E43: =SUMIFS('Daily P&L breakdown'!E:E, 'Daily P&L breakdown'!$A:$A, ">=" & EOMONTH($A43, -1) + 1, 'Daily P&L breakdown'!$A:$A, "<=" & EOMONTH($A43, 0)) -> 0 | F43: =SUMIFS('Daily P&L breakdown'!F:F, 'Daily P&L breakdown'!$A:$A, ">=" & EOMONTH($A43, -1) + 1, 'Daily P&L breakdown'!$A:$A, "<=" & EOMONTH($A43, 0)) -> 0 | G43: =SUMIFS('Daily P&L breakdown'!G:G, 'Daily P&L breakdown'!$A:$A, ">=" & EOMONTH($A43, -1) + 1, 'Daily P&L breakdown'!$A:$A, "<=" & EOMONTH($A43, 0)) -> 0 | H43: =SUMIFS('Daily P&L breakdown'!H:H, 'Daily P&L breakdown'!$A:$A, ">=" & EOMONTH($A43, -1) + 1, 'Daily P&L breakdown'!$A:$A, "<=" & EOMONTH($A43, 0)) -> 0 | I43: =SUMIFS('Daily P&L breakdown'!I:I, 'Daily P&L breakdown'!$A:$A, ">=" & EOMONTH($A43, -1) + 1, 'Daily P&L breakdown'!$A:$A, "<=" & EOMONTH($A43, 0)) -> 0 | K43: =SUM(B43:J43) -> 0
A44: 45992 | B44: =SUMIFS('Daily P&L breakdown'!B:B, 'Daily P&L breakdown'!$A:$A, ">=" & EOMONTH($A44, -1) + 1, 'Daily P&L breakdown'!$A:$A, "<=" & EOMONTH($A44, 0)) -> 0 | C44: =SUMIFS('Daily P&L breakdown'!D:D, 'Daily P&L breakdown'!$A:$A, ">=" & EOMONTH($A44, -1) + 1, 'Daily P&L breakdown'!$A:$A, "<=" & EOMONTH($A44, 0)) -> 0 | D44: =SUMIFS('Daily P&L breakdown'!C:C, 'Daily P&L breakdown'!$A:$A, ">=" & EOMONTH($A44, -1) + 1, 'Daily P&L breakdown'!$A:$A, "<=" & EOMONTH($A44, 0)) -> 0 | E44: =SUMIFS('Daily P&L breakdown'!E:E, 'Daily P&L breakdown'!$A:$A, ">=" & EOMONTH($A44, -1) + 1, 'Daily P&L breakdown'!$A:$A, "<=" & EOMONTH($A44, 0)) -> 0 | F44: =SUMIFS('Daily P&L breakdown'!F:F, 'Daily P&L breakdown'!$A:$A, ">=" & EOMONTH($A44, -1) + 1, 'Daily P&L breakdown'!$A:$A, "<=" & EOMONTH($A44, 0)) -> 0 | G44: =SUMIFS('Daily P&L breakdown'!G:G, 'Daily P&L breakdown'!$A:$A, ">=" & EOMONTH($A44, -1) + 1, 'Daily P&L breakdown'!$A:$A, "<=" & EOMONTH($A44, 0)) -> 0 | H44: =SUMIFS('Daily P&L breakdown'!H:H, 'Daily P&L breakdown'!$A:$A, ">=" & EOMONTH($A44, -1) + 1, 'Daily P&L breakdown'!$A:$A, "<=" & EOMONTH($A44, 0)) -> 0 | I44: =SUMIFS('Daily P&L breakdown'!I:I, 'Daily P&L breakdown'!$A:$A, ">=" & EOMONTH($A44, -1) + 1, 'Daily P&L breakdown'!$A:$A, "<=" & EOMONTH($A44, 0)) -> 0 | K44: =SUM(B44:J44) -> 0
A45: FY2025 | B45: =SUM(B33:B44) -> 1616907.2 | C45: =SUM(C33:C44) -> 234554.59 | D45: =SUM(D33:D44) -> 174582.75 | E45: =SUM(E33:E44) -> 436101.39 | F45: =SUM(F33:F44) -> 1307091.6 | G45: =SUM(G33:G44) -> 270528.75 | H45: =SUM(H33:H44) -> 914430.45 | I45: =SUM(I33:I44) -> 0 | ... K45: =SUM(K33:K44) -> 4954196.7
A46: FY2024 | B46: 4163680.5 | C46: 7118183.3 | D46: 1475451.6 | E46: -2096198.1 | F46: 749546.29 | G46: 5605745.8 | H46: 7949499.7 | I46: 0 | J46: -6960481.4 | K46: 18005428
A48: Monthly Attribution (Gross %)
A49: Month | B49: ETFs | C49: Stocks | D49: Stocks_int | E49: Bonds | F49: Commodities | G49: Future | H49: Option | I49: Others | J49: Interest and Dividend | K49: Total
A50: 45658 | B50: =B33/'Historical NAV'!$B$1169 -> 0.025557946 | C50: =C33/'Historical NAV'!$B$1169 -> 0.003601881 | D50: =D33/'Historical NAV'!$B$1169 -> 0.002759963 | E50: =E33/'Historical NAV'!$B$1169 -> 0.002359395 | F50: =F33/'Historical NAV'!$B$1169 -> 0.020663694 | G50: =G33/'Historical NAV'!$B$1169 -> 0.0042767648 | H50: =H33/'Historical NAV'!$B$1169 -> 0.014135178 | I50: =I33/'Historical NAV'!$B$1169 -> 0 | ... K50: =K33/'Historical NAV'!$B$1169 -> 0.073354822
A51: 45689 | B51: =B34/'Historical NAV'!$B$1191 -> 3.4291893e-06 | C51: =C34/'Historical NAV'!$B$1191 -> 0.00010128951 | D51: =D34/'Historical NAV'!$B$1191 -> 0 | E51: =E34/'Historical NAV'!$B$1191 -> 0.0043263673 | F51: =F34/'Historical NAV'!$B$1191 -> 0 | G51: =G34/'Historical NAV'!$B$1191 -> 0 | H51: =H34/'Historical NAV'!$B$1191 -> 0.00030621151 | I51: =I34/'Historical NAV'!$B$1191 -> 0 | ... K51: =K34/'Historical NAV'!$B$1191 -> 0.0047372975
A52: 45717
A53: 45748
A54: 45778
A55: 45809
A56: 45839
A57: 45870
A58: 45901
A59: 45931
A60: 45962
A61: 45992
A62: FY2025

Sheet Historical NAV
A1: DATE | B1: NAV (USD) | C1: CASH INJECTION | D1: NEXT START NAV | E1: M START NAV | F1: DAILY P&L | G1: Daily Return | H1: Weekly P&L | I1: Weekly Return | J1: MTD Change | K1: MTD % | L1: Cal | M1: LTD ROR% | N1: YTD ROR% | O1: Annualised Return | P1: Annualised Volatility | Q1: 30 Days P&L | R1: 30 Days Return | S1: 90 Days P&L | T1: 90 Days Return | U1: 365 Days P&L | V1: 365 Days Return | W1: Sharpe Ratio | X1: Risk Free Rate (Assumed 4.5%) | Y1: Excess Return | Z1: Negative Excess Returns | AA1: Square of (Negative Excess Returns) | AB1: Sotino Ratio | AC1: Value at Risk 95%(30days) | AD1: Value at Risk 95%(90days) | AE1: Value at Risk 95%(365days)
A2: 44013 | B2: 8106215.1 | D2: 8106215.1 | E2: 8129676.1 | F2: -23460.98 | G2: -0.0028858444 | J2: -23460.98 | K2: -0.0028858444 | L2: =1+G2 -> 0.99711416 | M2: =PRODUCT($L$2:L2)-1 -> -0.0028858444 | N2: =PRODUCT($L2:L$2)-1 -> -0.0028858444 | O2: =AVERAGE($G2:G$2)*252 -> -0.72723278 | P2: =STDEV($G2:G$2)*252^0.5 -> #DIV/0!
A3: 44014 | B3: 8174039.8 | D3: =B3 -> 8174039.8 | E3: =E2 -> 8129676.1 | F3: 67824.64 | G3: 0.0083669924 | J3: 44363.66 | K3: 0.0054570021 | L3: =1+G3 -> 1.008367 | M3: =PRODUCT($L$2:L3)-1 -> 0.0054570021 | N3: =PRODUCT($L$2:L3)-1 -> 0.0054570021 | O3: =AVERAGE($G$2:G3)*252 -> 0.69062465 | P3: =STDEV($G$2:G3)*252^0.5 -> 0.12631278
A4: 44018 | B4: 8297117.3 | D4: =B4 -> 8297117.3 | E4: =E3 -> 8129676.1 | F4: 123077.55 | G4: 0.015057126 | J4: 167441.21 | K4: 0.020596295 | L4: =1+G4 -> 1.0150571 | M4: =PRODUCT($L$2:L4)-1 -> 0.020596295 | N4: =PRODUCT($L$2:L4)-1 -> 0.020596295 | O4: =AVERAGE($G$2:G4)*252 -> 1.725215 | P4: =STDEV($G$2:G4)*252^0.5 -> 0.14394459
A5: 44019 | B5: 8333268.5 | D5: =B5 -> 8333268.5 | E5: =E4 -> 8129676.1 | F5: 36151.23 | G5: 0.0043570831 | J5: 203592.44 | K5: 0.025043118 | L5: =1+G5 -> 1.0043571 | M5: =PRODUCT($L$2:L5)-1 -> 0.025043118 | N5: =PRODUCT($L$2:L5)-1 -> 0.025043118 | O5: =AVERAGE($G$2:G5)*252 -> 1.5684075 | P5: =STDEV($G$2:G5)*252^0.5 -> 0.11917911
A6: 44020 | B6: 8402868.6 | D6: =B6 -> 8402868.6 | E6: =E5 -> 8129676.1 | F6: 69600.06 | G6: 0.0083520721 | J6: 273192.5 | K6: 0.033604352 | L6: =1+G6 -> 1.0083521 | M6: =PRODUCT($L$2:L6)-1 -> 0.033604352 | N6: =PRODUCT($L$2:L6)-1 -> 0.033604352 | O6: =AVERAGE($G$2:G6)*252 -> 1.6756705 | P6: =STDEV($G$2:G6)*252^0.5 -> 0.10431215
A7: 44021 | B7: 8486246.5 | D7: =B7 -> 8486246.5 | E7: =E6 -> 8129676.1 | F7: 83377.92 | G7: 0.0099225543 | J7: 356570.42 | K7: 0.043860348 | L7: =1+G7 -> 1.0099226 | M7: =PRODUCT($L$2:L7)-1 -> 0.043860348 | N7: =PRODUCT($L$2:L7)-1 -> 0.043860348 | O7: =AVERAGE($G$2:G7)*252 -> 1.8131393 | P7: =STDEV($G$2:G7)*252^0.5 -> 0.095680536
A8: 44025 | B8: 8403900.2 | D8: =B8 -> 8403900.2 | E8: =E7 -> 8129676.1 | F8: -82346.35 | G8: -0.0097035067 | J8: 274224.07 | K8: 0.033731242 | L8: =1+G8 -> 0.99029649 | M8: =PRODUCT($L$2:L8)-1 -> 0.033731242 | N8: =PRODUCT($L$2:L8)-1 -> 0.033731242 | O8: =AVERAGE($G$2:G8)*252 -> 1.2047932 | P8: =STDEV($G$2:G8)*252^0.5 -> 0.13382492
A9: 44026 | B9: 8483233.3 | D9: =B9 -> 8483233.3 | E9: =E8 -> 8129676.1 | F9: 79333.16 | G9: 0.0094400407 | J9: 353557.23 | K9: 0.043489707 | L9: =1+G9 -> 1.00944 | M9: =PRODUCT($L$2:L9)-1 -> 0.043489707 | N9: =PRODUCT($L$2:L9)-1 -> 0.043489707 | O9: =AVERAGE($G$2:G9)*252 -> 1.3515553 | P9: =STDEV($G$2:G9)*252^0.5 -> 0.1266272
A10: 44027 | B10: 8478930.9 | D10: =B10 -> 8478930.9 | E10: =E9 -> 8129676.1 | F10: -4302.43 | G10: -0.00050716865 | J10: 349254.8 | K10: 0.042960481 | L10: =1+G10 -> 0.99949283 | M10: =PRODUCT($L$2:L10)-1 -> 0.042960481 | N10: =PRODUCT($L$2:L10)-1 -> 0.042960481 | O10: =AVERAGE($G$2:G10)*252 -> 1.1871818 | P10: =STDEV($G$2:G10)*252^0.5 -> 0.12245446
A11: 44028 | B11: 8434812.8 | D11: =B11 -> 8434812.8 | E11: =E9 -> 8129676.1 | F11: -44118.11 | G11: -0.0052006244 | J11: 305136.69 | K11: 0.037533683 | L11: =1+G11 -> 0.99479938 | M11: =PRODUCT($L$2:L11)-1 -> 0.037536436 | N11: =PRODUCT($L$2:L11)-1 -> 0.037536436 | O11: =AVERAGE($G$2:G11)*252 -> 0.93740787 | P11: =STDEV($G$2:G11)*252^0.5 -> 0.12571654
A12: 44029 | B12: 8475481.8 | D12: =B12 -> 8475481.8 | E12: =E11 -> 8129676.1 | F12: 40668.96 | G12: 0.0048215605 | J12: 345805.65 | K12: 0.042536215 | L12: =1+G12 -> 1.0048216 | M12: =PRODUCT($L$2:L12)-1 -> 0.04253898 | N12: =PRODUCT($L$2:L12)-1 -> 0.04253898 | O12: =AVERAGE($G$2:G12)*252 -> 0.96264654 | P12: =STDEV($G$2:G12)*252^0.5 -> 0.11938169
A13: 44032 | B13: 7795603.9 | C13: -800000 | D13: =B13 -> 7795603.9 | E13: =E12 -> 8129676.1 | F13: 120122.1 | G13: 0.0157 | J13: -334072.25 | K13: 0.0589 | L13: =1+G13 -> 1.0157 | M13: =PRODUCT($L$2:L13)-1 -> 0.058906842 | N13: =PRODUCT($L$2:L13)-1 -> 0.058906842 | O13: =AVERAGE($G$2:G13)*252 -> 1.212126 | P13: =STDEV($G$2:G13)*252^0.5 -> 0.12617512
A14: 44033 | B14: 7768360.5 | D14: =B14 -> 7768360.5 | E14: =E13+C13 -> 7329676.1 | F14: -27243.35 | G14: -0.0034947068 | J14: 438684.4 | K14: 0.0552 | L14: =1+G14 -> 0.99650529 | M14: =PRODUCT($L$2:L14)-1 -> 0.055206273 | N14: =PRODUCT($L$2:L14)-1 -> 0.055206273 | O14: =AVERAGE($G$2:G14)*252 -> 1.051142 | P14: =STDEV($G$2:G14)*252^0.5 -> 0.12621573
A15: 44034 | B15: 7803379.3 | D15: =B15 -> 7803379.3 | E15: =E14 -> 7329676.1 | F15: 35018.83 | G15: 0.0045078791 | J15: 473703.23 | K15: 0.0599 | L15: =1+G15 -> 1.0045079 | M15: =PRODUCT($L$2:L15)-1 -> 0.059963016 | N15: =PRODUCT($L$2:L15)-1 -> 0.059963016 | O15: =AVERAGE($G$2:G15)*252 -> 1.0572022 | P15: =STDEV($G$2:G15)*252^0.5 -> 0.12127256
A16: 44035 | B16: 7757505.2 | D16: =B16 -> 7757505.2 | E16: 7362157.3 | F16: -45874.16 | G16: -0.0058787556 | J16: 395347.85 | K16: 0.0537 | L16: =1+G16 -> 0.99412124 | M16: =PRODUCT($L$2:L16)-1 -> 0.053731752 | N16: =PRODUCT($L$2:L16)-1 -> 0.053731752 | O16: =AVERAGE($G$2:G16)*252 -> 0.887959 | P16: =STDEV($G$2:G16)*252^0.5 -> 0.12394147
A17: 44036 | B17: 7718043 | D17: =B17 -> 7718043 | E17: =E16 -> 7362157.3 | F17: -39462.22 | G17: -0.0050869731 | J17: 355885.63 | K17: 0.048339856 | L17: =1+G17 -> 0.99491303 | M17: =PRODUCT($L$2:L17)-1 -> 0.048371447 | N17: =PRODUCT($L$2:L17)-1 -> 0.048371447 | O17: =AVERAGE($G$2:G17)*252 -> 0.75234173 | P17: =STDEV($G$2:G17)*252^0.5 -> 0.12451963
A18: 44039 | B18: 7848768.5 | D18: =B18 -> 7848768.5 | E18: =E17 -> 7362157.3 | F18: 130725.52 | G18: 0.016937651 | J18: 486611.15 | K18: 0.066096271 | L18: =1+G18 -> 1.0169377 | M18: =PRODUCT($L$2:L18)-1 -> 0.066128397 | N18: =PRODUCT($L$2:L18)-1 -> 0.066128397 | O18: =AVERAGE($G$2:G18)*252 -> 0.95916211 | P18: =STDEV($G$2:G18)*252^0.5 -> 0.13199114
A19: 44040 | B19: 7829336.3 | D19: =B19 -> 7829336.3 | E19: =E18 -> 7362157.3 | F19: -19432.15 | G19: -0.0024758215 | J19: 467179 | K19: 0.0634 | L19: =1+G19 -> 0.99752418 | M19: =PRODUCT($L$2:L19)-1 -> 0.063488854 | N19: =PRODUCT($L$2:L19)-1 -> 0.063488854 | O19: =AVERAGE($G$2:G19)*252 -> 0.87121382 | P19: =STDEV($G$2:G19)*252^0.5 -> 0.13018967
A20: 44041 | B20: 7899344.2 | D20: =B20 -> 7899344.2 | E20: =E19 -> 7362157.3 | F20: 70007.84 | G20: 0.0089417336 | J20: 537186.84 | K20: 0.0729 | L20: =1+G20 -> 1.0089417 | M20: =PRODUCT($L$2:L20)-1 -> 0.072998288 | N20: =PRODUCT($L$2:L20)-1 -> 0.072998288 | O20: =AVERAGE($G$2:G20)*252 -> 0.94395609 | P20: =STDEV($G$2:G20)*252^0.5 -> 0.12808855
A21: 44043 | B21: 8019590.3 | D21: =B21 -> 8019590.3 | E21: =E20 -> 7362157.3 | F21: 120149.88 | G21: 0.015210108 | J21: 657336.72 | K21: 0.089285883 | L21: =1+G21 -> 1.0152101 | M21: =PRODUCT($L$2:L21)-1 -> 0.089318708 | N21: =PRODUCT($L$2:L21)-1 -> 0.089318708 | O21: =AVERAGE($G$2:G21)*252 -> 1.0884056 | P21: =STDEV($G$2:G21)*252^0.5 -> 0.13114562
A22: 44046 | B22: 8080929.5 | D22: =B22 -> 8080929.5 | E22: =IF(MONTH(A22)=MONTH(A21),E21,D21) -> 8019590.3 | F22: =B22-C22-D21 -> 61339.18 | G22: =F22/B21 -> 0.0076486675 | J22: =IF(MONTH(A22)=MONTH(A21),J21+F22,F22) -> 61339.18 | K22: =J22/E22 -> 0.0076486675 | L22: =1+G22 -> 1.0076487 | M22: =PRODUCT($L$2:L22)-1 -> 0.097650544 | N22: =PRODUCT($L$2:L22)-1 -> 0.097650544 | O22: =AVERAGE($G$2:G22)*252 -> 1.1283608 | P22: =STDEV($G$2:G22)*252^0.5 -> 0.12834426
A23: 44047 | B23: 8290234 | D23: =B23 -> 8290234 | E23: =IF(MONTH(A23)=MONTH(A22),E22,D22) -> 8019590.3 | F23: =B23-C23-D22 -> 209304.52 | G23: =F23/B22 -> 0.025901045 | J23: =IF(MONTH(A23)=MONTH(A22),J22+F23,F23) -> 270643.7 | K23: =J23/E23 -> 0.033747821 | L23: =1+G23 -> 1.025901 | M23: =PRODUCT($L$2:L23)-1 -> 0.12608084 | N23: =PRODUCT($L$2:L23)-1 -> 0.12608084 | O23: =AVERAGE($G$2:G23)*252 -> 1.3737564 | P23: =STDEV($G$2:G23)*252^0.5 -> 0.14472412
A24: 44048 | B24: 8397007.3 | D24: =B24 -> 8397007.3 | E24: =IF(MONTH(A24)=MONTH(A23),E23,D23) -> 8019590.3 | F24: =B24-C24-D23 -> 106773.3 | G24: =F24/B23 -> 0.012879407 | J24: =IF(MONTH(A24)=MONTH(A23),J23+F24,F24) -> 377417 | K24: =J24/E24 -> 0.04706188 | L24: =1+G24 -> 1.0128794 | M24: =PRODUCT($L$2:L24)-1 -> 0.14058409 | N24: =PRODUCT($L$2:L24)-1 -> 0.14058409 | O24: =AVERAGE($G$2:G24)*252 -> 1.4551414 | P24: =STDEV($G$2:G24)*252^0.5 -> 0.14351846
A25: 44049 | B25: 8505200.1 | D25: =B25 -> 8505200.1 | E25: =IF(MONTH(A25)=MONTH(A24),E24,D24) -> 8019590.3 | F25: =B25-C25-D24 -> 108192.83 | G25: =F25/B24 -> 0.012884689 | J25: =IF(MONTH(A25)=MONTH(A24),J24+F25,F25) -> 485609.83 | K25: =J25/E25 -> 0.060552947 | L25: =1+G25 -> 1.0128847 | M25: =PRODUCT($L$2:L25)-1 -> 0.15528017 | N25: =PRODUCT($L$2:L25)-1 -> 0.15528017 | O25: =AVERAGE($G$2:G25)*252 -> 1.5297997 | P25: =STDEV($G$2:G25)*252^0.5 -> 0.14224221
A26: 44050 | B26: 8196625.5 | D26: =B26 -> 8196625.5 | E26: =IF(MONTH(A26)=MONTH(A25),E25,D25) -> 8019590.3 | F26: =B26-C26-D25 -> -308574.63 | G26: =F26/B25 -> -0.036280702 | J26: =IF(MONTH(A26)=MONTH(A25),J25+F26,F26) -> 177035.2 | K26: =J26/E26 -> 0.022075342 | L26: =1+G26 -> 0.9637193 | M26: =PRODUCT($L$2:L26)-1 -> 0.11336579 | N26: =PRODUCT($L$2:L26)-1 -> 0.11336579 | O26: =AVERAGE($G$2:G26)*252 -> 1.1028982 | P26: =STDEV($G$2:G26)*252^0.5 -> 0.19357081
A27: 44053 | B27: 7879783.9 | D27: =B27 -> 7879783.9 | E27: =IF(MONTH(A27)=MONTH(A26),E26,D26) -> 8019590.3 | F27: =B27-C27-D26 -> -316841.56 | G27: =F27/B26 -> -0.038655122 | J27: =IF(MONTH(A27)=MONTH(A26),J26+F27,F27) -> -139806.36 | K27: =J27/E27 -> -0.017433105 | L27: =1+G27 -> 0.96134488 | M27: =PRODUCT($L$2:L27)-1 -> 0.0703285 | N27: =PRODUCT($L$2:L27)-1 -> 0.0703285 | O27: =AVERAGE($G$2:G27)*252 -> 0.68582174 | P27: =STDEV($G$2:G27)*252^0.5 -> 0.23220333
A28: 44054 | B28: 7384368.2 | D28: =B28 -> 7384368.2 | E28: =IF(MONTH(A28)=MONTH(A27),E27,D27) -> 8019590.3 | F28: =B28-C28-D27 -> -495415.76 | G28: =F28/B27 -> -0.062871744 | J28: =IF(MONTH(A28)=MONTH(A27),J27+F28,F28) -> -635222.12 | K28: =J28/E28 -> -0.079208799 | L28: =1+G28 -> 0.93712826 | M28: =PRODUCT($L$2:L28)-1 -> 0.0030350806 | N28: =PRODUCT($L$2:L28)-1 -> 0.0030350806 | O28: =AVERAGE($G$2:G28)*252 -> 0.07361799 | P28: =STDEV($G$2:G28)*252^0.5 -> 0.30331673
A29: 44055 | B29: 7585400.9 | D29: =B29 -> 7585400.9 | E29: =IF(MONTH(A29)=MONTH(A28),E28,D28) -> 8019590.3 | F29: =B29-C29-D28 -> 201032.72 | G29: =F29/B28 -> 0.027224092 | J29: =IF(MONTH(A29)=MONTH(A28),J28+F29,F29) -> -434189.4 | K29: =J29/E29 -> -0.054141095 | L29: =1+G29 -> 1.0272241 | M29: =PRODUCT($L$2:L29)-1 -> 0.0303418 | N29: =PRODUCT($L$2:L29)-1 -> 0.0303418 | O29: =AVERAGE($G$2:G29)*252 -> 0.31600561 | P29: =STDEV($G$2:G29)*252^0.5 -> 0.30841784
A30: 44056 | B30: 7631434.3 | D30: =B30 -> 7631434.3 | E30: =IF(MONTH(A30)=MONTH(A29),E29,D29) -> 8019590.3 | F30: =B30-C30-D29 -> 46033.38 | G30: =F30/B29 -> 0.0060686812 | J30: =IF(MONTH(A30)=MONTH(A29),J29+F30,F30) -> -388156.02 | K30: =J30/E30 -> -0.048400979 | L30: =1+G30 -> 1.0060687 | M30: =PRODUCT($L$2:L30)-1 -> 0.036594616 | N30: =PRODUCT($L$2:L30)-1 -> 0.036594616 | O30: =AVERAGE($G$2:G30)*252 -> 0.35784361 | P30: =STDEV($G$2:G30)*252^0.5 -> 0.30319269
A31: 44057 | B31: 7623006.3 | D31: =B31 -> 7623006.3 | E31: =IF(MONTH(A31)=MONTH(A30),E30,D30) -> 8019590.3 | F31: =B31-C31-D30 -> -8427.99 | G31: =F31/B30 -> -0.0011043782 | J31: =IF(MONTH(A31)=MONTH(A30),J30+F31,F31) -> -396584.01 | K31: =J31/E31 -> -0.049451904 | L31: =1+G31 -> 0.99889562 | M31: =PRODUCT($L$2:L31)-1 -> 0.035449823 | N31: =PRODUCT($L$2:L31)-1 -> 0.035449823 | O31: =AVERAGE($G$2:G31)*252 -> 0.33663871 | P31: =STDEV($G$2:G31)*252^0.5 -> 0.29800919
A32: 44060 | B32: 7922402.5 | D32: =B32 -> 7922402.5 | E32: =IF(MONTH(A32)=MONTH(A31),E31,D31) -> 8019590.3 | F32: =B32-C32-D31 -> 299396.17 | G32: =F32/B31 -> 0.039275341 | J32: =IF(MONTH(A32)=MONTH(A31),J31+F32,F32) -> -97187.84 | K32: =J32/E32 -> -0.012118804 | L32: =1+G32 -> 1.0392753 | M32: =PRODUCT($L$2:L32)-1 -> 0.076117468 | N32: =PRODUCT($L$2:L32)-1 -> 0.076117468 | O32: =AVERAGE($G$2:G32)*252 -> 0.64504991 | P32: =STDEV($G$2:G32)*252^0.5 -> 0.31233015
A33: 44061 | B33: 8026372.1 | D33: =B33 -> 8026372.1 | E33: =IF(MONTH(A33)=MONTH(A32),E32,D32) -> 8019590.3 | F33: =B33-C33-D32 -> 103969.61 | G33: =F33/B32 -> 0.013123495 | J33: =IF(MONTH(A33)=MONTH(A32),J32+F33,F33) -> 6781.77 | K33: =J33/E33 -> 0.00084565043 | L33: =1+G33 -> 1.0131235 | M33: =PRODUCT($L$2:L33)-1 -> 0.090239891 | N33: =PRODUCT($L$2:L33)-1 -> 0.090239891 | O33: =AVERAGE($G$2:G33)*252 -> 0.72823962 | P33: =STDEV($G$2:G33)*252^0.5 -> 0.30867805
... A42: 44074 | B42: 8142193.1 | D42: =B42 -> 8142193.1 | E42: =IF(MONTH(A42)=MONTH(A41),E41,D41) -> 8019590.3 | F42: =B42-C42-D41 -> 290346.71 | G42: =F42/B41 -> 0.036978144 | J42: =IF(MONTH(A42)=MONTH(A41),J41+F42,F42) -> 122602.8 | K42: =J42/E42 -> 0.015287913 | L42: =1+G42 -> 1.0369781 | M42: =PRODUCT($L$2:L42)-1 -> 0.10597212 | N42: =PRODUCT($L$2:L42)-1 -> 0.10597212 | O42: =AVERAGE($G$2:G42)*252 -> 0.66509521 | P42: =STDEV($G$2:G42)*252^0.5 -> 0.30262598
A43: 44075 | B43: 8932854.6 | C43: 340000 | D43: =B43 -> 8932854.6 | E43: =IF(MONTH(A43)=MONTH(A42),E42,D42) -> 8142193.1 | F43: =790661.47-C43 -> 450661.47 | G43: 0.0531 | J43: =IF(MONTH(A43)=MONTH(A42),J42+F43,F43) -> 450661.47 | K43: =G43 -> 0.0531 | L43: =1+G43 -> 1.0531 | M43: =PRODUCT($L$2:L43)-1 -> 0.16469924 | N43: =PRODUCT($L$2:L43)-1 -> 0.16469924 | O43: =AVERAGE($G$2:G43)*252 -> 0.96785961 | P43: =STDEV($G$2:G43)*252^0.5 -> 0.32346017
A44: 44076 | B44: 8942808.3 | D44: =B44 -> 8942808.3 | E44: =IF(MONTH(A44)=MONTH(A43),E43,D43) -> 8142193.1 | F44: =B44-C44-D43 -> 9953.78 | G44: =F44/B43 -> 0.0011142888 | J44: =IF(MONTH(A44)=MONTH(A43),J43+F44,F44) -> 460615.25 | K44: 0.0543 | L44: =1+G44 -> 1.0011143 | M44: =PRODUCT($L$2:L44)-1 -> 0.16599705 | N44: =PRODUCT($L$2:L44)-1 -> 0.16599705 | O44: =AVERAGE($G$2:G44)*252 -> 0.9518815 | P44: =STDEV($G$2:G44)*252^0.5 -> 0.3196544
A45: 44077 | B45: 18349287 | C45: 10000000 | D45: =B45 -> 18349287 | E45: =IF(MONTH(A45)=MONTH(A44),E44,D44) -> 8142193.1 | F45: =B45-C45-D44 -> -593521.57 | G45: -0.0313 | J45: =IF(MONTH(A45)=MONTH(A44),J44+F45,F45) -> -132906.32 | K45: 0.0213 | L45: =1+G45 -> 0.9687 | M45: =PRODUCT($L$2:L45)-1 -> 0.12950134 | N45: =PRODUCT($L$2:L45)-1 -> 0.12950134 | O45: =AVERAGE($G$2:G45)*252 -> 0.75098419 | P45: =STDEV($G$2:G45)*252^0.5 -> 0.3268786
A46: 44078 | B46: 17844069 | D46: =B46 -> 17844069 | E46: =IF(MONTH(A46)=MONTH(A45),E45,D45) -> 8142193.1 | F46: =B46-C46-D45 -> -505217.29 | G46: =F46/B45 -> -0.027533348 | J46: =IF(MONTH(A46)=MONTH(A45),J45+F46,F46) -> -638123.61 | K46: -0.0068 | L46: =1+G46 -> 0.97246665 | M46: =PRODUCT($L$2:L46)-1 -> 0.098402388 | N46: =PRODUCT($L$2:L46)-1 -> 0.098402388 | O46: =AVERAGE($G$2:G46)*252 -> 0.58010891 | P46: =STDEV($G$2:G46)*252^0.5 -> 0.33111208
A47: 44081 | B47: 17832817 | D47: =B47 -> 17832817 | E47: =IF(MONTH(A47)=MONTH(A46),E46,D46) -> 8142193.1 | F47: =B47-C47-D46 -> -11252.47 | G47: =F47/B46 -> -0.00063059999 | J47: =IF(MONTH(A47)=MONTH(A46),J46+F47,F47) -> -649376.08 | K47: -0.0075 | L47: =1+G47 -> 0.9993694 | M47: =PRODUCT($L$2:L47)-1 -> 0.097709735 | N47: =PRODUCT($L$2:L47)-1 -> 0.097709735 | O47: =AVERAGE($G$2:G47)*252 -> 0.56404326 | P47: =STDEV($G$2:G47)*252^0.5 -> 0.32748433
A48: 44082 | B48: 17315845 | D48: =B48 -> 17315845 | E48: =IF(MONTH(A48)=MONTH(A47),E47,D47) -> 8142193.1 | F48: =B48-C48-D47 -> -516971.74 | G48: =F48/B47 -> -0.028989909 | J48: =IF(MONTH(A48)=MONTH(A47),J47+F48,F48) -> -1166347.8 | K48: -0.0362 | L48: =1+G48 -> 0.97101009 | M48: =PRODUCT($L$2:L48)-1 -> 0.06588723 | N48: =PRODUCT($L$2:L48)-1 -> 0.06588723 | O48: =AVERAGE($G$2:G48)*252 -> 0.39660708 | P48: =STDEV($G$2:G48)*252^0.5 -> 0.33187841
A49: 44083 | B49: 17720329 | D49: =B49 -> 17720329 | E49: =IF(MONTH(A49)=MONTH(A48),E48,D48) -> 8142193.1 | F49: =B49-C49-D48 -> 404483.41 | G49: =F49/B48 -> 0.023359149 | J49: =IF(MONTH(A49)=MONTH(A48),J48+F49,F49) -> -761864.41 | K49: -0.0137 | L49: =1+G49 -> 1.0233591 | M49: =PRODUCT($L$2:L49)-1 -> 0.090785449 | N49: =PRODUCT($L$2:L49)-1 -> 0.090785449 | O49: =AVERAGE($G$2:G49)*252 -> 0.51097996 | P49: =STDEV($G$2:G49)*252^0.5 -> 0.33210157
A50: 44084 | B50: 17546118 | D50: =B50 -> 17546118 | E50: =IF(MONTH(A50)=MONTH(A49),E49,D49) -> 8142193.1 | F50: =B50-C50-D49 -> -174210.95 | G50: =F50/B49 -> -0.0098311354 | J50: =IF(MONTH(A50)=MONTH(A49),J49+F50,F50) -> -936075.36 | K50: -0.0234 | L50: =1+G50 -> 0.99016886 | M50: =PRODUCT($L$2:L50)-1 -> 0.080061789 | N50: =PRODUCT($L$2:L50)-1 -> 0.080061789 | O50: =AVERAGE($G$2:G50)*252 -> 0.44999168 | P50: =STDEV($G$2:G50)*252^0.5 -> 0.32972256
A51: 44085 | B51: 17482798 | D51: =B51 -> 17482798 | E51: =IF(MONTH(A51)=MONTH(A50),E50,D50) -> 8142193.1 | F51: =B51-C51-D50 -> -63319.35 | G51: =F51/B50 -> -0.0036087385 | J51: =IF(MONTH(A51)=MONTH(A50),J50+F51,F51) -> -999394.71 | K51: -0.027 | L51: =1+G51 -> 0.99639126 | M51: =PRODUCT($L$2:L51)-1 -> 0.076164129 | N51: =PRODUCT($L$2:L51)-1 -> 0.076164129 | O51: =AVERAGE($G$2:G51)*252 -> 0.4228038 | P51: =STDEV($G$2:G51)*252^0.5 -> 0.32656533
A52: 44088 | B52: 17776535 | D52: =B52 -> 17776535 | E52: =IF(MONTH(A52)=MONTH(A51),E51,D51) -> 8142193.1 | F52: =B52-C52-D51 -> 293736.13 | G52: =F52/B51 -> 0.016801437 | J52: =IF(MONTH(A52)=MONTH(A51),J51+F52,F52) -> -705658.58 | K52: -0.0106 | L52: =1+G52 -> 1.0168014 | M52: =PRODUCT($L$2:L52)-1 -> 0.094245232 | N52: =PRODUCT($L$2:L52)-1 -> 0.094245232 | O52: =AVERAGE($G$2:G52)*252 -> 0.49753239 | P52: =STDEV($G$2:G52)*252^0.5 -> 0.32502644
A53: 44089 | B53: 17898749 | D53: =B53 -> 17898749 | E53: =IF(MONTH(A53)=MONTH(A52),E52,D52) -> 8142193.1 | F53: =B53-C53-D52 -> 122214.47 | G53: =F53/B52 -> 0.0068750447 | J53: =IF(MONTH(A53)=MONTH(A52),J52+F53,F53) -> -583444.11 | K53: -0.0038 | L53: =1+G53 -> 1.006875 | M53: =PRODUCT($L$2:L53)-1 -> 0.10176822 | N53: =PRODUCT($L$2:L53)-1 -> 0.10176822 | O53: =AVERAGE($G$2:G53)*252 -> 0.52128199 | P53: =STDEV($G$2:G53)*252^0.5 -> 0.32200491
A54: 44090 | B54: 17688460 | D54: =B54 -> 17688460 | E54: =IF(MONTH(A54)=MONTH(A53),E53,D53) -> 8142193.1 | F54: =B54-C54-D53 -> -210289.08 | G54: =F54/B53 -> -0.011748814 | J54: =IF(MONTH(A54)=MONTH(A53),J53+F54,F54) -> -793733.19 | K54: -0.0155 | L54: =1+G54 -> 0.98825119 | M54: =PRODUCT($L$2:L54)-1 -> 0.088823747 | N54: =PRODUCT($L$2:L54)-1 -> 0.088823747 | O54: =AVERAGE($G$2:G54)*252 -> 0.45558419 | P54: =STDEV($G$2:G54)*252^0.5 -> 0.32031383
A55: 44091 | B55: 17479824 | D55: =B55 -> 17479824 | E55: =IF(MONTH(A55)=MONTH(A54),E54,D54) -> 8142193.1 | F55: =B55-C55-D54 -> -208635.94 | G55: =F55/B54 -> -0.011795031 | J55: =IF(MONTH(A55)=MONTH(A54),J54+F55,F55) -> -1002369.1 | K55: -0.0271 | L55: =1+G55 -> 0.98820497 | M55: =PRODUCT($L$2:L55)-1 -> 0.075981037 | N55: =PRODUCT($L$2:L55)-1 -> 0.075981037 | O55: =AVERAGE($G$2:G55)*252 -> 0.39210397 | P55: =STDEV($G$2:G55)*252^0.5 -> 0.31863552
A56: 44092 | B56: 17499642 | D56: =B56 -> 17499642 | E56: =IF(MONTH(A56)=MONTH(A55),E55,D55) -> 8142193.1 | F56: =B56-C56-D55 -> 19817.69 | G56: =F56/B55 -> 0.0011337465 | J56: =IF(MONTH(A56)=MONTH(A55),J55+F56,F56) -> -982551.44 | K56: -0.026 | L56: =1+G56 -> 1.0011337 | M56: =PRODUCT($L$2:L56)-1 -> 0.077200926 | N56: =PRODUCT($L$2:L56)-1 -> 0.077200926 | O56: =AVERAGE($G$2:G56)*252 -> 0.39016942 | P56: =STDEV($G$2:G56)*252^0.5 -> 0.3156727
A57: 44095 | B57: 17628134 | D57: =B57 -> 17628134 | E57: =IF(MONTH(A57)=MONTH(A56),E56,D56) -> 8142193.1 | F57: =B57-C57-D56 -> 128492.31 | G57: =F57/B56 -> 0.0073425681 | J57: =IF(MONTH(A57)=MONTH(A56),J56+F57,F57) -> -854059.13 | K57: -0.0189 | L57: =1+G57 -> 1.0073426 | M57: =PRODUCT($L$2:L57)-1 -> 0.085110347 | N57: =PRODUCT($L$2:L57)-1 -> 0.085110347 | O57: =AVERAGE($G$2:G57)*252 -> 0.41624367 | P57: =STDEV($G$2:G57)*252^0.5 -> 0.3130312
... A64: 44104 | B64: 18033797 | D64: =B64 -> 18033797 | E64: =IF(MONTH(A64)=MONTH(A63),E63,D63) -> 8142193.1 | F64: =B64-C64-D63 -> 20016.77 | G64: =F64/B63 -> 0.0011111921 | J64: =IF(MONTH(A64)=MONTH(A63),J63+F64,F64) -> -448395.89 | K64: 0.0037 | L64: =1+G64 -> 1.0011112 | M64: =PRODUCT($L$2:L64)-1 -> 0.11008119 | N64: =PRODUCT($L$2:L64)-1 -> 0.11008119 | O64: =AVERAGE($G$2:G64)*252 -> 0.46411304 | P64: =STDEV($G$2:G64)*252^0.5 -> 0.30494894
A65: 44105 | B65: 18859614 | C65: 500000 | D65: =B65 -> 18859614 | E65: =IF(MONTH(A65)=MONTH(A64),E64,D64) -> 18033797 | F65: =B65-C65-D64 -> 325816.92 | G65: 0.0176 | J65: =IF(MONTH(A65)=MONTH(A64),J64+F65,F65) -> 325816.92 | K65: =G65 -> 0.0176 | L65: =1+G65 -> 1.0176 | M65: =PRODUCT($L$2:L65)-1 -> 0.12961862 | N65: =PRODUCT($L$2:L65)-1 -> 0.12961862 | O65: =AVERAGE($G$2:G65)*252 -> 0.52616127 | P65: =STDEV($G$2:G65)*252^0.5 -> 0.30413079
A66: 44106 | B66: 18429069 | D66: =B66 -> 18429069 | E66: =IF(MONTH(A66)=MONTH(A65),E65,D65) -> 18033797 | F66: =B66-C66-D65 -> -430545.13 | G66: =F66/B65 -> -0.022828947 | J66: =IF(MONTH(A66)=MONTH(A65),J65+F66,F66) -> -104728.21 | K66: -0.0057 | L66: =1+G66 -> 0.97717105 | M66: =PRODUCT($L$2:L66)-1 -> 0.10383062 | N66: =PRODUCT($L$2:L66)-1 -> 0.10383062 | O66: =AVERAGE($G$2:G66)*252 -> 0.42956041 | P66: =STDEV($G$2:G66)*252^0.5 -> 0.30570785
A67: 44109 | B67: 18733740 | D67: =B67 -> 18733740 | E67: =IF(MONTH(A67)=MONTH(A66),E66,D66) -> 18033797 | F67: =B67-C67-D66 -> 304671.43 | G67: =F67/B66 -> 0.016532112 | J67: =IF(MONTH(A67)=MONTH(A66),J66+F67,F67) -> 199943.22 | K67: 0.0108 | L67: =1+G67 -> 1.0165321 | M67: =PRODUCT($L$2:L67)-1 -> 0.12207927 | N67: =PRODUCT($L$2:L67)-1 -> 0.12207927 | O67: =AVERAGE($G$2:G67)*252 -> 0.48617453 | P67: =STDEV($G$2:G67)*252^0.5 -> 0.30472763
A68: 44110 | B68: 18512727 | D68: =B68 -> 18512727 | E68: =IF(MONTH(A68)=MONTH(A67),E67,D67) -> 18033797 | F68: =B68-C68-D67 -> -221013.53 | G68: =F68/B67 -> -0.011797619 | J68: =IF(MONTH(A68)=MONTH(A67),J67+F68,F68) -> -21070.31 | K68: -0.0011 | L68: =1+G68 -> 0.98820238 | M68: =PRODUCT($L$2:L68)-1 -> 0.1088414 | N68: =PRODUCT($L$2:L68)-1 -> 0.1088414 | O68: =AVERAGE($G$2:G68)*252 -> 0.43454506 | P68: =STDEV($G$2:G68)*252^0.5 -> 0.30357979
A69: 44111 | B69: 18809864 | D69: =B69 -> 18809864 | E69: =IF(MONTH(A69)=MONTH(A68),E68,D68) -> 18033797 | F69: =B69-C69-D68 -> 297137.54 | G69: =F69/B68 -> 0.016050447 | J69: =IF(MONTH(A69)=MONTH(A68),J68+F69,F69) -> 276067.23 | K69: =(1+K68)*(1+G69)-1 -> 0.014932791 | L69: =1+G69 -> 1.0160504 | M69: =PRODUCT($L$2:L69)-1 -> 0.1266388 | N69: =PRODUCT($L$2:L69)-1 -> 0.1266388 | O69: =AVERAGE($G$2:G69)*252 -> 0.48763576 | P69: =STDEV($G$2:G69)*252^0.5 -> 0.30256526
A70: 44112 | B70: 18757107 | D70: =B70 -> 18757107 | E70: =IF(MONTH(A70)=MONTH(A69),E69,D69) -> 18033797 | F70: =B70-C70-D69 -> -52757.55 | G70: =F70/B69 -> -0.002804781 | J70: =IF(MONTH(A70)=MONTH(A69),J69+F70,F70) -> 223309.68 | K70: 0.012 | L70: =1+G70 -> 0.99719522 | M70: =PRODUCT($L$2:L70)-1 -> 0.12347883 | N70: =PRODUCT($L$2:L70)-1 -> 0.12347883 | O70: =AVERAGE($G$2:G70)*252 -> 0.47032503 | P70: =STDEV($G$2:G70)*252^0.5 -> 0.30046884
A71: 44113 | B71: 19081799 | D71: =B71 -> 19081799 | E71: =IF(MONTH(A71)=MONTH(A70),E70,D70) -> 18033797 | F71: =B71-C71-D70 -> 324692.39 | G71: =F71/B70 -> 0.017310366 | J71: =IF(MONTH(A71)=MONTH(A70),J70+F71,F71) -> 548002.07 | K71: 0.0296 | L71: =1+G71 -> 1.0173104 | M71: =PRODUCT($L$2:L71)-1 -> 0.14292666 | N71: =PRODUCT($L$2:L71)-1 -> 0.14292666 | O71: =AVERAGE($G$2:G71)*252 -> 0.52592342 | P71: =STDEV($G$2:G71)*252^0.5 -> 0.29971947
A72: 44116 | B72: 19576913 | D72: =B72 -> 19576913 | E72: =IF(MONTH(A72)=MONTH(A71),E71,D71) -> 18033797 | F72: =B72-C72-D71 -> 495113.44 | G72: =F72/B71 -> 0.025946895 | J72: =IF(MONTH(A72)=MONTH(A71),J71+F72,F72) -> 1043115.5 | K72: 0.0563 | L72: =1+G72 -> 1.0259469 | M72: =PRODUCT($L$2:L72)-1 -> 0.17258206 | N72: =PRODUCT($L$2:L72)-1 -> 0.17258206 | O72: =AVERAGE($G$2:G72)*252 -> 0.61060925 | P72: =STDEV($G$2:G72)*252^0.5 -> 0.30094691
A73: 44117 | B73: 19922765 | D73: =B73 -> 19922765 | E73: =IF(MONTH(A73)=MONTH(A72),E72,D72) -> 18033797 | F73: =B73-C73-D72 -> 345852.56 | G73: =F73/B72 -> 0.017666348 | J73: =IF(MONTH(A73)=MONTH(A72),J72+F73,F73) -> 1388968.1 | K73: 0.0749 | L73: =1+G73 -> 1.0176663 | M73: =PRODUCT($L$2:L73)-1 -> 0.1932973 | N73: =PRODUCT($L$2:L73)-1 -> 0.1932973 | O73: =AVERAGE($G$2:G73)*252 -> 0.66396078 | P73: =STDEV($G$2:G73)*252^0.5 -> 0.30017774
A74: 44118 | B74: 19758823 | D74: =B74 -> 19758823 | E74: =IF(MONTH(A74)=MONTH(A73),E73,D73) -> 18033797 | F74: =B74-C74-D73 -> -163942.31 | G74: =F74/B73 -> -0.0082288933 | J74: =IF(MONTH(A74)=MONTH(A73),J73+F74,F74) -> 1225025.8 | K74: 0.0661 | L74: =1+G74 -> 0.99177111 | M74: =PRODUCT($L$2:L74)-1 -> 0.18347778 | N74: =PRODUCT($L$2:L74)-1 -> 0.18347778 | O74: =AVERAGE($G$2:G74)*252 -> 0.62645884 | P74: =STDEV($G$2:G74)*252^0.5 -> 0.29876848
A75: 44119 | B75: 20054697 | D75: =B75 -> 20054697 | E75: =IF(MONTH(A75)=MONTH(A74),E74,D74) -> 18033797 | F75: =B75-C75-D74 -> 295873.79 | G75: =F75/B74 -> 0.014974262 | J75: =IF(MONTH(A75)=MONTH(A74),J74+F75,F75) -> 1520899.6 | K75: =(1+K74)*(1+G75)-1 -> 0.082064061 | L75: =1+G75 -> 1.0149743 | M75: =PRODUCT($L$2:L75)-1 -> 0.20119949 | N75: =PRODUCT($L$2:L75)-1 -> 0.20119949 | O75: =AVERAGE($G$2:G75)*252 -> 0.66898661 | P75: =STDEV($G$2:G75)*252^0.5 -> 0.29760868
A76: 44120 | B76: 20040183 | D76: =B76 -> 20040183 | E76: =IF(MONTH(A76)=MONTH(A75),E75,D75) -> 18033797 | F76: =B76-C76-D75 -> -14514.18 | G76: =F76/B75 -> -0.00072372972 | J76: =IF(MONTH(A76)=MONTH(A75),J75+F76,F76) -> 1506385.4 | K76: 0.0813 | L76: =1+G76 -> 0.99927627 | M76: =PRODUCT($L$2:L76)-1 -> 0.20033015 | N76: =PRODUCT($L$2:L76)-1 -> 0.20033015 | O76: =AVERAGE($G$2:G76)*252 -> 0.65763506 | P76: =STDEV($G$2:G76)*252^0.5 -> 0.29565584
A77: 44123 | B77: 19733475 | D77: =B77 -> 19733475 | E77: =IF(MONTH(A77)=MONTH(A76),E76,D76) -> 18033797 | F77: =B77-C77-D76 -> -306707.58 | G77: =F77/B76 -> -0.01530463 | J77: =IF(MONTH(A77)=MONTH(A76),J76+F77,F77) -> 1199677.8 | K77: 0.0647 | L77: =1+G77 -> 0.98469537 | M77: =PRODUCT($L$2:L77)-1 -> 0.18195954 | N77: =PRODUCT($L$2:L77)-1 -> 0.18195954 | O77: =AVERAGE($G$2:G77)*252 -> 0.59823504 | P77: =STDEV($G$2:G77)*252^0.5 -> 0.29548432
A78: 44124 | B78: 19783649 | D78: =B78 -> 19783649 | E78: =IF(MONTH(A78)=MONTH(A77),E77,D77) -> 18033797 | F78: =B78-C78-D77 -> 50174.37 | G78: =F78/B77 -> 0.0025426018 | J78: =IF(MONTH(A78)=MONTH(A77),J77+F78,F78) -> 1249852.2 | K78: =(1+K77)*(1+G78)-1 -> 0.067407108 | L78: =1+G78 -> 1.0025426 | M78: =PRODUCT($L$2:L78)-1 -> 0.18496479 | N78: =PRODUCT($L$2:L78)-1 -> 0.18496479 | O78: =AVERAGE($G$2:G78)*252 -> 0.59878699 | P78: =STDEV($G$2:G78)*252^0.5 -> 0.29353407
A79: 44125 | B79: 19288148 | D79: =B79 -> 19288148 | E79: =IF(MONTH(A79)=MONTH(A78),E78,D78) -> 18033797 | F79: =B79-C79-D78 -> -495501.49 | G79: =F79/B78 -> -0.025046011 | J79: =IF(MONTH(A79)=MONTH(A78),J78+F79,F79) -> 754350.67 | K79: =(1+K78)*(1+G79)-1 -> 0.040672819 | L79: =1+G79 -> 0.97495399 | M79: =PRODUCT($L$2:L79)-1 -> 0.15528615 | N79: =PRODUCT($L$2:L79)-1 -> 0.15528615 | O79: =AVERAGE($G$2:G79)*252 -> 0.51019236 | P79: =STDEV($G$2:G79)*252^0.5 -> 0.29575787
A80: 44126 | B80: 18838068 | D80: =B80 -> 18838068 | E80: =IF(MONTH(A80)=MONTH(A79),E79,D79) -> 18033797 | F80: =B80-C80-D79 -> -450079.82 | G80: =F80/B79 -> -0.023334528 | J80: =IF(MONTH(A80)=MONTH(A79),J79+F80,F80) -> 304270.85 | K80: =(1+K79)*(1+G80)-1 -> 0.01638921 | L80: =1+G80 -> 0.97666547 | M80: =PRODUCT($L$2:L80)-1 -> 0.12832809 | N80: =PRODUCT($L$2:L80)-1 -> 0.12832809 | O80: =AVERAGE($G$2:G80)*252 -> 0.42930003 | P80: =STDEV($G$2:G80)*252^0.5 -> 0.29732579
A81: 44127 | B81: 19120205 | D81: =B81 -> 19120205 | E81: =IF(MONTH(A81)=MONTH(A80),E80,D80) -> 18033797 | F81: =B81-C81-D80 -> 282136.97 | G81: =F81/B80 -> 0.014976959 | J81: =IF(MONTH(A81)=MONTH(A80),J80+F81,F81) -> 586407.82 | K81: =(1+K80)*(1+G81)-1 -> 0.031611629 | L81: =1+G81 -> 1.014977 | M81: =PRODUCT($L$2:L81)-1 -> 0.14522702 | N81: =PRODUCT($L$2:L81)-1 -> 0.14522702 | O81: =AVERAGE($G$2:G81)*252 -> 0.4711112 | P81: =STDEV($G$2:G81)*252^0.5 -> 0.29637574
A82: 44130 | B82: 18895076 | D82: =B82 -> 18895076 | E82: =IF(MONTH(A82)=MONTH(A81),E81,D81) -> 18033797 | F82: =B82-C82-D81 -> -225129.48 | G82: =F82/B81 -> -0.011774428 | J82: =IF(MONTH(A82)=MONTH(A81),J81+F82,F82) -> 361278.34 | K82: =(1+K81)*(1+G82)-1 -> 0.019464992 | L82: =1+G82 -> 0.98822557 | M82: =PRODUCT($L$2:L82)-1 -> 0.13174262 | N82: =PRODUCT($L$2:L82)-1 -> 0.13174262 | O82: =AVERAGE($G$2:G82)*252 -> 0.42866346 | P82: =STDEV($G$2:G82)*252^0.5 -> 0.29549916
A83: 44131 | B83: 19203986 | D83: =B83 -> 19203986 | E83: =IF(MONTH(A83)=MONTH(A82),E82,D82) -> 18033797 | F83: =B83-C83-D82 -> 308910.56 | G83: =F83/B82 -> 0.016348734 | J83: =IF(MONTH(A83)=MONTH(A82),J82+F83,F83) -> 670188.9 | K83: 0.0362 | L83: =1+G83 -> 1.0163487 | M83: =PRODUCT($L$2:L83)-1 -> 0.15024518 | N83: =PRODUCT($L$2:L83)-1 -> 0.15024518 | O83: =AVERAGE($G$2:G83)*252 -> 0.47367831 | P83: =STDEV($G$2:G83)*252^0.5 -> 0.29478992
A84: 44132 | B84: 18424241 | D84: =B84 -> 18424241 | E84: =IF(MONTH(A84)=MONTH(A83),E83,D83) -> 18033797 | F84: =B84-C84-D83 -> -779745.06 | G84: =F84/B83 -> -0.040603292 | J84: =IF(MONTH(A84)=MONTH(A83),J83+F84,F84) -> -109556.16 | K84: =(1+K83)*(1+G84)-1 -> -0.0058731314 | L84: =1+G84 -> 0.95939671 | M84: =PRODUCT($L$2:L84)-1 -> 0.10354144 | N84: =PRODUCT($L$2:L84)-1 -> 0.10354144 | O84: =AVERAGE($G$2:G84)*252 -> 0.34469388 | P84: =STDEV($G$2:G84)*252^0.5 -> 0.30219359
A85: 44133 | B85: 18483188 | D85: =B85 -> 18483188 | E85: =IF(MONTH(A85)=MONTH(A84),E84,D84) -> 18033797 | F85: =B85-C85-D84 -> 58946.82 | G85: =F85/B84 -> 0.0031994165 | J85: =IF(MONTH(A85)=MONTH(A84),J84+F85,F85) -> -50609.34 | K85: =(1+K84)*(1+G85)-1 -> -0.0026925055 | L85: =1+G85 -> 1.0031994 | M85: =PRODUCT($L$2:L85)-1 -> 0.10707213 | N85: =PRODUCT($L$2:L85)-1 -> 0.10707213 | O85: =AVERAGE($G$2:G85)*252 -> 0.35018863 | P85: =STDEV($G$2:G85)*252^0.5 -> 0.30038438
A86: 44134 | B86: 17677657 | D86: =B86 -> 17677657 | E86: =IF(MONTH(A86)=MONTH(A85),E85,D85) -> 18033797 | F86: =B86-C86-D85 -> -805531.36 | G86: =F86/B85 -> -0.043581841 | J86: =IF(MONTH(A86)=MONTH(A85),J85+F86,F86) -> -856140.7 | K86: =(1+K85)*(1+G86)-1 -> -0.046157002 | L86: =1+G86 -> 0.95641816 | M86: =PRODUCT($L$2:L86)-1 -> 0.058823888 | N86: =PRODUCT($L$2:L86)-1 -> 0.058823888 | O86: =AVERAGE($G$2:G86)*252 -> 0.21686142 | P86: =STDEV($G$2:G86)*252^0.5 -> 0.30846803
A87: 44137 | B87: 18652090 | C87: 500000 | D87: =B87 -> 18652090 | E87: =IF(MONTH(A87)=MONTH(A86),E86,D86) -> 17677657 | F87: =B87-C87-D86 -> 474433.16 | G87: 0.0261 | J87: =IF(MONTH(A87)=MONTH(A86),J86+F87,F87) -> 474433.16 | K87: 0.0261 | L87: =1+G87 -> 1.0261 | M87: =PRODUCT($L$2:L87)-1 -> 0.086459191 | N87: =PRODUCT($L$2:L87)-1 -> 0.086459191 | O87: =AVERAGE($G$2:G87)*252 -> 0.29081885 | P87: =STDEV($G$2:G87)*252^0.5 -> 0.30967681
A88: 44138 | B88: 25045656 | C88: 6000000 | D88: =B88 -> 25045656 | E88: =IF(MONTH(A88)=MONTH(A87),E87,D87) -> 17677657 | F88: =B88-C88-D87 -> 393566.46 | G88: 0.016 | J88: =IF(MONTH(A88)=MONTH(A87),J87+F88,F88) -> 867999.62 | K88: =(1+K87)*(1+G88)-1 -> 0.0425176 | L88: =1+G88 -> 1.016 | M88: =PRODUCT($L$2:L88)-1 -> 0.10384254 | N88: =PRODUCT($L$2:L88)-1 -> 0.10384254 | O88: =AVERAGE($G$2:G88)*252 -> 0.33382093 | P88: =STDEV($G$2:G88)*252^0.5 -> 0.30890617
A89: 44139 | B89: 25941870 | D89: =B89 -> 25941870 | E89: =IF(MONTH(A89)=MONTH(A88),E88,D88) -> 17677657 | F89: =B89-C89-D88 -> 896213.97 | G89: =F89/B88 -> 0.03578321 | J89: =IF(MONTH(A89)=MONTH(A88),J88+F89,F89) -> 1764213.6 | K89: =(1+K88)*(1+G89)-1 -> 0.079822226 | L89: =1+G89 -> 1.0357832 | M89: =PRODUCT($L$2:L89)-1 -> 0.14334157 | N89: =PRODUCT($L$2:L89)-1 -> 0.14334157 | O89: =AVERAGE($G$2:G89)*252 -> 0.43249761 | P89: =STDEV($G$2:G89)*252^0.5 -> 0.31261231
A90: 44140 | B90: 27045285 | D90: =B90 -> 27045285 | E90: =IF(MONTH(A90)=MONTH(A89),E89,D89) -> 17677657 | F90: =B90-C90-D89 -> 1103414.9 | G90: =F90/B89 -> 0.042534131 | J90: =IF(MONTH(A90)=MONTH(A89),J89+F90,F90) -> 2867628.5 | K90: 0.1257 | L90: =1+G90 -> 1.0425341 | M90: =PRODUCT($L$2:L90)-1 -> 0.19197261 | N90: =PRODUCT($L$2:L90)-1 -> 0.19197261 | O90: =AVERAGE($G$2:G90)*252 -> 0.54807181 | P90: =STDEV($G$2:G90)*252^0.5 -> 0.31832911
A91: 44141 | B91: 26856161 | D91: =B91 -> 26856161 | E91: =IF(MONTH(A91)=MONTH(A90),E90,D90) -> 17677657 | F91: =B91-C91-D90 -> -189123.9 | G91: =F91/B90 -> -0.0069928603 | J91: =IF(MONTH(A91)=MONTH(A90),J90+F91,F91) -> 2678504.6 | K91: =(1+K90)*(1+G91)-1 -> 0.11782814 | L91: =1+G91 -> 0.99300714 | M91: =PRODUCT($L$2:L91)-1 -> 0.18363731 | N91: =PRODUCT($L$2:L91)-1 -> 0.18363731 | O91: =AVERAGE($G$2:G91)*252 -> 0.52240211 | P91: =STDEV($G$2:G91)*252^0.5 -> 0.31690721
A92: 44144 | B92: 24633130 | D92: =B92 -> 24633130 | E92: =IF(MONTH(A92)=MONTH(A91),E91,D91) -> 17677657 | F92: =B92-C92-D91 -> -2223030.8 | G92: =F92/B91 -> -0.082775449 | J92: =IF(MONTH(A92)=MONTH(A91),J91+F92,F92) -> 455473.8 | K92: =(1+K91)*(1+G92)-1 -> 0.025299411 | L92: =1+G92 -> 0.91722455 | M92: =PRODUCT($L$2:L92)-1 -> 0.0856612 | N92: =PRODUCT($L$2:L92)-1 -> 0.0856612 | O92: =AVERAGE($G$2:G92)*252 -> 0.28743711 | P92: =STDEV($G$2:G92)*252^0.5 -> 0.34532696
A93: 44145 | B93: 24153859 | D93: =B93 -> 24153859 | E93: =IF(MONTH(A93)=MONTH(A92),E92,D92) -> 17677657 | F93: =B93-C93-D92 -> -479271.61 | G93: =F93/B92 -> -0.019456383 | J93: =IF(MONTH(A93)=MONTH(A92),J92+F93,F93) -> -23797.81 | K93: =(1+K92)*(1+G93)-1 -> 0.0053507933 | L93: =1+G93 -> 0.98054362 | M93: =PRODUCT($L$2:L93)-1 -> 0.06453816 | N93: =PRODUCT($L$2:L93)-1 -> 0.06453816 | O93: =AVERAGE($G$2:G93)*252 -> 0.23101922 | P93: =STDEV($G$2:G93)*252^0.5 -> 0.34511201
A94: 44146 | B94: 24605653 | D94: =B94 -> 24605653 | E94: =IF(MONTH(A94)=MONTH(A93),E93,D93) -> 17677657 | F94: =B94-C94-D93 -> 451793.82 | G94: =F94/B93 -> 0.01870483 | J94: =IF(MONTH(A94)=MONTH(A93),J93+F94,F94) -> 427996.01 | K94: =(1+K93)*(1+G94)-1 -> 0.024155709 | L94: =1+G94 -> 1.0187048 | M94: =PRODUCT($L$2:L94)-1 -> 0.084450165 | N94: =PRODUCT($L$2:L94)-1 -> 0.084450165 | O94: =AVERAGE($G$2:G94)*252 -> 0.2792192 | P94: =STDEV($G$2:G94)*252^0.5 -> 0.344478
A95: 44147 | B95: 24818514 | D95: =B95 -> 24818514 | E95: =IF(MONTH(A95)=MONTH(A94),E94,D94) -> 17677657 | F95: =B95-C95-D94 -> 212861.94 | G95: =F95/B94 -> 0.0086509366 | J95: =IF(MONTH(A95)=MONTH(A94),J94+F95,F95) -> 640857.95 | K95: =(1+K94)*(1+G95)-1 -> 0.033015615 | L95: =1+G95 -> 1.0086509 | M95: =PRODUCT($L$2:L95)-1 -> 0.093831675 | N95: =PRODUCT($L$2:L95)-1 -> 0.093831675 | O95: =AVERAGE($G$2:G95)*252 -> 0.29944065 | P95: =STDEV($G$2:G95)*252^0.5 -> 0.34284349
A96: 44148 | B96: 25055011 | D96: =B96 -> 25055011 | E96: =IF(MONTH(A96)=MONTH(A95),E95,D95) -> 17677657 | F96: =B96-C96-D95 -> 236496.14 | G96: =F96/B95 -> 0.0095290208 | J96: =IF(MONTH(A96)=MONTH(A95),J95+F96,F96) -> 877354.09 | K96: =(1+K95)*(1+G96)-1 -> 0.042859242 | L96: =1+G96 -> 1.009529 | M96: =PRODUCT($L$2:L96)-1 -> 0.10425482 | N96: =PRODUCT($L$2:L96)-1 -> 0.10425482 | O96: =AVERAGE($G$2:G96)*252 -> 0.32156563 | P96: =STDEV($G$2:G96)*252^0.5 -> 0.34128544
A97: 44151 | B97: 25449314 | D97: =B97 -> 25449314 | E97: =IF(MONTH(A97)=MONTH(A96),E96,D96) -> 17677657 | F97: =B97-C97-D96 -> 394303.5 | G97: =F97/B96 -> 0.015737511 | J97: =IF(MONTH(A97)=MONTH(A96),J96+F97,F97) -> 1271657.6 | K97: =(1+K96)*(1+G97)-1 -> 0.059271251 | L97: =1+G97 -> 1.0157375 | M97: =PRODUCT($L$2:L97)-1 -> 0.12163304 | N97: =PRODUCT($L$2:L97)-1 -> 0.12163304 | O97: =AVERAGE($G$2:G97)*252 -> 0.35952695 | P97: =STDEV($G$2:G97)*252^0.5 -> 0.34029203
A98: 44152 | B98: 25793136 | D98: =B98 -> 25793136 | E98: =IF(MONTH(A98)=MONTH(A97),E97,D97) -> 17677657 | F98: =B98-C98-D97 -> 343822.24 | G98: =F98/B97 -> 0.013510079 | J98: =IF(MONTH(A98)=MONTH(A97),J97+F98,F98) -> 1615479.8 | K98: =(1+K97)*(1+G98)-1 -> 0.073582089 | L98: =1+G98 -> 1.0135101 | M98: =PRODUCT($L$2:L98)-1 -> 0.13678639 | N98: =PRODUCT($L$2:L98)-1 -> 0.13678639 | O98: =AVERAGE($G$2:G98)*252 -> 0.39091884 | P98: =STDEV($G$2:G98)*252^0.5 -> 0.33907485
A99: 44153 | B99: 25818408 | D99: =B99 -> 25818408 | E99: =IF(MONTH(A99)=MONTH(A98),E98,D98) -> 17677657 | F99: =B99-C99-D98 -> 25271.74 | G99: =F99/B98 -> 0.00097978546 | J99: =IF(MONTH(A99)=MONTH(A98),J98+F99,F99) -> 1640751.6 | K99: =(1+K98)*(1+G99)-1 -> 0.074633969 | L99: =1+G99 -> 1.0009798 | M99: =PRODUCT($L$2:L99)-1 -> 0.1379002 | N99: =PRODUCT($L$2:L99)-1 -> 0.1379002 | O99: =AVERAGE($G$2:G99)*252 -> 0.38944932 | P99: =STDEV($G$2:G99)*252^0.5 -> 0.33732375
A100: 44154 | B100: 26452344 | D100: =B100 -> 26452344 | E100: =IF(MONTH(A100)=MONTH(A99),E99,D99) -> 17677657 | F100: =B100-C100-D99 -> 633936.39 | G100: =F100/B99 -> 0.024553659 | J100: =IF(MONTH(A100)=MONTH(A99),J99+F100,F100) -> 2274688 | K100: =(1+K99)*(1+G100)-1 -> 0.10102017 | L100: =1+G100 -> 1.0245537 | M100: =PRODUCT($L$2:L100)-1 -> 0.16583981 | N100: =PRODUCT($L$2:L100)-1 -> 0.16583981 | O100: =AVERAGE($G$2:G100)*252 -> 0.44801571 | P100: =STDEV($G$2:G100)*252^0.5 -> 0.33759995
A101: 44155 | B101: 26839523 | D101: =B101 -> 26839523 | E101: =IF(MONTH(A101)=MONTH(A100),E100,D100) -> 17677657 | F101: =B101-C101-D100 -> 387178.77 | G101: =F101/B100 -> 0.014636841 | J101: =IF(MONTH(A101)=MONTH(A100),J100+F101,F101) -> 2661866.7 | K101: =(1+K100)*(1+G101)-1 -> 0.11713562 | L101: =1+G101 -> 1.0146368 | M101: =PRODUCT($L$2:L101)-1 -> 0.18290403 | N101: =PRODUCT($L$2:L101)-1 -> 0.18290403 | O101: =AVERAGE($G$2:G101)*252 -> 0.48042039 | P101: =STDEV($G$2:G101)*252^0.5 -> 0.33651028
A102: 44158 | B102: 27430907 | D102: =B102 -> 27430907 | E102: =IF(MONTH(A102)=MONTH(A101),E101,D101) -> 17677657 | F102: =B102-C102-D101 -> 591383.71 | G102: =F102/B101 -> 0.022034062 | J102: =IF(MONTH(A102)=MONTH(A101),J101+F102,F102) -> 3253250.4 | K102: =(1+K101)*(1+G102)-1 -> 0.14175066 | L102: =1+G102 -> 1.0220341 | M102: =PRODUCT($L$2:L102)-1 -> 0.20896821 | N102: =PRODUCT($L$2:L102)-1 -> 0.20896821 | O102: =AVERAGE($G$2:G102)*252 -> 0.53063983 | P102: =STDEV($G$2:G102)*252^0.5 -> 0.33632957
... A104: 44160 | B104: 27698159 | D104: =B104 -> 27698159 | E104: =IF(MONTH(A104)=MONTH(A103),E103,D103) -> 17677657 | F104: =B104-C104-D103 -> -275104.26 | G104: =F104/B103 -> -0.0098345429 | J104: =IF(MONTH(A104)=MONTH(A103),J103+F104,F104) -> 3520502.9 | K104: =(1+K103)*(1+G104)-1 -> 0.15287445 | L104: =1+G104 -> 0.99016546 | M104: =PRODUCT($L$2:L104)-1 -> 0.22074688 | N104: =PRODUCT($L$2:L104)-1 -> 0.22074688 | O104: =AVERAGE($G$2:G104)*252 -> 0.5446485 | P104: =STDEV($G$2:G104)*252^0.5 -> 0.33469699
A105: 44161 | B105: 27769610 | D105: =B105 -> 27769610 | E105: =IF(MONTH(A105)=MONTH(A104),E104,D104) -> 17677657 | F105: =B105-C105-D104 -> 71450.24 | G105: =F105/B104 -> 0.0025796025 | J105: =IF(MONTH(A105)=MONTH(A104),J104+F105,F105) -> 3591953.1 | K105: 0.1559 | L105: =1+G105 -> 1.0025796 | M105: =PRODUCT($L$2:L105)-1 -> 0.22389592 | N105: =PRODUCT($L$2:L105)-1 -> 0.22389592 | O105: =AVERAGE($G$2:G105)*252 -> 0.54566207 | P105: =STDEV($G$2:G105)*252^0.5 -> 0.33306892
A106: 44162 | B106: 28339483 | D106: =B106 -> 28339483 | E106: =IF(MONTH(A106)=MONTH(A105),E105,D105) -> 17677657 | F106: =B106-C106-D105 -> 569873.77 | G106: =F106/B105 -> 0.02052149 | J106: =IF(MONTH(A106)=MONTH(A105),J105+F106,F106) -> 4161826.9 | K106: =(1+K105)*(1+G106)-1 -> 0.17962079 | L106: =1+G106 -> 1.0205215 | M106: =PRODUCT($L$2:L106)-1 -> 0.24901209 | N106: =PRODUCT($L$2:L106)-1 -> 0.24901209 | O106: =AVERAGE($G$2:G106)*252 -> 0.58971687 | P106: =STDEV($G$2:G106)*252^0.5 -> 0.33268138
A107: 44165 | B107: 27946966 | D107: =B107 -> 27946966 | E107: =IF(MONTH(A107)=MONTH(A106),E106,D106) -> 17677657 | F107: =B107-C107-D106 -> -392517.59 | G107: =F107/B106 -> -0.013850556 | J107: =IF(MONTH(A107)=MONTH(A106),J106+F107,F107) -> 3769309.3 | K107: 0.1632 | L107: =1+G107 -> 0.98614944 | M107: =PRODUCT($L$2:L107)-1 -> 0.23171258 | N107: =PRODUCT($L$2:L107)-1 -> 0.23171258 | O107: =AVERAGE($G$2:G107)*252 -> 0.55122577 | P107: =STDEV($G$2:G107)*252^0.5 -> 0.33203318
A108: 44166 | B108: 27413132 | C108: 75000 | D108: =B108 -> 27413132 | E108: =IF(MONTH(A108)=MONTH(A107),E107,D107) -> 27946966 | F108: =B108-C108-D107 -> -608834.16 | G108: -0.0217 | J108: =IF(MONTH(A108)=MONTH(A107),J107+F108,F108) -> -608834.16 | K108: =G108 -> -0.0217 | L108: =1+G108 -> 0.9783 | M108: =PRODUCT($L$2:L108)-1 -> 0.20498441 | N108: =PRODUCT($L$2:L108)-1 -> 0.20498441 | O108: =AVERAGE($G$2:G108)*252 -> 0.49496758 | P108: =STDEV($G$2:G108)*252^0.5 -> 0.33249036
A109: 44167 | B109: 27385883 | D109: =B109 -> 27385883 | E109: =IF(MONTH(A109)=MONTH(A108),E108,D108) -> 27946966 | F109: =B109-C109-D108 -> -27248.39 | G109: =F109/B108 -> -0.00099399041 | J109: =IF(MONTH(A109)=MONTH(A108),J108+F109,F109) -> -636082.55 | K109: =(1+K108)*(1+G109)-1 -> -0.022672421 | L109: =1+G109 -> 0.99900601 | M109: =PRODUCT($L$2:L109)-1 -> 0.20378667 | N109: =PRODUCT($L$2:L109)-1 -> 0.20378667 | O109: =AVERAGE($G$2:G109)*252 -> 0.48806524 | P109: =STDEV($G$2:G109)*252^0.5 -> 0.33096386
A110: 44168 | B110: 27866525 | D110: =B110 -> 27866525 | E110: =IF(MONTH(A110)=MONTH(A109),E109,D109) -> 27946966 | F110: =B110-C110-D109 -> 480641.52 | G110: =F110/B109 -> 0.017550704 | J110: =IF(MONTH(A110)=MONTH(A109),J109+F110,F110) -> -155441.03 | K110: =(1+K109)*(1+G110)-1 -> -0.0055196341 | L110: =1+G110 -> 1.0175507 | M110: =PRODUCT($L$2:L110)-1 -> 0.22491397 | N110: =PRODUCT($L$2:L110)-1 -> 0.22491397 | O110: =AVERAGE($G$2:G110)*252 -> 0.52416351 | P110: =STDEV($G$2:G110)*252^0.5 -> 0.33028243
A111: 44169 | B111: 27947341 | D111: =B111 -> 27947341 | E111: =IF(MONTH(A111)=MONTH(A110),E110,D110) -> 27946966 | F111: =B111-C111-D110 -> 80816.2 | G111: =F111/B110 -> 0.0029001176 | J111: =IF(MONTH(A111)=MONTH(A110),J110+F111,F111) -> -74624.83 | K111: -0.0027 | L111: =1+G111 -> 1.0029001 | M111: =PRODUCT($L$2:L111)-1 -> 0.22846637 | N111: =PRODUCT($L$2:L111)-1 -> 0.22846637 | O111: =AVERAGE($G$2:G111)*252 -> 0.5260423 | P111: =STDEV($G$2:G111)*252^0.5 -> 0.32876622
A112: 44172 | B112: 28435336 | D112: =B112 -> 28435336 | E112: =IF(MONTH(A112)=MONTH(A111),E111,D111) -> 27946966 | F112: =B112-C112-D111 -> 487995.33 | G112: =F112/B111 -> 0.017461244 | J112: =IF(MONTH(A112)=MONTH(A111),J111+F112,F112) -> 413370.5 | K112: 0.0148 | L112: =1+G112 -> 1.0174612 | M112: =PRODUCT($L$2:L112)-1 -> 0.24991692 | N112: =PRODUCT($L$2:L112)-1 -> 0.24991692 | O112: =AVERAGE($G$2:G112)*252 -> 0.56094492 | P112: =STDEV($G$2:G112)*252^0.5 -> 0.32808719
A113: 44173 | B113: 28815379 | D113: =B113 -> 28815379 | E113: =IF(MONTH(A113)=MONTH(A112),E112,D112) -> 27946966 | F113: =B113-C113-D112 -> 380042.8 | G113: =F113/B112 -> 0.013365159 | J113: =IF(MONTH(A113)=MONTH(A112),J112+F113,F113) -> 793413.3 | K113: 0.0283 | L113: =1+G113 -> 1.0133652 | M113: =PRODUCT($L$2:L113)-1 -> 0.26662226 | N113: =PRODUCT($L$2:L113)-1 -> 0.26662226 | O113: =AVERAGE($G$2:G113)*252 -> 0.58600809 | P113: =STDEV($G$2:G113)*252^0.5 -> 0.3270331
A114: 44174 | B114: 27726628 | D114: =B114 -> 27726628 | E114: =IF(MONTH(A114)=MONTH(A113),E113,D113) -> 27946966 | F114: =B114-C114-D113 -> -1088750.7 | G114: =F114/B113 -> -0.037783667 | J114: =IF(MONTH(A114)=MONTH(A113),J113+F114,F114) -> -295337.4 | K114: -0.0105 | L114: =1+G114 -> 0.96221633 | M114: =PRODUCT($L$2:L114)-1 -> 0.21876462 | N114: =PRODUCT($L$2:L114)-1 -> 0.21876462 | O114: =AVERAGE($G$2:G114)*252 -> 0.49656126 | P114: =STDEV($G$2:G114)*252^0.5 -> 0.33103378
A115: 44175 | B115: 28038440 | D115: =B115 -> 28038440 | E115: =IF(MONTH(A115)=MONTH(A114),E114,D114) -> 27946966 | F115: =B115-C115-D114 -> 311811.17 | G115: =F115/B114 -> 0.01124591 | J115: =IF(MONTH(A115)=MONTH(A114),J114+F115,F115) -> 16473.77 | K115: =(1+K114)*(1+G115)-1 -> 0.00062782804 | L115: =1+G115 -> 1.0112459 | M115: =PRODUCT($L$2:L115)-1 -> 0.23247074 | N115: =PRODUCT($L$2:L115)-1 -> 0.23247074 | O115: =AVERAGE($G$2:G115)*252 -> 0.51706484 | P115: =STDEV($G$2:G115)*252^0.5 -> 0.32985418
...

Sheet Mark to Market
A1: Mark to Market Breakdown
A2: Symbol | B2: AssetClass | C2: Currency | D2: Current Quantity | E2: Current Price | F2: FCY_marketvalue | G2: Conversion Rate | H2: Final_marketvalue | I2: Weightage
A3: SGOV | B3: Bonds | C3: USD | D3: 207975 | E3: 100.51 | F3: 20903567 | G3: 1 | H3: 20903567 | I3: 100

Sheet Daily P&L breakdown
A1: Date | B1: ETFs | C1: Stocks_int | D1: Stocks | E1: Bonds | F1: Commodities | G1: Future | H1: Option | I1: Crypto | J1: Others | K1: Others2 | L1: Total
A2: ='Historical NAV'!A994 -> 45413 | B2: -1970094.7 | C2: 0 | D2: -313917.4 | E2: -5998.97 | F2: 122642.36 | H2: 0 | L2: =SUM(B2:K2) -> -2167368.7
A3: ='Historical NAV'!A995 -> 45414 | B3: 2436118.4 | C3: 23250.47 | D3: 259278.4 | E3: 51716.52 | F3: 10509.84 | H3: 0 | L3: =SUM(B3:K3) -> 2780873.6
A4: ='Historical NAV'!A996 -> 45415 | B4: 2771769.6 | C4: 154804.98 | D4: 277584.8 | E4: 50177.07 | F4: 13860.98 | H4: 0 | L4: =SUM(B4:K4) -> 3268197.5
A5: ='Historical NAV'!A997 -> 45418 | B5: 2346005.5 | C5: -119425.76 | D5: 312983.4 | E5: 15660.96 | F5: 137325.26 | H5: 0 | L5: =SUM(B5:K5) -> 2692549.4
A6: ='Historical NAV'!A998 -> 45419 | B6: -507593.41 | C6: 23032.62 | D6: -148132.4 | E6: 34299.14 | F6: -25473.91 | H6: 0 | L6: =SUM(B6:K6) -> -623867.96
A7: ='Historical NAV'!A999 -> 45420 | B7: 152959.43 | C7: -76052.85 | D7: -13262.8 | E7: -19711.85 | F7: -73297.26 | H7: 0 | L7: =SUM(B7:K7) -> -29365.33
A8: ='Historical NAV'!A1000 -> 45421 | B8: 139090.48 | C8: 202257.72 | D8: -155511 | E8: 9588.08 | F8: 204666.24 | H8: 0 | L8: =SUM(B8:K8) -> 400091.52
A9: ='Historical NAV'!A1001 -> 45422 | B9: 653912.02 | C9: 562316.1 | D9: 105635.4 | E9: -24363.21 | F9: 58651.75 | H9: 0 | L9: =SUM(B9:K9) -> 1356152.1
A10: ='Historical NAV'!A1002 -> 45425 | B10: 91627.43 | C10: -153587.82 | D10: 48661.4 | E10: 4116.74 | F10: -155030.89 | H10: 0 | L10: =SUM(B10:K10) -> -164213.14
A11: ='Historical NAV'!A1003 -> 45426 | B11: 1227745 | C11: -179070.84 | D11: 89383.8 | E11: 20723.99 | F11: 101843.55 | H11: 0 | L11: =SUM(B11:K11) -> 1260625.5
A12: ='Historical NAV'!A1004 -> 45427 | B12: 2264910.6 | C12: -2106.92 | D12: 305791.6 | E12: 64874.77 | F12: 146691.54 | H12: 0 | L12: =SUM(B12:K12) -> 2780161.6
A13: ='Historical NAV'!A1005 -> 45428 | B13: -599659.93 | C13: 72779.26 | D13: -25311.4 | E13: -13198.09 | F13: -45519.6 | H13: 0 | L13: =SUM(B13:K13) -> -610909.76
... A32: ='Historical NAV'!A1024 -> 45455 | B32: 1455137.8 | C32: -15513.11 | D32: 478169.94 | E32: 45660.71 | F32: 63545.75 | H32: 21422.55 | L32: =SUM(B32:K32) -> 2048423.6
A33: ='Historical NAV'!A1025 -> 45456 | B33: -72270.02 | C33: -139433.15 | D33: 455390.56 | E33: 31311.89 | F33: -191213.19 | G33: -300 | H33: 39563.89 | L33: =SUM(B33:K33) -> 123049.98
A34: ='Historical NAV'!A1026 -> 45457 | B34: -222728.21 | C34: -102600.35 | D34: 231071.47 | E34: -4070.66 | F34: 109071.7 | G34: 162.8 | H34: 3590.57 | L34: =SUM(B34:K34) -> 14497.32
A35: ='Historical NAV'!A1027 -> 45460 | B35: 1143293.3 | C35: -150055.4 | D35: -57615 | E35: -23422.15 | F35: -116714.4 | G35: 0 | H35: 28076.3 | L35: =SUM(B35:K35) -> 823562.61
A36: ='Historical NAV'!A1028 -> 45461 | B36: 542224.08 | C36: -22841.94 | D36: 520943.88 | E36: 31896.94 | F36: 109318.26 | G36: -586.5 | H36: 13783.84 | L36: =SUM(B36:K36) -> 1194738.6
A37: ='Historical NAV'!A1029 -> 45462 | B37: 0 | C37: 889806.69 | D37: 0 | E37: 0 | F37: 0 | G37: 0 | H37: -2034.45 | L37: =SUM(B37:K37) -> 887772.24
A38: ='Historical NAV'!A1030 -> 45463 | B38: -686347.1 | C38: 300120.46 | D38: -762729.19 | E38: -19123.09 | F38: 194246.51 | G38: 2971.88 | H38: -6859.5 | L38: =SUM(B38:K38) -> -977720.03
A39: ='Historical NAV'!A1031 -> 45464 | B39: -424152.6 | C39: -521624.46 | D39: -499358.56 | E39: 5989.15 | F39: -255987.4 | G39: 0 | H39: 31958.5 | L39: =SUM(B39:K39) -> -1663175.4
A40: ='Historical NAV'!A1032 -> 45467 | B40: -814310 | C40: 50237.97 | D40: -1243576.4 | E40: 3747.87 | F40: 78430.83 | G40: 0 | H40: 8300.73 | L40: =SUM(B40:K40) -> -1917169
A41: ='Historical NAV'!A1033 -> 45468 | B41: 780248.49 | C41: 65843.85 | D41: 1340503.9 | E41: 50.64 | F41: -172901.05 | G41: 0 | H41: -71164.1 | L41: =SUM(B41:K41) -> 1942581.7
A42: ='Historical NAV'!A1034 -> 45469 | B42: -134543.06 | C42: -126431.6 | D42: 33773.99 | E42: -34214.78 | F42: -119773.58 | G42: 0 | H42: 14710.28 | L42: =SUM(B42:K42) -> -366478.75
A43: ='Historical NAV'!A1035 -> 45470 | B43: 136300.68 | C43: -708946.39 | D43: -597843 | E43: 13661.86 | F43: 132769.33 | G43: 0 | H43: 186852.56 | L43: =SUM(B43:K43) -> -837204.96
A44: ='Historical NAV'!A1036 -> 45471 | B44: 247789.23 | C44: 466048.59 | D44: 23974.8 | E44: -33182.84 | F44: 49235.3 | G44: -11275 | H44: 65841.58 | L44: =SUM(B44:K44) -> 808431.66
... A56: ='Historical NAV'!A1048 -> 45489 | B56: 1004163.4 | C56: -250796.76 | D56: -195364.75 | E56: 84453.55 | F56: 302809.42 | G56: 1035 | H56: 5208.3 | L56: =SUM(B56:K56) -> 951508.17
A57: ='Historical NAV'!A1049 -> 45490 | B57: =-3359461.34-66757.2 -> -3426218.5 | C57: -613418.23 | D57: -2253430.8 | E57: -22051.99 | F57: -282468.43 | G57: 0 | H57: -22412.47 | L57: =SUM(B57:K57) -> -6620000.5
A58: ='Historical NAV'!A1050 -> 45491 | B58: -972898.82 | C58: 99684.86 | D58: 114083.79 | E58: -64523.55 | F58: -155600.85 | G58: 0 | H58: 107578.22 | L58: =SUM(B58:K58) -> -871676.35
A59: ='Historical NAV'!A1051 -> 45492 | B59: -1228709 | C59: -476140.2 | D59: -728557.26 | E59: -38397.45 | F59: -436590.09 | G59: -312.35 | H59: 23373.75 | L59: =SUM(B59:K59) -> -2885332.6
A60: ='Historical NAV'!A1052 -> 45495 | B60: 1378132.4 | C60: 144299.29 | D60: 945666.4 | E60: 20972.52 | F60: -12091.11 | G60: 637.5 | H60: 44207.43 | L60: =SUM(B60:K60) -> 2521824.4
A61: ='Historical NAV'!A1053 -> 45496 | B61: -524853.7 | C61: -80446.59 | D61: -131135.23 | E61: -11455.05 | F61: -36991.83 | G61: 2156.25 | H61: 3964.32 | L61: =SUM(B61:K61) -> -778761.83
A62: ='Historical NAV'!A1054 -> 45497 | B62: -2418257.9 | C62: -12538.97 | D62: -1663639.3 | E62: -102396.6 | F62: -154432.84 | G62: 441086.85 | H62: 128974.68 | L62: =SUM(B62:K62) -> -3781204.1
A63: ='Historical NAV'!A1055 -> 45498 | B63: -139113.7 | C63: -333649.61 | D63: -233070.94 | E63: 35824.52 | F63: -338913.56 | G63: 116466.67 | H63: 87157.4 | L63: =SUM(B63:K63) -> -805299.22
A64: ='Historical NAV'!A1056 -> 45499 | B64: 1354522.6 | C64: 29227.42 | D64: 201949.39 | E64: 72407.7 | F64: 307604.64 | G64: 64760.25 | H64: 38479.95 | L64: =SUM(B64:K64) -> 2068952
A65: ='Historical NAV'!A1057 -> 45502 | B65: -302201.08 | C65: 297398.18 | D65: =-281644.21-90000 -> -371644.21 | E65: 19921.18 | F65: -64154.74 | G65: =-90468.12+90000 -> -468.12 | H65: 66591.13 | L65: =SUM(B65:K65) -> -354557.66
A66: ='Historical NAV'!A1058 -> 45503 | B66: -530420.34 | C66: -277334.39 | D66: -1354623.5 | E66: 21589.52 | F66: 163519.92 | G66: -175465 | H66: 5932.33 | L66: =SUM(B66:K66) -> -2146801.5
A67: ='Historical NAV'!A1059 -> 45504 | B67: 2049105.6 | C67: 237889.3 | D67: 2435149.3 | E67: 102279.83 | F67: 519853.99 | G67: 337501.95 | H67: 171208.22 | L67: =SUM(B67:K67) -> 5852988.2
A68: ='Historical NAV'!A1060 -> 45505 | B68: -2866463.5 | C68: 29753.27 | D68: -1512431 | E68: -38964.42 | F68: -428467.99 | G68: 180673.21 | H68: -77397.23 | L68: =SUM(B68:K68) -> -4713297.7
A69: ='Historical NAV'!A1061 -> 45506 | B69: -2717185.6 | C69: -334600.58 | D69: -812418.47 | E69: 65754.13 | F69: -268584.16 | G69: 941518.65 | H69: -54915.51 | L69: =SUM(B69:K69) -> -3180431.5
A70: ='Historical NAV'!A1062 -> 45509 | B70: -2681747.3 | C70: -538666.94 | D70: -1093972.5 | E70: -69279.19 | F70: -345388.99 | G70: -555138.85 | H70: -62520.63 | L70: =SUM(B70:K70) -> -5346714.4
A71: ='Historical NAV'!A1063 -> 45510 | B71: 819532.69 | C71: -120457.14 | D71: 993604.43 | E71: -57480.54 | F71: -158590.81 | G71: -222470 | H71: 179060.06 | L71: =SUM(B71:K71) -> 1433198.7
A72: ='Historical NAV'!A1064 -> 45511 | B72: -741416.51 | C72: 282372.62 | D72: -801311.13 | E72: -46727.43 | F72: 12321.28 | G72: -81949.15 | H72: -43054.48 | L72: =SUM(B72:K72) -> -1419764.8
A73: ='Historical NAV'!A1065 -> 45512 | B73: 2494570.8 | C73: 111792.2 | D73: 1452676.5 | E73: 14118.44 | F73: 286824.89 | G73: 12563.74 | H73: 96830.97 | L73: =SUM(B73:K73) -> 4469377.5
A74: ='Historical NAV'!A1066 -> 45513 | B74: 254023.54 | C74: 162412.5 | D74: 136041.5 | E74: 75653.37 | F74: 117610.09 | G74: 1350 | H74: 32782.22 | L74: =SUM(B74:K74) -> 779873.22
A75: ='Historical NAV'!A1067 -> 45516 | B75: 36284.64 | C75: -20999.51 | D75: 639924.48 | E75: 23748.31 | F75: 235321.23 | G75: -9675 | H75: 33696.2 | L75: =SUM(B75:K75) -> 938300.35
A76: ='Historical NAV'!A1068 -> 45517 | B76: 1411495.7 | C76: 144397.43 | D76: 1280664.5 | E76: 253888.39 | F76: -13001.43 | G76: 19500 | H76: 67528.36 | L76: =SUM(B76:K76) -> 3164472.9
A77: ='Historical NAV'!A1069 -> 45518 | B77: 151595.46 | C77: -7803.66 | D77: 155845.5 | E77: -11950.99 | F77: -143661.4 | G77: -2375 | H77: 27355.55 | L77: =SUM(B77:K77) -> 169005.46
... A90: ='Historical NAV'!A1082 -> 45537 | B90: 0 | C90: -262789.72 | D90: -2600 | E90: 0 | F90: -31890.57 | G90: 0 | H90: 7688.81 | L90: =SUM(B90:K90) -> -289591.48
A91: ='Historical NAV'!A1083 -> 45538 | B91: =-2832102.36-664686.16-664686.16 -> -4161474.7 | C91: -40860.63 | D91: -2305481.4 | E91: -4630.73 | F91: -173727.58 | G91: 664686.16 | H91: -206661.72 | L91: =SUM(B91:K91) -> -6228150.6
A92: ='Historical NAV'!A1084 -> 45539 | B92: -258381.05 | C92: -453396.63 | D92: -191703.86 | E92: 103336.49 | F92: -173381.46 | G92: -334008.85 | H92: -5606.64 | L92: =SUM(B92:K92) -> -1313142
A93: ='Historical NAV'!A1085 -> 45540 | B93: -370947.86 | C93: 12143.13 | D93: 259847.78 | E93: 75017.48 | F93: 67627.64 | G93: -47087.5 | H93: 83796.75 | L93: =SUM(B93:K93) -> 80397.42
A94: ='Historical NAV'!A1086 -> 45541 | B94: -3943211.4 | C94: -148358.25 | D94: =-2336944.59 -> -2336944.6 | E94: 30478.1 | F94: -386720 | G94: 248957.25 | H94: -71439.02 | L94: -3459052.6
A95: ='Historical NAV'!A1087 -> 45544 | B95: 985778.42 | C95: -311038.5 | D95: 907811.22 | E95: 51682.44 | F95: 88210.07 | G95: -25993.68 | H95: 257227.25 | L95: =SUM(B95:K95) -> 1953677.2
A96: ='Historical NAV'!A1088 -> 45545 | B96: 365537.75 | C96: -4488.36 | D96: 531786.14 | E96: 101103.65 | F96: 78131.47 | G96: 134199.5 | H96: 173820.79 | L96: =SUM(B96:K96) -> 1380090.9
A97: ='Historical NAV'!A1089 -> 45546 | B97: 1178064 | C97: -74849.11 | D97: 1787279.8 | E97: 23092.05 | F97: -8453.45 | G97: 110400.6 | H97: 283492.65 | L97: =SUM(B97:K97) -> 3299026.5
A98: ='Historical NAV'!A1090 -> 45547 | B98: 725486.46 | C98: 114794.99 | D98: 448216 | E98: 490.28 | F98: 285566.6 | G98: 59322.8 | H98: 21104.94 | L98: =SUM(B98:K98) -> 1654982.1
A99: ='Historical NAV'!A1091 -> 45548 | B99: 796371.79 | C99: 86072.04 | D99: 96675.5 | E99: 59012.69 | F99: 194640.51 | G99: 43750 | H99: 75521.03 | L99: =SUM(B99:K99) -> 1352043.6
A100: ='Historical NAV'!A1092 -> 45551 | B100: 40075.72 | C100: 5425.35 | D100: -610742.75 | E100: 101513.05 | F100: -22087.02 | G100: -32433.6 | H100: 77321.72 | L100: =SUM(B100:K100) -> -440927.53
A101: ='Historical NAV'!A1093 -> 45552 | B101: 238992.42 | C101: 190138.11 | D101: -302406 | E101: -7132 | F101: -16714 | G101: -20725 | H101: 39600.5 | L101: =SUM(B101:K101) -> 121754.03
A102: ='Historical NAV'!A1094 -> 45553 | B102: -386828.74 | C102: -2084.19 | D102: -387125.5 | E102: -70956.96 | F102: -97745.95 | G102: -63000 | H102: 13269.69 | L102: =SUM(B102:K102) -> -994471.65
A103: ='Historical NAV'!A1095 -> 45554 | B103: 1943878.6 | C103: 317574.7 | D103: 1281066 | E103: 56955.1 | F103: 315544.62 | G103: 350700 | H103: 78405.06 | L103: =SUM(B103:K103) -> 4344124.1
A104: ='Historical NAV'!A1096 -> 45555 | B104: -398442.01 | C104: 53913.56 | D104: -417166 | E104: -14179.89 | F104: 192718.07 | G104: -13738 | H104: 72404.29 | L104: =SUM(B104:K104) -> -524489.98
A105: ='Historical NAV'!A1097 -> 45558 | B105: 146450.64 | C105: -48491.59 | D105: 90587 | E105: -14089.28 | F105: 71626.07 | G105: 46100 | H105: 63562.59 | L105: =SUM(B105:K105) -> 355745.43
A106: ='Historical NAV'!A1098 -> 45559 | B106: 346136.06 | C106: 589312.82 | D106: 1207125.3 | E106: 35031.96 | F106: 244700.59 | G106: 86300 | H106: 56359.87 | L106: =SUM(B106:K106) -> 2564966.6
... A110: ='Historical NAV'!A1102 -> 45565 | B110: 185466.61 | C110: 207903.42 | D110: -383396.17 | E110: -30989.53 | F110: -155972.76 | G110: 90150 | H110: 97332.23 | L110: =SUM(B110:K110) -> 10493.8
A111: ='Historical NAV'!A1103 -> 45566 | B111: =-663075.12 -> -663075.12 | C111: 35058.36 | D111: -1181063 | E111: -4523.57 | F111: 156632.14 | G111: =-482500 -> -482500 | H111: -113084.87 | L111: =SUM(B111:K111) -> -2252556.1
A112: ='Historical NAV'!A1104 -> 45567 | B112: 129173.89 | C112: 787345.39 | D112: 790934 | E112: -23494.48 | F112: -7405.95 | G112: 49650 | H112: 88317.66 | L112: =SUM(B112:K112) -> 1814520.5
A113: ='Historical NAV'!A1105 -> 45568 | B113: -72995.12 | C113: -227846.34 | D113: 1208595 | E113: -77635.46 | F113: 6538.23 | G113: -48800 | H113: 17024.62 | L113: =SUM(B113:K113) -> 804880.93
A114: ='Historical NAV'!A1106 -> 45569 | B114: 814663.82 | C114: 327280.73 | D114: 650723 | E114: -65657.69 | F114: -16664.88 | G114: 432800 | H114: 219486.03 | L114: =SUM(B114:K114) -> 2362631
A115: ='Historical NAV'!A1107 -> 45572 | B115: =-787155.28 -> -787155.28 | C115: 228783.94 | D115: 862488 | E115: -98023.88 | F115: -47939.23 | G115: =-438800 -> -438800 | H115: -64138.31 | L115: =SUM(B115:K115) -> -344784.76
A116: ='Historical NAV'!A1108 -> 45573 | B116: 508166.38 | C116: -1234274.9 | D116: 1352058 | E116: 33751.57 | F116: -184725.8 | G116: 628575 | H116: -80179.63 | L116: =SUM(B116:K116) -> 1023370.7
A117: ='Historical NAV'!A1109 -> 45574 | B117: 584082.42 | C117: -226459.83 | D117: 111703 | E117: -40715.68 | F117: -77974.92 | G117: 193775 | H117: 135253.46 | L117: =SUM(B117:K117) -> 679663.45
A118: ='Historical NAV'!A1110 -> 45575 | B118: -171443.82 | C118: 366406.27 | D118: 331557.12 | E118: -11385.25 | F118: 124601.37 | G118: -62175 | H118: 73283.94 | L118: =SUM(B118:K118) -> 650844.63
A119: ='Historical NAV'!A1111 -> 45576 | B119: 639787.93 | C119: 30100.25 | D119: 544800 | E119: 34291.13 | F119: 260564.65 | G119: 70425 | H119: 102309.62 | L119: =SUM(B119:K119) -> 1682278.6
A120: ='Historical NAV'!A1112 -> 45579 | B120: 533563.27 | C120: 31647.89 | D120: 806802.36 | E120: 4505.13 | F120: 16007.6 | G120: 252000 | H120: 163510.93 | L120: =SUM(B120:K120) -> 1808037.2
A121: ='Historical NAV'!A1113 -> 45580 | B121: -859528.7 | C121: -468564.75 | D121: -1803161 | E121: 82934.03 | F121: 24528.85 | G121: -352725 | H121: -133277.53 | L121: =SUM(B121:K121) -> -3509794.1
A122: ='Historical NAV'!A1114 -> 45581 | B122: 441591.54 | C122: 6801.12 | D122: 934222 | E122: 51564.73 | F122: 104696.63 | G122: 49000 | H122: 52165.69 | L122: =SUM(B122:K122) -> 1640041.7
A123: ='Historical NAV'!A1115 -> 45582 | B123: -28981.81 | C123: -146782.86 | D123: 1992422 | E123: -126686.72 | F123: 121981.88 | G123: 15700 | H123: 22089.52 | L123: =SUM(B123:K123) -> 1849742
A124: ='Historical NAV'!A1116 -> 45583 | B124: 226518.52 | C124: 379888.11 | D124: -247478.46 | E124: 27380.4 | F124: 201879.84 | G124: 166900 | H124: 274070.6 | L124: =SUM(B124:K124) -> 1029159
A125: ='Historical NAV'!A1117 -> 45586 | B125: -411088.94 | C125: -166633.6 | D125: 1242817 | E125: -174063.64 | F125: -20919.05 | G125: 18400 | H125: 9413.22 | L125: =SUM(B125:K125) -> 497924.99
A126: ='Historical NAV'!A1118 -> 45587 | B126: -236995.67 | C126: -14826.97 | D126: -348062.46 | E126: -15753.37 | F126: 153288.51 | G126: 19500 | H126: 35246.9 | L126: =SUM(B126:K126) -> -407603.06
A127: ='Historical NAV'!A1119 -> 45588 | B127: -792837.52 | C127: 70309.6 | D127: -738671 | E127: -92882.94 | F127: -244991.86 | G127: -495300 | H127: -88275.82 | L127: =SUM(B127:K127) -> -2382649.5
... A132: ='Historical NAV'!A1124 -> 45595 | B132: -333044.94 | C132: -350647.93 | D132: -693918.08 | E132: -10080.69 | F132: 74953.21 | G132: -112200 | H132: 138503.46 | L132: =SUM(B132:K132) -> -1286435
A133: ='Historical NAV'!A1125 -> 45596 | B133: =-1225643.82-237075*2 -> -1699793.8 | C133: -80493.38 | D133: -1797661 | E133: -25319.05 | F133: -306924.19 | G133: =-711225+237075*2 -> -237075 | H133: 43642.36 | L133: =SUM(B133:K133) -> -4103624.1
A134: ='Historical NAV'!A1126 -> 45597 | B134: 368575.08 | C134: 199249.41 | D134: 779788.92 | E134: -157225.79 | F134: -42840.24 | G134: 194025 | H134: 8853.99 | L134: =SUM(B134:K134) -> 1350426.4
A135: ='Historical NAV'!A1127 -> 45600 | B135: -93872.68 | C135: 66090.24 | D135: -20878.6 | E135: 156830.58 | F135: -6886.84 | G135: -111475 | H135: 44748.11 | L135: =SUM(B135:K135) -> 34555.81
A136: ='Historical NAV'!A1128 -> 45601 | B136: 1000787.1 | C136: 332968.81 | D136: 1254812 | E136: 91316.99 | F136: 98319.17 | G136: 418912.5 | H136: -24695.65 | L136: =SUM(B136:K136) -> 3172420.9
A137: ='Historical NAV'!A1129 -> 45602 | B137: 2719948.9 | C137: -316051.68 | D137: 1142474 | E137: -126091.18 | F137: -318943.7 | G137: 679525 | H137: -170052.24 | L137: =SUM(B137:K137) -> 3610809.1
A138: ='Historical NAV'!A1130 -> 45603 | B138: 341940.76 | C138: 384881.85 | D138: 1439898.9 | E138: 168336.26 | F138: 309902.2 | G138: -3050 | H138: 48970.03 | L138: =SUM(B138:K138) -> 2690880
A139: ='Historical NAV'!A1131 -> 45604 | B139: 180712.72 | C139: -217237.94 | D139: -108655 | E139: 117201.88 | F139: -132047.89 | G139: -150800 | H139: 355891.55 | L139: =SUM(B139:K139) -> 45065.32
A140: ='Historical NAV'!A1132 -> 45607 | B140: 289519.8 | C140: -208381.09 | D140: -1214631.9 | E140: -18702.19 | F140: -196688.21 | G140: 5074 | H140: 319682.21 | L140: =SUM(B140:K140) -> -1024127.4
A141: ='Historical NAV'!A1133 -> 45608 | B141: -443574.45 | C141: -379360.66 | D141: 216701 | E141: -156149.2 | F141: -110255.29 | G141: -4687.5 | H141: 14233.13 | L141: =SUM(B141:K141) -> -863092.97
A142: ='Historical NAV'!A1134 -> 45609 | B142: -146728.11 | C142: -3240.37 | D142: -736632 | E142: -51951.67 | F142: -165020.77 | G142: 2250 | H142: 36636.04 | L142: =SUM(B142:K142) -> -1064686.9
A143: ='Historical NAV'!A1135 -> 45610 | B143: -467668.19 | C143: -276682.43 | D143: 114715.5 | E143: -28932.85 | F143: -79307.32 | G143: -28312.5 | H143: -20767.12 | L143: =SUM(B143:K143) -> -786954.91
A144: ='Historical NAV'!A1136 -> 45611 | B144: -1128280.5 | C144: -28233.66 | D144: -1014714 | E144: -14771.68 | F144: 99531.97 | G144: -315062.5 | H144: 3661.74 | L144: =SUM(B144:K144) -> -2397868.6
A145: ='Historical NAV'!A1137 -> 45614 | B145: 395174.45 | C145: 203081.25 | D145: -160337 | E145: 48550.58 | F145: 366448.5 | G145: 101475 | H145: 170181.61 | L145: =SUM(B145:K145) -> 1124574.4
... A212: ='Historical NAV'!A1204 -> 45708 | B212: 0 | C212: 0 | D212: 789.6 | E212: 12500 | F212: 0 | G212: 0 | H212: 636.1 | L212: =SUM(B212:K212) -> 13925.7

Sheet Email
B2: Performance Comparisons | N2: Global Macro Discretionary Fund Breakdowns | S2: Monthly NAV Breakdowns
B3: Us v.s Benchmarks | C3: Description | D3: Week 1 | E3: Week 2 | F3: Week 3 | G3: Week 4 | H3: Week 5 | I3: Daily | J3: MTD | K3: MTD | L3: YTD | O3: Inhouse | P3: Quantedge | Q3: Total | S3: Starting Value | T3: =ROUND(VLOOKUP("Starting Value", 'Email input'!C:D, 2, FALSE),2) -> 66302018
B4: Inhouse | C4: Straits Multi-Asset Macro Strategy | D4: =IF(D18=0, "", D18) -> 0.0017 | E4: =IF(E18=0, "", E18) -> 0.0030108225 | F4: =IF(F18=0, "", F18) -> -0.6851328 | G4: =IF(G18=0, "", G18) | H4: =IF(H18=0, "", H18) | I4: =IF(I18=0, "", I18) -> -0.6851328 | J4: =IF(J18=0, "", J18) -> -0.68349276 | K4: =J4 -> -0.68349276 | L4: =IF(L18=0, "", L18) -> -0.66335391 | N4: Starting Value | O4: =T3 -> 66302018 | P4: =P16 -> 2307179.6 | Q4: =SUM(O4:P4) -> 68609198 | S4: Deposits & Withdrawals | T4: 0 | V4: =ROUND(VLOOKUP("Deposits & Withdrawals", 'Email input'!C:D, 2, FALSE),2) -> #N/A
B5: Quantedge | C5: Singapore-based Global Macro Fund | D5: =D19 -> 0 | E5: =IF(E19=0, "", E19) -> 0.01 | F5: =IF(F19=0, "", F19) | G5: =IF(G19=0, "", G19) | H5: =IF(H19=0, "", H19) | I5: NA | J5: =SUM(D5:H5) -> 0.01 | K5: =J5 -> 0.01 | L5: =L19+J5 -> 0.083 | N5: Deposits & Withdrawals | O5: =T4 -> 0 | Q5: =SUM(O5:P5) -> 0 | S5: Commodities | T5: 0 | U5: =VLOOKUP("Commodities", 'Email input'!F:G, 2, FALSE)/100 -> #N/A
B6: SPX Index | C6: S&P 500 Index | D6: {=IFERROR(_xll.BDP($B6,"INTERVAL_PERCENT_CHANGE", "END_DATE_OVERRIDE="&TEXT(D$17,"yyyymmdd"), "START_DATE_OVERRIDE="&TEXT(D$16,"yyyymmdd"))/100, "")} -> 0.28157398 | E6: {=IFERROR(_xll.BDP($B6,"INTERVAL_PERCENT_CHANGE", "END_DATE_OVERRIDE="&TEXT(E$17,"yyyymmdd"), "START_DATE_OVERRIDE="&TEXT(E$16,"yyyymmdd"))/100, "")} -> 0.28816179 | F6: {=IFERROR(_xll.BDP($B6,"INTERVAL_PERCENT_CHANGE", "END_DATE_OVERRIDE="&TEXT(F$17,"yyyymmdd"), "START_DATE_OVERRIDE="&TEXT(F$16,"yyyymmdd"))/100, "")} -> 0.30567529 | G6: {=IFERROR(_xll.BDP($B6,"INTERVAL_PERCENT_CHANGE", "END_DATE_OVERRIDE="&TEXT(G$17,"yyyymmdd"), "START_DATE_OVERRIDE="&TEXT(G$16,"yyyymmdd"))/100, "")} -> 0.43160336 | H6: {=IFERROR(_xll.BDP($B6,"INTERVAL_PERCENT_CHANGE", "END_DATE_OVERRIDE="&TEXT(H$17,"yyyymmdd"), "START_DATE_OVERRIDE="&TEXT(H$16,"yyyymmdd"))/100, "")} -> 0.38325423 | I6: =_xll.BDP(B6,"CHG_PCT_1D")/100 -> 0.02913117 | J6: =_xll.BDP($B6,"CURRENT_TRR_MTD")/100 -> 0 | K6: =_xll.BDP(B6,"CHG_PCT_1M")/100 -> -0.05093269 | L6: {=_xll.BDP($B6,"CHG_PCT_YTD")/100} -> -0.04630487 | N6: Allocation | O6: =SUM(O4:O5)/SUM(O4:P5) -> 0.96637215 | P6: =SUM(P4:P5)/SUM(O4:P5) -> 0.033627847 | Q6: =SUM(O6:P6) -> 1 | S6: Equities | T6: =($T$3+T$4)*U6 -> 25562.79 | U6: =VLOOKUP("new_equity", 'Email input'!F:G, 2, FALSE)/100 -> 0.00038555071
B7: NDX Index | C7: Nasdaq-100 Index | D7: {=IFERROR(_xll.BDP($B7,"INTERVAL_PERCENT_CHANGE", "END_DATE_OVERRIDE="&TEXT(D$17,"yyyymmdd"), "START_DATE_OVERRIDE="&TEXT(D$16,"yyyymmdd"))/100, "")} -> 0.38788183 | E7: {=IFERROR(_xll.BDP($B7,"INTERVAL_PERCENT_CHANGE", "END_DATE_OVERRIDE="&TEXT(E$17,"yyyymmdd"), "START_DATE_OVERRIDE="&TEXT(E$16,"yyyymmdd"))/100, "")} -> 0.4061962 | F7: {=IFERROR(_xll.BDP($B7,"INTERVAL_PERCENT_CHANGE", "END_DATE_OVERRIDE="&TEXT(F$17,"yyyymmdd"), "START_DATE_OVERRIDE="&TEXT(F$16,"yyyymmdd"))/100, "")} -> 0.42138604 | G7: {=IFERROR(_xll.BDP($B7,"INTERVAL_PERCENT_CHANGE", "END_DATE_OVERRIDE="&TEXT(G$17,"yyyymmdd"), "START_DATE_OVERRIDE="&TEXT(G$16,"yyyymmdd"))/100, "")} -> 0.59640414 | H7: {=IFERROR(_xll.BDP($B7,"INTERVAL_PERCENT_CHANGE", "END_DATE_OVERRIDE="&TEXT(H$17,"yyyymmdd"), "START_DATE_OVERRIDE="&TEXT(H$16,"yyyymmdd"))/100, "")} -> 0.50684549 | I7: {=_xll.BDP(B7,"CHG_PCT_1D")/100} -> 0.03427861 | J7: {=_xll.BDP($B7,"CURRENT_TRR_MTD")/100} -> 0 | K7: =_xll.BDP(B7,"CHG_PCT_1M")/100 -> -0.0488721 | L7: {=_xll.BDP($B7,"CHG_PCT_YTD")/100} -> -0.05978888 | N7: Daily P&L | O7: =OFFSET('Historical NAV'!F1,COUNT('Historical NAV'!A:A),,,) -> -45662297 | P7: NA | Q7: =SUM(O7:P7) -> -45662297 | S7: Fixed Income | T7: =($T$3+T$4)*U7 -> 109564.51 | U7: =VLOOKUP("Fixed Income", 'Email input'!F:G, 2, FALSE)/100 -> 0.0016525064
B8: MXWO Index | C8: MSCI World Index | D8: {=IFERROR(_xll.BDP($B8,"INTERVAL_PERCENT_CHANGE", "END_DATE_OVERRIDE="&TEXT(D$17,"yyyymmdd"), "START_DATE_OVERRIDE="&TEXT(D$16,"yyyymmdd"))/100, "")} -> 0.19076125 | E8: {=IFERROR(_xll.BDP($B8,"INTERVAL_PERCENT_CHANGE", "END_DATE_OVERRIDE="&TEXT(E$17,"yyyymmdd"), "START_DATE_OVERRIDE="&TEXT(E$16,"yyyymmdd"))/100, "")} -> 0.19476276 | F8: {=IFERROR(_xll.BDP($B8,"INTERVAL_PERCENT_CHANGE", "END_DATE_OVERRIDE="&TEXT(F$17,"yyyymmdd"), "START_DATE_OVERRIDE="&TEXT(F$16,"yyyymmdd"))/100, "")} -> 0.20330426 | G8: {=IFERROR(_xll.BDP($B8,"INTERVAL_PERCENT_CHANGE", "END_DATE_OVERRIDE="&TEXT(G$17,"yyyymmdd"), "START_DATE_OVERRIDE="&TEXT(G$16,"yyyymmdd"))/100, "")} -> 0.31208216 | H8: {=IFERROR(_xll.BDP($B8,"INTERVAL_PERCENT_CHANGE", "END_DATE_OVERRIDE="&TEXT(H$17,"yyyymmdd"), "START_DATE_OVERRIDE="&TEXT(H$16,"yyyymmdd"))/100, "")} -> 0.29417658 | I8: {=_xll.BDP(B8,"CHG_PCT_1D")/100} -> 0.02270466 | J8: {=_xll.BDP($B8,"CURRENT_TRR_MTD")/100} -> 4.311423e-05 | K8: =_xll.BDP(B8,"CHG_PCT_1M")/100 -> -0.06550225 | L8: {=_xll.BDP($B8,"CHG_PCT_YTD")/100} -> -0.03883862 | N8: MTD P&L before fee | O8: =OFFSET('Historical NAV'!J1,COUNT('Historical NAV'!A:A),,,) -> -45662297 | P8: =SUM(P4:P5)*P9 -> 23071.796 | Q8: =SUM(O8:P8) -> -45639225 | S8: Cash | T8: =($T$3+T$4)*U8 -> 194892.03 | U8: =VLOOKUP("Cash", 'Email input'!F:G, 2, FALSE)/100 -> 0.0029394585
B9: SBWGU Index | C9: FTSE World Government Bond Index | D9: {=IFERROR(_xll.BDP($B9,"INTERVAL_PERCENT_CHANGE", "END_DATE_OVERRIDE="&TEXT(D$17,"yyyymmdd"), "START_DATE_OVERRIDE="&TEXT(D$16,"yyyymmdd"))/100, "")} -> -0.15068936 | E9: {=IFERROR(_xll.BDP($B9,"INTERVAL_PERCENT_CHANGE", "END_DATE_OVERRIDE="&TEXT(E$17,"yyyymmdd"), "START_DATE_OVERRIDE="&TEXT(E$16,"yyyymmdd"))/100, "")} -> -0.14623118 | F9: {=IFERROR(_xll.BDP($B9,"INTERVAL_PERCENT_CHANGE", "END_DATE_OVERRIDE="&TEXT(F$17,"yyyymmdd"), "START_DATE_OVERRIDE="&TEXT(F$16,"yyyymmdd"))/100, "")} -> -0.14696936 | G9: {=IFERROR(_xll.BDP($B9,"INTERVAL_PERCENT_CHANGE", "END_DATE_OVERRIDE="&TEXT(G$17,"yyyymmdd"), "START_DATE_OVERRIDE="&TEXT(G$16,"yyyymmdd"))/100, "")} -> -0.1349148 | H9: {=IFERROR(_xll.BDP($B9,"INTERVAL_PERCENT_CHANGE", "END_DATE_OVERRIDE="&TEXT(H$17,"yyyymmdd"), "START_DATE_OVERRIDE="&TEXT(H$16,"yyyymmdd"))/100, "")} -> -0.1334153 | I9: {=_xll.BDP(B9,"CHG_PCT_1D")/100} -> 0.003071177 | J9: {=_xll.BDP($B9,"CURRENT_TRR_MTD")/100} -> 0 | K9: =_xll.BDP(B9,"CHG_PCT_1M")/100 -> -0.03182128 | L9: {=_xll.BDP($B9,"CHG_PCT_YTD")/100} -> -0.01050591 | N9: MTD P&L before fee (%) | O9: =OFFSET('Historical NAV'!K1,COUNT('Historical NAV'!A:A),,,) -> -0.68349276 | P9: =J5 -> 0.01 | S9: Total Trading P&L | T9: =SUM(T5:T8) -> 330019.33 | V9: =T9/(T3+T4) -> 0.0049775156
B10: BCOM Index | C10: Bloomberg Commodity Index | D10: {=IFERROR(_xll.BDP($B10,"INTERVAL_PERCENT_CHANGE", "END_DATE_OVERRIDE="&TEXT(D$17,"yyyymmdd"), "START_DATE_OVERRIDE="&TEXT(D$16,"yyyymmdd"))/100, "")} -> -0.10435881 | E10: {=IFERROR(_xll.BDP($B10,"INTERVAL_PERCENT_CHANGE", "END_DATE_OVERRIDE="&TEXT(E$17,"yyyymmdd"), "START_DATE_OVERRIDE="&TEXT(E$16,"yyyymmdd"))/100, "")} -> -0.093448329 | F10: {=IFERROR(_xll.BDP($B10,"INTERVAL_PERCENT_CHANGE", "END_DATE_OVERRIDE="&TEXT(F$17,"yyyymmdd"), "START_DATE_OVERRIDE="&TEXT(F$16,"yyyymmdd"))/100, "")} -> -0.08010459 | G10: {=IFERROR(_xll.BDP($B10,"INTERVAL_PERCENT_CHANGE", "END_DATE_OVERRIDE="&TEXT(G$17,"yyyymmdd"), "START_DATE_OVERRIDE="&TEXT(G$16,"yyyymmdd"))/100, "")} -> -0.095390816 | H10: {=IFERROR(_xll.BDP($B10,"INTERVAL_PERCENT_CHANGE", "END_DATE_OVERRIDE="&TEXT(H$17,"yyyymmdd"), "START_DATE_OVERRIDE="&TEXT(H$16,"yyyymmdd"))/100, "")} -> -0.16477792 | I10: =_xll.BDP(B10,"CHG_PCT_1D")/100 -> -0.006231608 | J10: {=_xll.BDP($B10,"CURRENT_TRR_MTD")/100} -> -0.006231637 | K10: =_xll.BDP(B10,"CHG_PCT_1M")/100 -> 0.1045347 | L10: {=_xll.BDP($B10,"CHG_PCT_YTD")/100} -> 0.2253004 | N10: Ending Value | O10: =O4+O5+O8 -> 20639722 | P10: =P4+P5+P8 -> 2330251.4 | Q10: =SUM(O10:P10) -> 22969973 | S10: Interest and Dividend related | T10: =SUM('Email input'!D5:D6) -> 163158.58
S11: Hardcode | T11: -170897.33
S12: Other Trading Cost | T12: =SUM('Email input'!D7:D9) -> 23066.663
S13: Ending Value | T13: =T3+T4+T9+T10+T12+T11 -> 66647366
B16: start date | D16: 44594 | E16: =D16+7 -> 44601 | F16: =E16+7 -> 44608 | G16: =F16+7 -> 44615 | H16: =G16+7 -> 44622 | N16: Quantedge NAV | P16: 2307179.6 | S16: nav | T16: =OFFSET('Historical NAV'!B1,COUNT('Historical NAV'!A:A),,,) -> 20985069
B17: end date | D17: 45657 | E17: =D17+7 -> 45664 | F17: =E17+7 -> 45671 | G17: =F17+7 -> 45678 | H17: =G17+7 -> 45685 | P17: 45688 | T17: =T13 -> 66647366
B18: buy and hold | D18: 0.0017 | E18: 0.0030108225 | F18: =Dashboard!$B$4 -> -0.6851328 | I18: =Dashboard!B9 -> -0.6851328 | J18: =Dashboard!B5 -> -0.68349276 | L18: =Dashboard!B6 -> -0.66335391 | T18: =T16-T17 -> -45662297
B19: qe | D19: 0 | E19: 0.01 | J19: =SUM(D19:H19) -> 0.01 | L19: 0.073 | M19: =P17 -> 45688

Sheet Email input
A1: Change in NAV | B1: Header | C1: Field Name | D1: Field Value | F1: Performance by Asset Class | G1: Performance by Asset Class
A2: Change in NAV | B2: Data | C2: Starting Value | D2: 66302018 | F2: Header | G2: Data
A3: Change in NAV | B3: Data | C3: Mark-to-Market | D3: 161244 | F3: Date | G3: Total
A4: Change in NAV | B4: Data | C4: Dividends | D4: 1452.82 | F4: Fixed Income | G4: 0.16525064
A5: Change in NAV | B5: Data | C5: Withholding Tax | D5: 164167.45 | F5: Cash | G5: 0.29394585
A6: Change in NAV | B6: Data | C6: Change in Dividend Accruals | D6: -1008.87
A7: Change in NAV | B7: Data | C7: Interest | D7: -472182.15
A8: Change in NAV | B8: Data | C8: Change in Interest Accruals | D8: 495445.25
A9: Change in NAV | B9: Data | C9: Other Fees | D9: -196.44 | F9: new_equity | G9: 0.038555071
A10: Change in NAV | B10: Data | C10: Commissions | D10: -3444.821
A11: Change in NAV | B11: Data | C11: Other FX Translations | D11: -130.00165
A12: Change in NAV | B12: Data | C12: Ending Value | D12: 66647366

Sheet QuantEdge
A1: Dates | B1: MTD
A2: 44013 | B2: -0.0146
A3: 44014 | B3: 0.0014
A4: 44015 | B4: 0.0042
A5: 44018 | B5: 0.018
A6: 44019 | B6: 0.0235
A7: 44021 | B7: 0.0407
A8: 44022 | B8: 0.0392
A9: 44025 | B9: 0.0466
A10: 44026 | B10: 0.0514
A11: 44027 | B11: 0.06
A12: 44028 | B12: 0.0572
A13: 44029 | B13: 0.0521
... A647: 45632 | B647: 0.03
A648: =A647+7 -> 45639 | B648: 0.03
A649: =A648+7 -> 45646 | B649: -0.03
A650: =A649+7+4 -> 45657 | B650: -0.026
A651: 45674 | B651: 0.01

Sheet Categorized P&L
B1: Previos Month | C1: 202406
B2: YTD Return (before fees) - TOTAL | C2: 0.033335414
B3: YTD Return (before fees) - IN-HOUSE BUY AND HOLD | C3: 0.046278035
B4: YTD Return (before fees) - QE | C4: 0.168272
C6: Total (USD) | D6: In-House Buy & Hold (USD) | E6: QuantEdge (USD) | F6: Global Sigma(USD)
B7: Month Start NAV | C7: =SUM(D7:F7)+D8 -> 68579961 | D7: =OFFSET('Historical NAV'!E1, COUNT('Historical NAV'!B:B),,,) -> 66647366 | E7: 1932595.1 | F7: 0
B8: Subscription
B9: Percentage | C9: =SUM(D9:F9) -> 1 | D9: =(D7+D8)/(D7+D8+E7) -> 0.97181983 | E9: =E7/(D7+D8+E7) -> 0.028180172 | F9: 0
B10: Portfolio NAV | C10: =SUM(D10:F10) -> #REF! | D10: =OFFSET('Historical NAV'!B1, COUNT('Historical NAV'!B:B),,,) -> 20985069 | E10: =E7+E11 -> #REF! | F10: =F7+F11 -> 0
B11: MTD P&L | C11: =SUM(D11:F11) -> #REF! | D11: =OFFSET('Historical NAV'!J1, COUNT('Historical NAV'!B:B),,,) -> -45662297 | E11: =E12*E7 -> #REF! | F11: =F12*F7 -> 0
B12: MTD Return (before fees) | C12: =D12*D9+E12*E9 -> #REF! | D12: =OFFSET('Historical NAV'!K1, COUNT('Historical NAV'!B:B),,,) -> -0.68349276 | E12: =OFFSET(#REF!, COUNT(#REF!),,,) -> #REF! | F12: 0
B13: YTD Return (before fees) | C13: =(1+C2)*(1+C12)-1 -> #REF! | D13: =(1+C3)*(1+D12)-1 -> -0.66884542 | E13: =(1+C4)*(1+E12)-1 -> #REF!
B14: Daily Change | D14: =OFFSET('Historical NAV'!G1, COUNT('Historical NAV'!B:B),,,) -> -0.6851328 | E14: NA

Sheet IB_Margin
A1: Date | B1: NAV(Net Liquidity) | C1: Maintenance | D1: Excess Liquidity | E1: Alert | F1: IB Alert 10% | G1: IB Alert 15% | H1: Excess Liquidity/NAV
A2: 45170 | B2: 37374972 | C2: 10706569 | D2: =B2-C2 -> 26668403 | E2: =B2*0.25 -> 9343742.9 | F2: =B2*0.1 -> 3737497.2 | G2: =B2*0.15 -> 5606245.7 | H2: =D2/B2 -> 0.7135364
A3: 45171 | B3: 37374972 | C3: 10706569 | D3: =B3-C3 -> 26668403 | E3: =B3*0.25 -> 9343742.9 | F3: =B3*0.1 -> 3737497.2 | G3: =B3*0.15 -> 5606245.7 | H3: =D3/B3 -> 0.7135364
A4: 45173 | B4: 37375362 | C4: 10705819 | D4: =B4-C4 -> 26669543 | E4: =B4*0.25 -> 9343840.6 | F4: =B4*0.1 -> 3737536.2 | G4: =B4*0.15 -> 5606304.4 | H4: =D4/B4 -> 0.71355945
A5: 45174 | B5: 37340919 | C5: 10703347 | D5: =B5-C5 -> 26637573 | E5: =B5*0.25 -> 9335229.9 | F5: =B5*0.1 -> 3734091.9 | G5: =B5*0.15 -> 5601137.9 | H5: =D5/B5 -> 0.71336146
A6: 45175 | B6: 37244792 | C6: 12600903 | D6: =B6-C6 -> 24643889 | E6: =B6*0.25 -> 9311198.1 | F6: =B6*0.1 -> 3724479.2 | G6: =B6*0.15 -> 5586718.9 | H6: =D6/B6 -> 0.66167343
A7: 45177 | B7: 36440413 | C7: 12956000 | D7: =B7-C7 -> 23484413 | E7: =B7*0.25 -> 9110103.2 | F7: =B7*0.1 -> 3644041.3 | G7: =B7*0.15 -> 5466061.9 | H7: =D7/B7 -> 0.64446068
A8: 45178 | B8: 36613715 | C8: 12904681 | D8: =B8-C8 -> 23709034 | E8: =B8*0.25 -> 9153428.8 | F8: =B8*0.1 -> 3661371.5 | G8: =B8*0.15 -> 5492057.2 | H8: =D8/B8 -> 0.64754516
A9: 45180 | B9: 36586860 | C9: 12904102 | D9: =B9-C9 -> 23682758 | E9: =B9*0.25 -> 9146714.9 | F9: =B9*0.1 -> 3658686 | G9: =B9*0.15 -> 5488028.9 | H9: =D9/B9 -> 0.64730229
A10: 45181 | B10: 37262904 | C10: 14578535 | D10: =B10-C10 -> 22684369 | E10: =B10*0.25 -> 9315725.9 | F10: =B10*0.1 -> 3726290.4 | G10: =B10*0.15 -> 5589435.6 | H10: =D10/B10 -> 0.60876545
A11: 45182 | B11: 36597913 | C11: 14489723 | D11: =B11-C11 -> 22108190 | E11: =B11*0.25 -> 9149478.2 | F11: =B11*0.1 -> 3659791.3 | G11: =B11*0.15 -> 5489687 | H11: =D11/B11 -> 0.60408335
A12: 45183 | B12: 36912497 | C12: 14552983 | D12: =B12-C12 -> 22359514 | E12: =B12*0.25 -> 9228124.2 | F12: =B12*0.1 -> 3691249.7 | G12: =B12*0.15 -> 5536874.5 | H12: =D12/B12 -> 0.60574374
A13: 45184 | B13: 37474543 | C13: 14681211 | D13: =B13-C13 -> 22793332 | E13: =B13*0.25 -> 9368635.8 | F13: =B13*0.1 -> 3747454.3 | G13: =B13*0.15 -> 5621181.5 | H13: =D13/B13 -> 0.60823509
... A181: 45429 | B181: 55793659 | C181: 30305524 | D181: =B181-C181 -> 25488135 | E181: =B181*0.25 -> 13948415 | F181: =B181*0.1 -> 5579365.9 | G181: =B181*0.15 -> 8369048.8 | H181: =D181/B181 -> 0.45682853
A182: 45430 | B182: 56343495 | D182: =B182-C182 -> 56343495 | E182: =B182*0.25 -> 14085874 | F182: =B182*0.1 -> 5634349.5 | G182: =B182*0.15 -> 8451524.2 | H182: =D182/B182 -> 1
A183: 45431 | B183: 53856958 | C183: 28726470 | D183: =B183-C183 -> 25130488 | E183: =B183*0.25 -> 13464240 | F183: =B183*0.1 -> 5385695.8 | G183: =B183*0.15 -> 8078543.7 | H183: =D183/B183 -> 0.46661544
A184: 45439 | B184: 56489689 | C184: 25209925 | D184: =B184-C184 -> 31279764 | E184: =B184*0.25 -> 14122422 | F184: =B184*0.1 -> 5648968.9 | G184: =B184*0.15 -> 8473453.3 | H184: =D184/B184 -> 0.55372519
A185: 45440 | D185: =B185-C185 -> 0 | E185: =B185*0.25 -> 0 | F185: =B185*0.1 -> 0 | G185: =B185*0.15 -> 0 | H185: =D185/B185 -> #DIV/0!
A186: 45446 | B186: =56100350-9000000 -> 47100350 | C186: 26176485 | D186: =B186-C186 -> 20923865 | E186: =B186*0.25 -> 11775088 | F186: =B186*0.1 -> 4710035 | G186: =B186*0.15 -> 7065052.5 | H186: =D186/B186 -> 0.44424012
A187: 45447 | B187: 54917894 | C187: 27447604 | D187: =B187-C187 -> 27470290 | E187: =B187*0.25 -> 13729474 | F187: =B187*0.1 -> 5491789.4 | G187: =B187*0.15 -> 8237684.1 | H187: =D187/B187 -> 0.50020654
A188: 45448 | B188: 58212170 | C188: 28677655 | D188: =B188-C188 -> 29534515 | E188: =B188*0.25 -> 14553042 | F188: =B188*0.1 -> 5821217 | G188: =B188*0.15 -> 8731825.5 | H188: =D188/B188 -> 0.5073598
A189: 45449 | B189: 57976716 | C189: 28758949 | D189: =B189-C189 -> 29217767 | E189: =B189*0.25 -> 14494179 | F189: =B189*0.1 -> 5797671.6 | G189: =B189*0.15 -> 8696507.4 | H189: =D189/B189 -> 0.50395692

Sheet IB_html
B1: Mark-to-Market Performance Summary
C2: Quantity | E2: Price | G2: Mark-to-Market P/L
B3: Symbol | C3: Prior | D3: Current | E3: Prior | F3: Current | G3: Position | H3: Transaction | I3: Commissions | J3: Other | K3: Total | L3: Code | N3: Equity and Index Options
B4: Stocks | N4: 2899 27JUN24 17.5 C | O4: 0 | P4: -40 | Q4: -- | R4: 0.15 | S4: 1024.32 | T4: 281.71 | U4: -14.34 | V4: 0 | W4: 1291.69
B5: 333 | C5: 28000 | D5: 28000 | E5: 64.76 | F5: 63.92 | G5: -3231.75 | H5: 0 | I5: 0 | J5: 0 | K5: -3231.75 | N5: 2899 27JUN24 18 C | O5: 0 | P5: 0 | Q5: -- | R5: -- | S5: 3379.32 | T5: -1664.3 | U5: -28.68 | V5: 0 | W5: 1686.34
B6: 921 | C6: 34100 | D6: 34100 | E6: 40.67 | F6: 38.26 | G6: -11307.6 | H6: 0 | I6: 0 | J6: 0 | K6: -11307.6 | N6: 700 27JUN24 400 C | O6: 0 | P6: -46 | Q6: -- | R6: 2.57 | S6: -653.77 | T6: 410.53 | U6: -29.2 | V6: 0 | W6: -272.44
B7: 1109 | C7: 220000 | D7: 220000 | E7: 28.4 | F7: 26.85 | G7: -43700.47 | H7: 0 | I7: 0 | J7: 0 | K7: -43700.47 | N7: BNP 14JUN24 60 C | O7: 0 | P7: -50 | Q7: -- | R7: 0.67 | S7: 0 | T7: -1557.01 | U7: -61.21 | V7: 0 | W7: -1618.22
B8: 1288 | C8: 2325000 | D8: 2325000 | E8: 3.27 | F8: 3.21 | G8: -17883.67 | H8: 0 | I8: 0 | J8: 0 | K8: -17883.67 | N8: BNP 14JUN24 63 C | O8: 0 | P8: -100 | Q8: -- | R8: 0.05 | S8: 9548.36 | T8: -1528.63 | U8: -122.72 | V8: 0 | W8: 7897.01
B9: 2020 | C9: 104800 | D9: 104800 | E9: 83.25 | F9: 82.05 | G9: -16144.49 | H9: 0 | I9: 0 | J9: 0 | K9: -16144.49 | N9: DELL 07JUN24 121 P | O9: -5 | P9: 0 | Q9: 0.1593 | R9: -- | S9: 79.65 | T9: 0 | U9: 0 | V9: 0 | W9: 79.65
B10: 2823 | C10: 468900 | D10: 618900 | E10: 12.73 | F10: 12.43 | G10: -22809.32 | H10: -791.17 | I10: -148.97 | J10: 0 | K10: -23749.46 | N10: DELL 07JUN24 125 P | O10: -4 | P10: 0 | Q10: 0.3105 | R10: -- | S10: 124.2 | T10: 0 | U10: 0 | V10: 0 | W10: 124.2
B11: 2828 | C11: 523000 | D11: 553000 | E11: 64.84 | F11: 65.66 | G11: 53416.59 | H11: -1408 | I11: -154.23 | J11: 0 | K11: 51854.36 | N11: DELL 07JUN24 130 P | O11: -6 | P11: 0 | Q11: 0.8787 | R11: -- | S11: 509.22 | T11: 18 | U11: 0 | V11: 0 | W11: 527.22
B12: 2899 | C12: 1360000 | D12: 1360000 | E12: 16.54 | F12: 16.38 | G12: -27864.77 | H12: 0 | I12: 0 | J12: 0 | K12: -27864.77 | N12: DELL 14JUN24 119 P | O12: 0 | P12: -10 | Q12: -- | R12: 0.0001 | S12: 779 | T12: 470.9 | U12: 2.97 | V12: 0 | W12: 1252.87
B13: 600519 | C13: 900 | D13: 900 | E13: 1648.45 | F13: 1555.01 | G13: -11567.9 | H13: 0 | I13: 0 | J13: 0 | K13: -11567.9 | N13: DELL 14JUN24 120 P | O13: -5 | P13: -8 | Q13: 0.3821 | R13: 0.0001 | S13: 468.47 | T13: 181.5 | U13: -2.11 | V13: 0 | W13: 647.86
B14: 600690 | C14: 22600 | D14: 22600 | E14: 29.54 | F14: 29.93 | G14: 1218.41 | H14: 0 | I14: 0 | J14: 0 | K14: 1218.41 | N14: DELL 14JUN24 122 P | O14: 0 | P14: -30 | Q14: -- | R14: 0.0002 | S14: 3756 | T14: 1433.4 | U14: -0.63 | V14: 0 | W14: 5188.77
B15: 688 | C15: 220000 | D15: 240000 | E15: 14.74 | F15: 14.42 | G15: -10723.34 | H15: -614.64 | I15: -63.93 | J15: 0 | K15: -11401.91 | N15: DELL 14JUN24 123 P | O15: -2 | P15: -2 | Q15: 0.6114 | R15: 0.0007 | S15: 122.14 | T15: 0 | U15: 0 | V15: 0 | W15: 122.14
B16: 700 | C16: 15300 | D16: 15300 | E16: 359.8 | F16: 379.8 | G16: 39141.75 | H16: 0 | I16: 0 | J16: 0 | K16: 39141.75 | N16: DELL 14JUN24 126 P | O16: -4 | P16: -4 | Q16: 0.9154 | R16: 0.0115 | S16: 361.56 | T16: 0 | U16: 0 | V16: 0 | W16: 361.56
B17: 857 | C17: 2860000 | D17: 2860000 | E17: 7.97 | F17: 7.69 | G17: -102516.7 | H17: 0 | I17: 0 | J17: 0 | K17: -102516.7 | N17: EWY 21JUN24 66 C | O17: 0 | P17: -100 | Q17: -- | R17: 0.3 | S17: 2250 | T17: 660 | U17: -17.87 | V17: 0 | W17: 2892.13
B18: 883 | C18: 2562000 | D18: 2562000 | E18: 20.9 | F18: 21.4 | G18: 164044.86 | H18: 0 | I18: 0 | J18: 0 | K18: 164044.86 | N18: EWY 21JUN24 67 C | O18: 0 | P18: -130 | Q18: -- | R18: 0.1 | S18: 1950 | T18: 419 | U18: -48.86 | V18: 0 | W18: 2320.14
B19: 921 | C19: 24000 | D19: 24000 | E19: 35.5 | F19: 33.3 | G19: -6760.39 | H19: 0 | I19: 0 | J19: 0 | K19: -6760.39 | N19: GLD 31MAY24 217.5 P | O19: -80 | P19: 0 | Q19: 2.2 | R19: -- | S19: 0 | T19: 17600 | U19: 0 | V19: 0 | W19: 17600
B20: 9888 | C20: 15600 | D20: 15600 | E20: 93.5 | F20: 92.45 | G20: -2099.49 | H20: 0 | I20: 0 | J20: 0 | K20: -2099.49 | N20: GLD 07JUN24 217.5 C | O20: 0 | P20: 0 | Q20: -- | R20: -- | S20: 6100 | T20: -1810 | U20: -23.7 | V20: 0 | W20: 4266.3
B21: 9988 | C21: 22000 | D21: 22000 | E21: 74.9 | F21: 74.5 | G21: -1133.29 | H21: 0 | I21: 0 | J21: 0 | K21: -1133.29 | N21: GLD 07JUN24 220 C | O21: 0 | P21: 0 | Q21: -- | R21: -- | S21: 3240 | T21: -1060 | U21: -23.65 | V21: 0 | W21: 2156.35
B22: BNP | C22: 0 | D22: 15000 | E22: -- | F22: 60 | G22: -34397.93 | H22: 3751.29 | I22: -3352.38 | J22: 0 | K22: -33999.02 | N22: GLD 14JUN24 205 P | O22: 0 | P22: -5 | Q22: -- | R22: 0.0024 | S22: 188.8 | T22: -90 | U22: -3.45 | V22: 0 | W22: 95.35
B23: COWZ | C23: 267138 | D23: 201138 | E23: 56.19 | F23: 54.58 | G23: -414252.18 | H23: -9716.05 | I23: -312.92 | J23: 0 | K23: -424281.15 | N23: GLD 14JUN24 207.5 P | O23: 0 | P23: -5 | Q23: -- | R23: 0.015 | S23: 370 | T23: -202.5 | U23: -3.45 | V23: 0 | W23: 164.05
B24: CWB | C24: 38350 | D24: 38350 | E24: 71.67 | F24: 71.91 | G24: 9204 | H24: 0 | I24: 0 | J24: 3544.01 | K24: 12748.01 | N24: GLD 14JUN24 212.5 C | O24: 0 | P24: -40 | Q24: -- | R24: 1.0335 | S24: 5920.4 | T24: -634.4 | U24: -19.87 | V24: 0 | W24: 5266.13
B25: DBA | C25: 43084 | D25: 43084 | E25: 25.13 | F25: 25.85 | G25: 31020.48 | H25: 0 | I25: 0 | J25: 0 | K25: 31020.48 | N25: GLD 14JUN24 215 C | O25: 0 | P25: -40 | Q25: -- | R25: 0.185 | S25: 3100 | T25: 4241 | U25: -27.85 | V25: 0 | W25: 7313.15
B26: DELL | C26: 0 | D26: 0 | E26: -- | F26: -- | G26: 0 | H26: -810 | I26: -3.21 | J26: 0 | K26: -813.21 | N26: GLD 14JUN24 217.5 C | O26: 0 | P26: -80 | Q26: -- | R26: 0.035 | S26: 3680 | T26: 2210 | U26: -50.64 | V26: 0 | W26: 5839.36
B27: DXJ | C27: 44650 | D27: 44650 | E27: 111.11 | F27: 108.33 | G27: -124127 | H27: 0 | I27: 0 | J27: 0 | K27: -124127 | N27: IWM 07JUN24 208 C | O27: 0 | P27: 0 | Q27: -- | R27: -- | S27: 2726 | T27: -1668 | U27: -41.23 | V27: 0 | W27: 1016.77
B28: EPI | C28: 154454 | D28: 154454 | E28: 45.89 | F28: 47.3 | G28: 217780.14 | H28: 0 | I28: 0 | J28: 0 | K28: 217780.14 | N28: IWM 14JUN24 206 C | O28: 0 | P28: -2 | Q28: -- | R28: 0.035 | S28: 0 | T28: 19 | U28: -2.38 | V28: 0 | W28: 16.62
B29: EWI | C29: 80000 | D29: 80000 | E29: 38.83 | F29: 36.32 | G29: -200800 | H29: 0 | I29: 0 | J29: 0 | K29: -200800 | N29: IWM 14JUN24 208 C | O29: 0 | P29: -58 | Q29: -- | R29: 0.0045 | S29: 2148.9 | T29: 985 | U29: -45.69 | V29: 0 | W29: 3088.21
B30: EWY | C30: 126253 | D30: 122253 | E30: 62.18 | F30: 64.84 | G30: 336242.98 | H30: 710 | I30: -18.52 | J30: 0 | K30: 336934.46 | N30: IWM 17JUN24 204 C | O30: 0 | P30: -45 | Q30: -- | R30: 0.43 | S30: 0 | T30: 2059 | U30: -31.51 | V30: 0 | W30: 2027.49
B31: FPE | C31: 115300 | D31: 115300 | E31: 17.25 | F31: 17.39 | G31: 16142 | H31: 0 | I31: 0 | J31: 0 | K31: 16142 | N31: MCD 14JUN24 265 C | O31: 0 | P31: -7 | Q31: -- | R31: 0.002 | S31: 884.1 | T31: -6.5 | U31: -4.11 | V31: 0 | W31: 873.49
B32: GLD | C32: 44481 | D32: 60481 | E32: 215.3 | F32: 212.97 | G32: -134440.73 | H32: -12452.1 | I32: -25.42 | J32: 0 | K32: -146918.26 | N32: QQQ 06JUN24 460 P | O32: 0 | P32: 0 | Q32: -- | R32: -- | S32: 0 | T32: 1115 | U32: -29.07 | V32: 0 | W32: 1085.93
B33: HES | C33: 0 | D33: 11000 | E33: -- | F33: 143.75 | G33: -29620 | H33: -3312.9 | I33: -30.33 | J33: 0 | K33: -32963.23 | N33: QQQ 07JUN24 458 P | O33: 0 | P33: 0 | Q33: -- | R33: -- | S33: 0 | T33: 200 | U33: -6.9 | V33: 0 | W33: 193.1
B34: IAUM | C34: 43200 | D34: 43200 | E34: 23.23 | F34: 22.97 | G34: -11232 | H34: 0 | I34: 0 | J34: 0 | K34: -11232 | N34: QQQ 07JUN24 460 C | O34: 0 | P34: 0 | Q34: -- | R34: -- | S34: 11437.2 | T34: 22.8 | U34: -35.2 | V34: 0 | W34: 11424.8
B35: ISTB | C35: 21013 | D35: 21013 | E35: 47.28 | F35: 47.44 | G35: 3362.08 | H35: 0 | I35: 0 | J35: 2202.62 | K35: 5564.7 | N35: QQQ 10JUN24 458 P | O35: 0 | P35: 0 | Q35: -- | R35: -- | S35: 0 | T35: 350 | U35: -13.83 | V35: 0 | W35: 336.17
B36: IWM | C36: 58224 | D36: 58224 | E36: 205.77 | F36: 201.94 | G36: -222997.92 | H36: 0 | I36: 0 | J36: 0 | K36: -222997.92 | N36: QQQ 10JUN24 459 P | O36: 0 | P36: 0 | Q36: -- | R36: -- | S36: 0 | T36: 500 | U36: -13.82 | V36: 0 | W36: 486.18
B37: LQD | C37: 26725 | D37: 26725 | E37: 106.89 | F37: 108.37 | G37: 39553 | H37: 0 | I37: 0 | J37: 7567.34 | K37: 47120.34 | N37: QQQ 10JUN24 460 P | O37: 0 | P37: 0 | Q37: -- | R37: -- | S37: 0 | T37: 1290 | U37: -46.06 | V37: 0 | W37: 1243.94
B38: MCD | C38: 0 | D38: 700 | E38: -- | F38: 253.7 | G38: -4403 | H38: -18.96 | I38: -2.18 | J38: 0 | K38: -4424.14 | N38: QQQ 11JUN24 459 P | O38: 0 | P38: 0 | Q38: -- | R38: -- | S38: 0 | T38: 200 | U38: -6.9 | V38: 0 | W38: 193.1
B39: NVDA | C39: 8140 | D39: 103400 | E39: 1096.33 | F39: 129.61 | G39: 1879405.8 | H39: 47391.44 | I39: -6.63 | J39: 0 | K39: 1926790.6 | N39: QQQ 11JUN24 460 P | O39: 0 | P39: 0 | Q39: -- | R39: -- | S39: 0 | T39: 860 | U39: -27.69 | V39: 0 | W39: 832.31
B40: QQQ | C40: 55883 | D40: 51183 | E40: 450.71 | F40: 476.72 | G40: 1489261.8 | H40: -32046.92 | I40: -20.06 | J40: 0 | K40: 1457194.9 | N40: QQQ 11JUN24 461 P | O40: 0 | P40: 0 | Q40: -- | R40: -- | S40: 0 | T40: 1190 | U40: -31.32 | V40: 0 | W40: 1158.68
B41: SMH | C41: 36485 | D41: 47885 | E41: 240.48 | F41: 267.21 | G41: 1207576.1 | H41: 31406.39 | I41: -37.49 | J41: 0 | K41: 1238944.9 | N41: QQQ 11JUN24 462 P | O41: 0 | P41: 0 | Q41: -- | R41: -- | S41: 0 | T41: 410 | U41: -11.48 | V41: 0 | W41: 398.52
B42: TLT | C42: 0 | D42: 0 | E42: -- | F42: -- | G42: 3458 | H42: -283.22 | I42: -53.48 | J42: 0 | K42: 3121.31 | N42: QQQ 12JUN24 472 C | O42: 0 | P42: 0 | Q42: -- | R42: -- | S42: 0 | T42: 8610 | U42: -50.08 | V42: 0 | W42: 8559.92
B43: TSM | C43: 0 | D43: 9000 | E43: -- | F43: 172.91 | G43: 35790 | H43: 3051.47 | I43: -24.75 | J43: 0 | K43: 38816.72 | N43: TLT 07JUN24 92.5 C | O43: 0 | P43: 0 | Q43: -- | R43: -- | S43: 545.6 | T43: -270.6 | U43: -2.58 | V43: 0 | W43: 272.42
B44: UNG | C44: 10000 | D44: 16000 | E44: 17.59 | F44: 20.11 | G44: 21620 | H44: -170 | I44: -16.9 | J44: 0 | K44: 21433.1 | N44: TLT 07JUN24 93 C | O44: 0 | P44: 0 | Q44: -- | R44: -- | S44: 2720.84 | T44: -769.84 | U44: -26.62 | V44: 0 | W44: 1924.38
B45: URNM | C45: 15270 | D45: 15270 | E45: 56.53 | F45: 51.71 | G45: -73601.4 | H45: 0 | I45: 0 | J45: 0 | K45: -73601.4 | N45: TSM 14JUN24 170 C | O45: 0 | P45: -15 | Q45: -- | R45: 3.3422 | S45: -3775.8 | T45: 73.5 | U45: -8.97 | V45: 0 | W45: -3711.27
B46: USHY | C46: 58743 | D46: 58743 | E46: 36.33 | F46: 36.345 | G46: 881.15 | H46: 0 | I46: 0 | J46: 8309.34 | K46: 9190.49 | N46: XLV 07JUN24 147 C | O46: 0 | P46: 0 | Q46: -- | R46: -- | S46: 155 | T46: 145 | U46: -4.5 | V46: 0 | W46: 295.5
B47: VCIT | C47: 36312 | D47: 36312 | E47: 79.645 | F47: 80.48 | G47: 30320.52 | H47: 0 | I47: 0 | J47: 7605.18 | K47: 37925.7 | N47: XLV 07JUN24 147.5 C | O47: 0 | P47: 0 | Q47: -- | R47: -- | S47: 187.5 | T47: 222.5 | U47: -17.4 | V47: 0 | W47: 392.6
B48: XLE | C48: 73500 | D48: 97500 | E48: 93.2 | F48: 88.7 | G48: -369540 | H48: 2510.66 | I48: -68.95 | J48: 0 | K48: -367098.29 | N48: XLV 07JUN24 148 C | O48: 0 | P48: 0 | Q48: -- | R48: -- | S48: 31.5 | T48: 49.5 | U48: -4.95 | V48: 0 | W48: 76.05
B49: XLF | C49: 213563 | D49: 213563 | E49: 41.64 | F49: 40.78 | G49: -183664.18 | H49: 0 | I49: 0 | J49: 0 | K49: -183664.18 | N49: XLV 14JUN24 147 C | O49: 0 | P49: -22 | Q49: -- | R49: 0.125 | S49: 1652.2 | T49: -757.2 | U49: -12.8 | V49: 0 | W49: 882.2
B50: XLK | C50: 60591 | D50: 60591 | E50: 210.16 | F50: 226.82 | G50: 1009446.1 | H50: 0 | I50: 0 | J50: 0 | K50: 1009446.1 | N50: XLV 14JUN24 147.5 C | O50: 0 | P50: -22 | Q50: -- | R50: 0.0702 | S50: 1242.56 | T50: -479 | U50: -12.32 | V50: 0 | W50: 751.24
B51: XLU | C51: 0 | D51: 3000 | E51: -- | F51: 70.11 | G51: -5250 | H51: 1855 | I51: -10.32 | J51: 0 | K51: -3405.32 | N51: XLV 21JUN24 148 C | O51: 0 | P51: -44 | Q51: -- | R51: 0.235 | S51: 2024 | T51: -726 | U51: -22.35 | V51: 0 | W51: 1275.65
B52: XLV | C52: 35254 | D52: 35254 | E52: 143.7 | F52: 145.93 | G52: 78616.42 | H52: 0 | I52: 0 | J52: 0 | K52: 78616.42 | N52: Total Equity and Index Options | S52: 68277.27 | T52: 33003.36 | U52: -985.03 | V52: 0 | W52: 100295.6
B53: XME | C53: 6000 | D53: 61000 | E53: 64.43 | F53: 58.78 | G53: -336950 | H53: -17007.98 | I53: -174.76 | J53: 0 | K53: -354132.75 | N53: Futures
B54: Total Stocks | G54: 4244482.6 | H54: 12044.3 | I54: -4525.42 | J54: 29228.49 | K54: 4281230 | N54: MNQM4 | O54: 0 | P54: 20 | Q54: -- | R54: 19602.5 | S54: 0 | T54: -300 | U54: 0 | V54: 0 | W54: -300
B55: Equity and Index Options | N55: Total Futures | S55: 0 | T55: -300 | U55: 0 | V55: 0 | W55: -300
B56: 2899 27JUN24 17.5 C | C56: 0 | D56: -40 | E56: -- | F56: 0.15 | G56: 1024.32 | H56: 281.71 | I56: -14.34 | J56: 0 | K56: 1291.69 | N56: Options On Futures
B57: 2899 27JUN24 18 C | C57: 0 | D57: 0 | E57: -- | F57: -- | G57: 3379.32 | H57: -1664.3 | I57: -28.68 | J57: 0 | K57: 1686.34 | N57: MNQ 12JUN24 19350 P | O57: 0 | P57: 0 | Q57: -- | R57: -- | S57: 0 | T57: 785 | U57: -4.7 | V57: 0 | W57: 780.3
B58: 700 27JUN24 400 C | C58: 0 | D58: -46 | E58: -- | F58: 2.57 | G58: -653.77 | H58: 410.53 | I58: -29.2 | J58: 0 | K58: -272.44 | N58: MNQ 12JUN24 19400 P | O58: 0 | P58: 0 | Q58: -- | R58: -- | S58: 0 | T58: 749 | U58: -6.58 | V58: 0 | W58: 742.42
B59: BNP 14JUN24 60 C | C59: 0 | D59: -50 | E59: -- | F59: 0.67 | G59: 0 | H59: -1557.01 | I59: -61.21 | J59: 0 | K59: -1618.22 | N59: MNQ 12JUN24 19420 P | O59: 0 | P59: 0 | Q59: -- | R59: -- | S59: 0 | T59: 8705.5 | U59: -23.97 | V59: 0 | W59: 8681.53
B60: BNP 14JUN24 63 C | C60: 0 | D60: -100 | E60: -- | F60: 0.05 | G60: 9548.36 | H60: -1528.63 | I60: -122.72 | J60: 0 | K60: 7897.01 | N60: MNQ 12JUN24 19425 P | O60: 0 | P60: 0 | Q60: -- | R60: -- | S60: 0 | T60: 655 | U60: -4.7 | V60: 0 | W60: 650.3
B61: DELL 07JUN24 121 P | C61: -5 | D61: 0 | E61: 0.1593 | F61: -- | G61: 79.65 | H61: 0 | I61: 0 | J61: 0 | K61: 79.65 | N61: MNQ 12JUN24 19430 P | O61: 0 | P61: 0 | Q61: -- | R61: -- | S61: 0 | T61: 1630 | U61: -9.4 | V61: 0 | W61: 1620.6
B62: DELL 07JUN24 125 P | C62: -4 | D62: 0 | E62: 0.3105 | F62: -- | G62: 124.2 | H62: 0 | I62: 0 | J62: 0 | K62: 124.2 | N62: MNQ 12JUN24 19450 P | O62: 0 | P62: 0 | Q62: -- | R62: -- | S62: 0 | T62: 1100 | U62: -4.7 | V62: 0 | W62: 1095.3
B63: DELL 07JUN24 130 P | C63: -6 | D63: 0 | E63: 0.8787 | F63: -- | G63: 509.22 | H63: 18 | I63: 0 | J63: 0 | K63: 527.22 | N63: MNQ 13JUN24 19630 C | O63: 0 | P63: 0 | Q63: -- | R63: -- | S63: 0 | T63: -114 | U63: -9.4 | V63: 0 | W63: -123.4
B64: DELL 14JUN24 119 P | C64: 0 | D64: -10 | E64: -- | F64: 0.0001 | G64: 779 | H64: 470.9 | I64: 2.97 | J64: 0 | K64: 1252.87 | N64: MNQ 13JUN24 19660 C | O64: 0 | P64: 0 | Q64: -- | R64: -- | S64: 0 | T64: 220 | U64: -4.7 | V64: 0 | W64: 215.3
B65: DELL 14JUN24 120 P | C65: -5 | D65: -8 | E65: 0.3821 | F65: 0.0001 | G65: 468.47 | H65: 181.5 | I65: -2.11 | J65: 0 | K65: 647.86 | N65: MNQ 13JUN24 19500 P | O65: 0 | P65: 0 | Q65: -- | R65: -- | S65: 0 | T65: 285 | U65: -7.05 | V65: 0 | W65: 277.95
B66: DELL 14JUN24 122 P | C66: 0 | D66: -30 | E66: -- | F66: 0.0002 | G66: 3756 | H66: 1433.4 | I66: -0.63 | J66: 0 | K66: 5188.77 | N66: MNQ 13JUN24 19520 P | O66: 0 | P66: 0 | Q66: -- | R66: -- | S66: 0 | T66: 367.5 | U66: -7.05 | V66: 0 | W66: 360.45
B67: DELL 14JUN24 123 P | C67: -2 | D67: -2 | E67: 0.6114 | F67: 0.0007 | G67: 122.14 | H67: 0 | I67: 0 | J67: 0 | K67: 122.14 | N67: MNQ 13JUN24 19600 P | O67: 0 | P67: 0 | Q67: -- | R67: -- | S67: 0 | T67: 660 | U67: -4.7 | V67: 0 | W67: 655.3
B68: DELL 14JUN24 126 P | C68: -4 | D68: -4 | E68: 0.9154 | F68: 0.0115 | G68: 361.56 | H68: 0 | I68: 0 | J68: 0 | K68: 361.56 | N68: MNQ 13JUN24 19610 P | O68: 0 | P68: 0 | Q68: -- | R68: -- | S68: 0 | T68: 1285 | U68: -18.8 | V68: 0 | W68: 1266.2
B69: EWY 21JUN24 66 C | C69: 0 | D69: -100 | E69: -- | F69: 0.3 | G69: 2250 | H69: 660 | I69: -17.87 | J69: 0 | K69: 2892.13 | N69: MNQ 14JUN24 19600 P | O69: 0 | P69: -51 | Q69: -- | R69: 52.5 | S69: 0 | T69: 2893.5 | U69: -23.97 | V69: 0 | W69: 2869.53
B70: EWY 21JUN24 67 C | C70: 0 | D70: -130 | E70: -- | F70: 0.1 | G70: 1950 | H70: 419 | I70: -48.86 | J70: 0 | K70: 2320.14 | N70: NQ 12JUN24 19400 P | O70: 0 | P70: 0 | Q70: -- | R70: -- | S70: 0 | T70: 3035 | U70: -39.76 | V70: 0 | W70: 2995.24
B71: GLD 31MAY24 217.5 P | C71: -80 | D71: 0 | E71: 2.2 | F71: -- | G71: 0 | H71: 17600 | I71: 0 | J71: 0 | K71: 17600 | N71: NQ 12JUN24 19425 P | O71: 0 | P71: 0 | Q71: -- | R71: -- | S71: 0 | T71: 3550 | U71: -28.4 | V71: 0 | W71: 3521.6
B72: GLD 07JUN24 217.5 C | C72: 0 | D72: 0 | E72: -- | F72: -- | G72: 6100 | H72: -1810 | I72: -23.7 | J72: 0 | K72: 4266.3 | N72: NQ 12JUN24 19430 P | O72: 0 | P72: 0 | Q72: -- | R72: -- | S72: 0 | T72: 2600 | U72: -28.4 | V72: 0 | W72: 2571.6
B73: GLD 07JUN24 220 C | C73: 0 | D73: 0 | E73: -- | F73: -- | G73: 3240 | H73: -1060 | I73: -23.65 | J73: 0 | K73: 2156.35 | N73: NQ 13JUN24 19600 C | O73: 0 | P73: 0 | Q73: -- | R73: -- | S73: 0 | T73: -3190 | U73: -28.4 | V73: 0 | W73: -3218.4
B74: GLD 14JUN24 205 P | C74: 0 | D74: -5 | E74: -- | F74: 0.0024 | G74: 188.8 | H74: -90 | I74: -3.45 | J74: 0 | K74: 95.35 | N74: NQ 13JUN24 19600 P | O74: 0 | P74: 0 | Q74: -- | R74: -- | S74: 0 | T74: 5450 | U74: -7.1 | V74: 0 | W74: 5442.9
B75: GLD 14JUN24 207.5 P | C75: 0 | D75: -5 | E75: -- | F75: 0.015 | G75: 370 | H75: -202.5 | I75: -3.45 | J75: 0 | K75: 164.05 | N75: Total Options On Futures | S75: 0 | T75: 30666.5 | U75: -261.78 | V75: 0 | W75: 30404.72
B76: GLD 14JUN24 212.5 C | C76: 0 | D76: -40 | E76: -- | F76: 1.0335 | G76: 5920.4 | H76: -634.4 | I76: -19.87 | J76: 0 | K76: 5266.13
B77: GLD 14JUN24 215 C | C77: 0 | D77: -40 | E77: -- | F77: 0.185 | G77: 3100 | H77: 4241 | I77: -27.85 | J77: 0 | K77: 7313.15
B78: GLD 14JUN24 217.5 C | C78: 0 | D78: -80 | E78: -- | F78: 0.035 | G78: 3680 | H78: 2210 | I78: -50.64 | J78: 0 | K78: 5839.36
B79: IWM 07JUN24 208 C | C79: 0 | D79: 0 | E79: -- | F79: -- | G79: 2726 | H79: -1668 | I79: -41.23 | J79: 0 | K79: 1016.77
B80: IWM 14JUN24 206 C | C80: 0 | D80: -2 | E80: -- | F80: 0.035 | G80: 0 | H80: 19 | I80: -2.38 | J80: 0 | K80: 16.62
B81: IWM 14JUN24 208 C | C81: 0 | D81: -58 | E81: -- | F81: 0.0045 | G81: 2148.9 | H81: 985 | I81: -45.69 | J81: 0 | K81: 3088.21
B82: IWM 17JUN24 204 C | C82: 0 | D82: -45 | E82: -- | F82: 0.43 | G82: 0 | H82: 2059 | I82: -31.51 | J82: 0 | K82: 2027.49
B83: MCD 14JUN24 265 C | C83: 0 | D83: -7 | E83: -- | F83: 0.002 | G83: 884.1 | H83: -6.5 | I83: -4.11 | J83: 0 | K83: 873.49
B84: QQQ 06JUN24 460 P | C84: 0 | D84: 0 | E84: -- | F84: -- | G84: 0 | H84: 1115 | I84: -29.07 | J84: 0 | K84: 1085.93
B85: QQQ 07JUN24 458 P | C85: 0 | D85: 0 | E85: -- | F85: -- | G85: 0 | H85: 200 | I85: -6.9 | J85: 0 | K85: 193.1
B86: QQQ 07JUN24 460 C | C86: 0 | D86: 0 | E86: -- | F86: -- | G86: 11437.2 | H86: 22.8 | I86: -35.2 | J86: 0 | K86: 11424.8
B87: QQQ 10JUN24 458 P | C87: 0 | D87: 0 | E87: -- | F87: -- | G87: 0 | H87: 350 | I87: -13.83 | J87: 0 | K87: 336.17
B88: QQQ 10JUN24 459 P | C88: 0 | D88: 0 | E88: -- | F88: -- | G88: 0 | H88: 500 | I88: -13.82 | J88: 0 | K88: 486.18
B89: QQQ 10JUN24 460 P | C89: 0 | D89: 0 | E89: -- | F89: -- | G89: 0 | H89: 1290 | I89: -46.06 | J89: 0 | K89: 1243.94
B90: QQQ 11JUN24 459 P | C90: 0 | D90: 0 | E90: -- | F90: -- | G90: 0 | H90: 200 | I90: -6.9 | J90: 0 | K90: 193.1
B91: QQQ 11JUN24 460 P | C91: 0 | D91: 0 | E91: -- | F91: -- | G91: 0 | H91: 860 | I91: -27.69 | J91: 0 | K91: 832.31
B92: QQQ 11JUN24 461 P | C92: 0 | D92: 0 | E92: -- | F92: -- | G92: 0 | H92: 1190 | I92: -31.32 | J92: 0 | K92: 1158.68
B93: QQQ 11JUN24 462 P | C93: 0 | D93: 0 | E93: -- | F93: -- | G93: 0 | H93: 410 | I93: -11.48 | J93: 0 | K93: 398.52
B94: QQQ 12JUN24 472 C | C94: 0 | D94: 0 | E94: -- | F94: -- | G94: 0 | H94: 8610 | I94: -50.08 | J94: 0 | K94: 8559.92
B95: TLT 07JUN24 92.5 C | C95: 0 | D95: 0 | E95: -- | F95: -- | G95: 545.6 | H95: -270.6 | I95: -2.58 | J95: 0 | K95: 272.42
B96: TLT 07JUN24 93 C | C96: 0 | D96: 0 | E96: -- | F96: -- | G96: 2720.84 | H96: -769.84 | I96: -26.62 | J96: 0 | K96: 1924.38
B97: TSM 14JUN24 170 C | C97: 0 | D97: -15 | E97: -- | F97: 3.3422 | G97: -3775.8 | H97: 73.5 | I97: -8.97 | J97: 0 | K97: -3711.27
B98: XLV 07JUN24 147 C | C98: 0 | D98: 0 | E98: -- | F98: -- | G98: 155 | H98: 145 | I98: -4.5 | J98: 0 | K98: 295.5
B99: XLV 07JUN24 147.5 C | C99: 0 | D99: 0 | E99: -- | F99: -- | G99: 187.5 | H99: 222.5 | I99: -17.4 | J99: 0 | K99: 392.6
B100: XLV 07JUN24 148 C | C100: 0 | D100: 0 | E100: -- | F100: -- | G100: 31.5 | H100: 49.5 | I100: -4.95 | J100: 0 | K100: 76.05
...

Sheet Sheet1
A1: 10Y | B1: 30Y | E1: 30Y price | F1: 10Y price
A2: 0.0388 | B2: 0.0397 | E2: 125.34 | F2: 112.3
A3: 0.0346 | B3: 0.0362 | E3: 131.06 | F3: 115.03
A4: =A3/A2-1 -> -0.10824742 | B4: =B3/B2-1 -> -0.088161209 | E4: =E3/E2-1 -> 0.04563587 | F4: =F3/F2-1 -> 0.024309884
A6: =A3-A2 -> -0.0042 | B6: =B3-B2 -> -0.0035
E7: =E4/B6 -> -13.03882 | F7: =F4/A6 -> -5.7880677
B8: =3% -> 0.03
B9: =B8-B2 -> -0.0097
B10: =B9*E7 -> 0.12647656
E14: 0.195 | F14: 0.355 | H14: =F14-E14 -> 0.16
E15: 0.315 | F15: 0.681 | H15: =F15-E15 -> 0.366
E16: -0.324 | F16: 0.028 | H16: =F16-E16 -> 0.352
E17: 0.592 | F17: 1.302 | H17: =F17-E17 -> 0.71
E18: 0.105 | F18: 0.903 | H18: =F18-E18 -> 0.798
E19: 0.137 | F19: 0.75 | H19: =F19-E19 -> 0.613
E20: -0.548 | F20: -0.368 | H20: =F20-E20 -> 0.18

Sheet Historical NAV_no option
A1: DATE | B1: NAV (USD) | C1: CASH INJECTION | D1: Interest Accruals | E1: Dividend Accruals | F1: NEXT START NAV | G1: M START NAV | H1: DAILY P&L | I1: Daily Return | J1: MTD Change | K1: MTD % | L1: Cal | M1: LTD ROR% | N1: YTD ROR% | O1: Annualised Return | P1: Annualised Volatility | Q1: 30 Days P&L | R1: 30 Days Return | S1: 90 Days P&L | T1: 90 Days Return | U1: 365 Days P&L | V1: 365 Days Return | W1: Sharpe Ratio | X1: Risk Free Rate (Assumed 4.5%) | Y1: Excess Return | Z1: Negative Excess Returns | AA1: Square of (Negative Excess Returns) | AB1: Sotino Ratio | AC1: Value at Risk 95%(30days) | AD1: Value at Risk 95%(90days) | AE1: Value at Risk 95%(365days)
A2: 44013 | B2: 8106215.1 | F2: 8106215.1 | G2: 8129676.1 | H2: -23460.98 | I2: -0.0028858444 | J2: -23460.98 | K2: -0.0028858444 | L2: =1+I2 -> 0.99711416 | M2: =PRODUCT($L$2:L2)-1 -> -0.0028858444
A3: 44014 | B3: 8174039.8 | F3: =B3 -> 8174039.8 | G3: =G2 -> 8129676.1 | H3: 67824.64 | I3: 0.0083669924 | J3: 44363.66 | K3: 0.0054570021 | L3: =1+I3 -> 1.008367 | M3: =PRODUCT($L$2:L3)-1 -> 0.0054570021
A4: 44018 | B4: 8297117.3 | F4: =B4 -> 8297117.3 | G4: =G3 -> 8129676.1 | H4: 123077.55 | I4: 0.015057126 | J4: 167441.21 | K4: 0.020596295 | L4: =1+I4 -> 1.0150571 | M4: =PRODUCT($L$2:L4)-1 -> 0.020596295
A5: 44019 | B5: 8333268.5 | F5: =B5 -> 8333268.5 | G5: =G4 -> 8129676.1 | H5: 36151.23 | I5: 0.0043570831 | J5: 203592.44 | K5: 0.025043118 | L5: =1+I5 -> 1.0043571 | M5: =PRODUCT($L$2:L5)-1 -> 0.025043118
A6: 44020 | B6: 8402868.6 | F6: =B6 -> 8402868.6 | G6: =G5 -> 8129676.1 | H6: 69600.06 | I6: 0.0083520721 | J6: 273192.5 | K6: 0.033604352 | L6: =1+I6 -> 1.0083521 | M6: =PRODUCT($L$2:L6)-1 -> 0.033604352
A7: 44021 | B7: 8486246.5 | F7: =B7 -> 8486246.5 | G7: =G6 -> 8129676.1 | H7: 83377.92 | I7: 0.0099225543 | J7: 356570.42 | K7: 0.043860348 | L7: =1+I7 -> 1.0099226 | M7: =PRODUCT($L$2:L7)-1 -> 0.043860348
A8: 44025 | B8: 8403900.2 | F8: =B8 -> 8403900.2 | G8: =G7 -> 8129676.1 | H8: -82346.35 | I8: -0.0097035067 | J8: 274224.07 | K8: 0.033731242 | L8: =1+I8 -> 0.99029649 | M8: =PRODUCT($L$2:L8)-1 -> 0.033731242
A9: 44026 | B9: 8483233.3 | F9: =B9 -> 8483233.3 | G9: =G8 -> 8129676.1 | H9: 79333.16 | I9: 0.0094400407 | J9: 353557.23 | K9: 0.043489707 | L9: =1+I9 -> 1.00944 | M9: =PRODUCT($L$2:L9)-1 -> 0.043489707
A10: 44027 | B10: 8478930.9 | F10: =B10 -> 8478930.9 | G10: =G9 -> 8129676.1 | H10: -4302.43 | I10: -0.00050716865 | J10: 349254.8 | K10: 0.042960481 | L10: =1+I10 -> 0.99949283 | M10: =PRODUCT($L$2:L10)-1 -> 0.042960481
A11: 44028 | B11: 8434812.8 | F11: =B11 -> 8434812.8 | G11: =G9 -> 8129676.1 | H11: -44118.11 | I11: -0.0052006244 | J11: 305136.69 | K11: 0.037533683 | L11: =1+I11 -> 0.99479938 | M11: =PRODUCT($L$2:L11)-1 -> 0.037536436
A12: 44029 | B12: 8475481.8 | F12: =B12 -> 8475481.8 | G12: =G11 -> 8129676.1 | H12: 40668.96 | I12: 0.0048215605 | J12: 345805.65 | K12: 0.042536215 | L12: =1+I12 -> 1.0048216 | M12: =PRODUCT($L$2:L12)-1 -> 0.04253898
A13: 44032 | B13: 7795603.9 | C13: -800000 | F13: =B13 -> 7795603.9 | G13: =G12 -> 8129676.1 | H13: 120122.1 | I13: 0.0157 | J13: -334072.25 | K13: 0.0589 | L13: =1+I13 -> 1.0157 | M13: =PRODUCT($L$2:L13)-1 -> 0.058906842
A14: 44033 | B14: 7768360.5 | F14: =B14 -> 7768360.5 | G14: =G13+C13 -> 7329676.1 | H14: -27243.35 | I14: -0.0034947068 | J14: 438684.4 | K14: 0.0552 | L14: =1+I14 -> 0.99650529 | M14: =PRODUCT($L$2:L14)-1 -> 0.055206273
A15: 44034 | B15: 7803379.3 | F15: =B15 -> 7803379.3 | G15: =G14 -> 7329676.1 | H15: 35018.83 | I15: 0.0045078791 | J15: 473703.23 | K15: 0.0599 | L15: =1+I15 -> 1.0045079 | M15: =PRODUCT($L$2:L15)-1 -> 0.059963016
A16: 44035 | B16: 7757505.2 | F16: =B16 -> 7757505.2 | G16: 7362157.3 | H16: -45874.16 | I16: -0.0058787556 | J16: 395347.85 | K16: 0.0537 | L16: =1+I16 -> 0.99412124 | M16: =PRODUCT($L$2:L16)-1 -> 0.053731752
A17: 44036 | B17: 7718043 | F17: =B17 -> 7718043 | G17: =G16 -> 7362157.3 | H17: -39462.22 | I17: -0.0050869731 | J17: 355885.63 | K17: 0.048339856 | L17: =1+I17 -> 0.99491303 | M17: =PRODUCT($L$2:L17)-1 -> 0.048371447
A18: 44039 | B18: 7848768.5 | F18: =B18 -> 7848768.5 | G18: =G17 -> 7362157.3 | H18: 130725.52 | I18: 0.016937651 | J18: 486611.15 | K18: 0.066096271 | L18: =1+I18 -> 1.0169377 | M18: =PRODUCT($L$2:L18)-1 -> 0.066128397
A19: 44040 | B19: 7829336.3 | F19: =B19 -> 7829336.3 | G19: =G18 -> 7362157.3 | H19: -19432.15 | I19: -0.0024758215 | J19: 467179 | K19: 0.0634 | L19: =1+I19 -> 0.99752418 | M19: =PRODUCT($L$2:L19)-1 -> 0.063488854
A20: 44041 | B20: 7899344.2 | F20: =B20 -> 7899344.2 | G20: =G19 -> 7362157.3 | H20: 70007.84 | I20: 0.0089417336 | J20: 537186.84 | K20: 0.0729 | L20: =1+I20 -> 1.0089417 | M20: =PRODUCT($L$2:L20)-1 -> 0.072998288
A21: 44043 | B21: 8019590.3 | F21: =B21 -> 8019590.3 | G21: =G20 -> 7362157.3 | H21: 120149.88 | I21: 0.015210108 | J21: 657336.72 | K21: 0.089285883 | L21: =1+I21 -> 1.0152101 | M21: =PRODUCT($L$2:L21)-1 -> 0.089318708
A22: 44046 | B22: 8080929.5 | F22: =B22 -> 8080929.5 | G22: =IF(MONTH(A22)=MONTH(A21),G21,F21) -> 8019590.3 | H22: =B22-C22-F21 -> 61339.18 | I22: =H22/B21 -> 0.0076486675 | J22: =IF(MONTH(A22)=MONTH(A21),J21+H22,H22) -> 61339.18 | K22: =J22/G22 -> 0.0076486675 | L22: =1+I22 -> 1.0076487 | M22: =PRODUCT($L$2:L22)-1 -> 0.097650544
A23: 44047 | B23: 8290234 | D23: -263.43 | E23: 0 | F23: =B23 -> 8290234 | G23: =IF(MONTH(A23)=MONTH(A22),G22,F22) -> 8019590.3 | H23: =B23-C23-F22 -> 209304.52 | I23: =H23/B22 -> 0.025901045 | J23: =IF(MONTH(A23)=MONTH(A22),J22+H23,H23) -> 270643.7 | K23: =J23/G23 -> 0.033747821 | L23: =1+I23 -> 1.025901 | M23: =PRODUCT($L$2:L23)-1 -> 0.12608084
A24: 44048 | B24: 8397007.3 | D24: 98.79 | E24: -137.98 | F24: =B24 -> 8397007.3 | G24: =IF(MONTH(A24)=MONTH(A23),G23,F23) -> 8019590.3 | H24: =B24-C24-F23 -> 106773.3 | I24: =H24/B23 -> 0.012879407 | J24: =IF(MONTH(A24)=MONTH(A23),J23+H24,H24) -> 377417 | K24: =J24/G24 -> 0.04706188 | L24: =1+I24 -> 1.0128794 | M24: =PRODUCT($L$2:L24)-1 -> 0.14058409
A25: 44049 | B25: 8505200.1 | D25: -80.62 | E25: -137.98 | F25: =B25 -> 8505200.1 | G25: =IF(MONTH(A25)=MONTH(A24),G24,F24) -> 8019590.3 | H25: =B25-C25-F24 -> 108192.83 | I25: =H25/B24 -> 0.012884689 | J25: =IF(MONTH(A25)=MONTH(A24),J24+H25,H25) -> 485609.83 | K25: =J25/G25 -> 0.060552947 | L25: =1+I25 -> 1.0128847 | M25: =PRODUCT($L$2:L25)-1 -> 0.15528017
A26: 44050 | B26: 8196625.5 | D26: -231.61 | E26: 803.96 | F26: =B26 -> 8196625.5 | G26: =IF(MONTH(A26)=MONTH(A25),G25,F25) -> 8019590.3 | H26: =B26-C26-F25 -> -308574.63 | I26: =H26/B25 -> -0.036280702 | J26: =IF(MONTH(A26)=MONTH(A25),J25+H26,H26) -> 177035.2 | K26: =J26/G26 -> 0.022075342 | L26: =1+I26 -> 0.9637193 | M26: =PRODUCT($L$2:L26)-1 -> 0.11336579
A27: 44053 | B27: 7879783.9 | D27: -885.99 | E27: 803.95 | F27: =B27 -> 7879783.9 | G27: =IF(MONTH(A27)=MONTH(A26),G26,F26) -> 8019590.3 | H27: =B27-C27-F26 -> -316841.56 | I27: =H27/B26 -> -0.038655122 | J27: =IF(MONTH(A27)=MONTH(A26),J26+H27,H27) -> -139806.36 | K27: =J27/G27 -> -0.017433105 | L27: =1+I27 -> 0.96134488 | M27: =PRODUCT($L$2:L27)-1 -> 0.0703285
A28: 44054 | B28: 7384368.2 | D28: -1108.68 | E28: 803.95 | F28: =B28 -> 7384368.2 | G28: =IF(MONTH(A28)=MONTH(A27),G27,F27) -> 8019590.3 | H28: =B28-C28-F27 -> -495415.76 | I28: =H28/B27 -> -0.062871744 | J28: =IF(MONTH(A28)=MONTH(A27),J27+H28,H28) -> -635222.12 | K28: =J28/G28 -> -0.079208799 | L28: =1+I28 -> 0.93712826 | M28: =PRODUCT($L$2:L28)-1 -> 0.0030350806
A29: 44055 | B29: 7585400.9 | D29: -1485.76 | E29: 803.95 | F29: =B29 -> 7585400.9 | G29: =IF(MONTH(A29)=MONTH(A28),G28,F28) -> 8019590.3 | H29: =B29-C29-F28 -> 201032.72 | I29: =H29/B28 -> 0.027224092 | J29: =IF(MONTH(A29)=MONTH(A28),J28+H29,H29) -> -434189.4 | K29: =J29/G29 -> -0.054141095 | L29: =1+I29 -> 1.0272241 | M29: =PRODUCT($L$2:L29)-1 -> 0.0303418
A30: 44056 | B30: 7631434.3 | D30: -1746.46 | E30: 1887.85 | F30: =B30 -> 7631434.3 | G30: =IF(MONTH(A30)=MONTH(A29),G29,F29) -> 8019590.3 | H30: =B30-C30-F29 -> 46033.38 | I30: =H30/B29 -> 0.0060686812 | J30: =IF(MONTH(A30)=MONTH(A29),J29+H30,H30) -> -388156.02 | K30: =J30/G30 -> -0.048400979 | L30: =1+I30 -> 1.0060687 | M30: =PRODUCT($L$2:L30)-1 -> 0.036594616
A31: 44057 | B31: 7623006.3 | D31: -1824.82 | E31: 1887.85 | F31: =B31 -> 7623006.3 | G31: =IF(MONTH(A31)=MONTH(A30),G30,F30) -> 8019590.3 | H31: =B31-C31-F30 -> -8427.99 | I31: =H31/B30 -> -0.0011043782 | J31: =IF(MONTH(A31)=MONTH(A30),J30+H31,H31) -> -396584.01 | K31: =J31/G31 -> -0.049451904 | L31: =1+I31 -> 0.99889562 | M31: =PRODUCT($L$2:L31)-1 -> 0.035449823
A32: 44060 | B32: 7922402.5 | D32: -1965.64 | E32: 1887.85 | F32: =B32 -> 7922402.5 | G32: =IF(MONTH(A32)=MONTH(A31),G31,F31) -> 8019590.3 | H32: =B32-C32-F31 -> 299396.17 | I32: =H32/B31 -> 0.039275341 | J32: =IF(MONTH(A32)=MONTH(A31),J31+H32,H32) -> -97187.84 | K32: =J32/G32 -> -0.012118804 | L32: =1+I32 -> 1.0392753 | M32: =PRODUCT($L$2:L32)-1 -> 0.076117468
A33: 44061 | B33: 8026372.1 | D33: -2018.29 | E33: 1887.85 | F33: =B33 -> 8026372.1 | G33: =IF(MONTH(A33)=MONTH(A32),G32,F32) -> 8019590.3 | H33: =B33-C33-F32 -> 103969.61 | I33: =H33/B32 -> 0.013123495 | J33: =IF(MONTH(A33)=MONTH(A32),J32+H33,H33) -> 6781.77 | K33: =J33/G33 -> 0.00084565043 | L33: =1+I33 -> 1.0131235 | M33: =PRODUCT($L$2:L33)-1 -> 0.090239891
A34: 44062 | B34: 7968227 | D34: -2173.41 | E34: 1887.85 | F34: =B34 -> 7968227 | G34: =IF(MONTH(A34)=MONTH(A33),G33,F33) -> 8019590.3 | H34: =B34-C34-F33 -> -58145.04 | I34: =H34/B33 -> -0.0072442493 | J34: =IF(MONTH(A34)=MONTH(A33),J33+H34,H34) -> -51363.27 | K34: =J34/G34 -> -0.0064047249 | L34: =1+I34 -> 0.99275575 | M34: =PRODUCT($L$2:L34)-1 -> 0.082341921
... A42: 44074 | B42: 8142193.1 | D42: -2737.32 | E42: 4959.06 | F42: =B42 -> 8142193.1 | G42: =IF(MONTH(A42)=MONTH(A41),G41,F41) -> 8019590.3 | H42: =B42-C42-F41 -> 290346.71 | I42: =H42/B41 -> 0.036978144 | J42: =IF(MONTH(A42)=MONTH(A41),J41+H42,H42) -> 122602.8 | K42: =J42/G42 -> 0.015287913 | L42: =1+I42 -> 1.0369781 | M42: =PRODUCT($L$2:L42)-1 -> 0.10597212
A43: 44075 | B43: 8932854.6 | C43: 340000 | D43: -35.73 | E43: -1894.34 | F43: =B43 -> 8932854.6 | G43: =IF(MONTH(A43)=MONTH(A42),G42,F42) -> 8142193.1 | H43: =790661.47-C43 -> 450661.47 | I43: 0.0531 | J43: =IF(MONTH(A43)=MONTH(A42),J42+H43,H43) -> 450661.47 | K43: =I43 -> 0.0531 | L43: =1+I43 -> 1.0531 | M43: =PRODUCT($L$2:L43)-1 -> 0.16469924
A44: 44076 | B44: 8942808.3 | D44: -95.22 | E44: -1894.34 | F44: =B44 -> 8942808.3 | G44: =IF(MONTH(A44)=MONTH(A43),G43,F43) -> 8142193.1 | H44: =B44-C44-F43 -> 9953.78 | I44: =H44/B43 -> 0.0011142888 | J44: =IF(MONTH(A44)=MONTH(A43),J43+H44,H44) -> 460615.25 | K44: 0.0543 | L44: =1+I44 -> 1.0011143 | M44: =PRODUCT($L$2:L44)-1 -> 0.16599705
A45: 44077 | B45: 18349287 | C45: 10000000 | D45: 2880.09 | E45: -1894.34 | F45: =B45 -> 18349287 | G45: =IF(MONTH(A45)=MONTH(A44),G44,F44) -> 8142193.1 | H45: =B45-C45-F44 -> -593521.57 | I45: -0.0313 | J45: =IF(MONTH(A45)=MONTH(A44),J44+H45,H45) -> -132906.32 | K45: 0.0213 | L45: =1+I45 -> 0.9687 | M45: =PRODUCT($L$2:L45)-1 -> 0.12950134
A46: 44078 | B46: 17844069 | D46: 2873.06 | E46: -1894.34 | F46: =B46 -> 17844069 | G46: =IF(MONTH(A46)=MONTH(A45),G45,F45) -> 8142193.1 | H46: =B46-C46-F45 -> -505217.29 | I46: =H46/B45 -> -0.027533348 | J46: =IF(MONTH(A46)=MONTH(A45),J45+H46,H46) -> -638123.61 | K46: -0.0068 | L46: =1+I46 -> 0.97246665 | M46: =PRODUCT($L$2:L46)-1 -> 0.098402388
A47: 44081 | B47: 17832817 | D47: 2873.08 | E47: -1894.34 | F47: =B47 -> 17832817 | G47: =IF(MONTH(A47)=MONTH(A46),G46,F46) -> 8142193.1 | H47: =B47-C47-F46 -> -11252.47 | I47: =H47/B46 -> -0.00063059999 | J47: =IF(MONTH(A47)=MONTH(A46),J46+H47,H47) -> -649376.08 | K47: -0.0075 | L47: =1+I47 -> 0.9993694 | M47: =PRODUCT($L$2:L47)-1 -> 0.097709735
A48: 44082 | B48: 17315845 | D48: 2851.22 | E48: -1894.34 | F48: =B48 -> 17315845 | G48: =IF(MONTH(A48)=MONTH(A47),G47,F47) -> 8142193.1 | H48: =B48-C48-F47 -> -516971.74 | I48: =H48/B47 -> -0.028989909 | J48: =IF(MONTH(A48)=MONTH(A47),J47+H48,H48) -> -1166347.8 | K48: -0.0362 | L48: =1+I48 -> 0.97101009 | M48: =PRODUCT($L$2:L48)-1 -> 0.06588723
A49: 44083 | B49: 17720329 | D49: 2844.86 | E49: -4965.55 | F49: =B49 -> 17720329 | G49: =IF(MONTH(A49)=MONTH(A48),G48,F48) -> 8142193.1 | H49: =B49-C49-F48 -> 404483.41 | I49: =H49/B48 -> 0.023359149 | J49: =IF(MONTH(A49)=MONTH(A48),J48+H49,H49) -> -761864.41 | K49: -0.0137 | L49: =1+I49 -> 1.0233591 | M49: =PRODUCT($L$2:L49)-1 -> 0.090785449
A50: 44084 | B50: 17546118 | D50: 2838.49 | E50: -4965.55 | F50: =B50 -> 17546118 | G50: =IF(MONTH(A50)=MONTH(A49),G49,F49) -> 8142193.1 | H50: =B50-C50-F49 -> -174210.95 | I50: =H50/B49 -> -0.0098311354 | J50: =IF(MONTH(A50)=MONTH(A49),J49+H50,H50) -> -936075.36 | K50: -0.0234 | L50: =1+I50 -> 0.99016886 | M50: =PRODUCT($L$2:L50)-1 -> 0.080061789
A51: 44085 | B51: 17482798 | D51: 2833.78 | E51: -4965.55 | F51: =B51 -> 17482798 | G51: =IF(MONTH(A51)=MONTH(A50),G50,F50) -> 8142193.1 | H51: =B51-C51-F50 -> -63319.35 | I51: =H51/B50 -> -0.0036087385 | J51: =IF(MONTH(A51)=MONTH(A50),J50+H51,H51) -> -999394.71 | K51: -0.027 | L51: =1+I51 -> 0.99639126 | M51: =PRODUCT($L$2:L51)-1 -> 0.076164129
A52: 44088 | B52: 17776535 | D52: 2817.56 | E52: -4965.55 | F52: =B52 -> 17776535 | G52: =IF(MONTH(A52)=MONTH(A51),G51,F51) -> 8142193.1 | H52: =B52-C52-F51 -> 293736.13 | I52: =H52/B51 -> 0.016801437 | J52: =IF(MONTH(A52)=MONTH(A51),J51+H52,H52) -> -705658.58 | K52: -0.0106 | L52: =1+I52 -> 1.0168014 | M52: =PRODUCT($L$2:L52)-1 -> 0.094245232
A53: 44089 | B53: 17898749 | D53: 2812.89 | E53: -4965.55 | F53: =B53 -> 17898749 | G53: =IF(MONTH(A53)=MONTH(A52),G52,F52) -> 8142193.1 | H53: =B53-C53-F52 -> 122214.47 | I53: =H53/B52 -> 0.0068750447 | J53: =IF(MONTH(A53)=MONTH(A52),J52+H53,H53) -> -583444.11 | K53: -0.0038 | L53: =1+I53 -> 1.006875 | M53: =PRODUCT($L$2:L53)-1 -> 0.10176822
A54: 44090 | B54: 17688460 | D54: 2806.85 | E54: -4965.55 | F54: =B54 -> 17688460 | G54: =IF(MONTH(A54)=MONTH(A53),G53,F53) -> 8142193.1 | H54: =B54-C54-F53 -> -210289.08 | I54: =H54/B53 -> -0.011748814 | J54: =IF(MONTH(A54)=MONTH(A53),J53+H54,H54) -> -793733.19 | K54: -0.0155 | L54: =1+I54 -> 0.98825119 | M54: =PRODUCT($L$2:L54)-1 -> 0.088823747
A55: 44091 | B55: 17479824 | D55: 2802.31 | E55: -4965.55 | F55: =B55 -> 17479824 | G55: =IF(MONTH(A55)=MONTH(A54),G54,F54) -> 8142193.1 | H55: =B55-C55-F54 -> -208635.94 | I55: =H55/B54 -> -0.011795031 | J55: =IF(MONTH(A55)=MONTH(A54),J54+H55,H55) -> -1002369.1 | K55: -0.0271 | L55: =1+I55 -> 0.98820497 | M55: =PRODUCT($L$2:L55)-1 -> 0.075981037
A56: 44092 | B56: 17499642 | D56: 2796.39 | E56: -4965.55 | F56: =B56 -> 17499642 | G56: =IF(MONTH(A56)=MONTH(A55),G55,F55) -> 8142193.1 | H56: =B56-C56-F55 -> 19817.69 | I56: =H56/B55 -> 0.0011337465 | J56: =IF(MONTH(A56)=MONTH(A55),J55+H56,H56) -> -982551.44 | K56: -0.026 | L56: =1+I56 -> 1.0011337 | M56: =PRODUCT($L$2:L56)-1 -> 0.077200926
A57: 44095 | B57: 17628134 | D57: 2780.54 | E57: -4965.55 | F57: =B57 -> 17628134 | G57: =IF(MONTH(A57)=MONTH(A56),G56,F56) -> 8142193.1 | H57: =B57-C57-F56 -> 128492.31 | I57: =H57/B56 -> 0.0073425681 | J57: =IF(MONTH(A57)=MONTH(A56),J56+H57,H57) -> -854059.13 | K57: -0.0189 | L57: =1+I57 -> 1.0073426 | M57: =PRODUCT($L$2:L57)-1 -> 0.085110347
... A64: 44104 | B64: 18033797 | D64: 2568.33 | E64: -5097.04 | F64: =B64 -> 18033797 | G64: =IF(MONTH(A64)=MONTH(A63),G63,F63) -> 8142193.1 | H64: =B64-C64-F63 -> 20016.77 | I64: =H64/B63 -> 0.0011111921 | J64: =IF(MONTH(A64)=MONTH(A63),J63+H64,H64) -> -448395.89 | K64: 0.0037 | L64: =1+I64 -> 1.0011112 | M64: =PRODUCT($L$2:L64)-1 -> 0.11008119
A65: 44105 | B65: 18859614 | C65: 500000 | D65: -5.29 | F65: =B65 -> 18859614 | G65: =IF(MONTH(A65)=MONTH(A64),G64,F64) -> 18033797 | H65: =B65-C65-F64 -> 325816.92 | I65: 0.0176 | J65: =IF(MONTH(A65)=MONTH(A64),J64+H65,H65) -> 325816.92 | K65: =I65 -> 0.0176 | L65: =1+I65 -> 1.0176 | M65: =PRODUCT($L$2:L65)-1 -> 0.12961862
A66: 44106 | B66: 18429069 | D66: -39.79 | F66: =B66 -> 18429069 | G66: =IF(MONTH(A66)=MONTH(A65),G65,F65) -> 18033797 | H66: =B66-C66-F65 -> -430545.13 | I66: =H66/B65 -> -0.022828947 | J66: =IF(MONTH(A66)=MONTH(A65),J65+H66,H66) -> -104728.21 | K66: -0.0057 | L66: =1+I66 -> 0.97717105 | M66: =PRODUCT($L$2:L66)-1 -> 0.10383062
A67: 44109 | B67: 18733740 | D67: 145.05 | F67: =B67 -> 18733740 | G67: =IF(MONTH(A67)=MONTH(A66),G66,F66) -> 18033797 | H67: =B67-C67-F66 -> 304671.43 | I67: =H67/B66 -> 0.016532112 | J67: =IF(MONTH(A67)=MONTH(A66),J66+H67,H67) -> 199943.22 | K67: 0.0108 | L67: =1+I67 -> 1.0165321 | M67: =PRODUCT($L$2:L67)-1 -> 0.12207927
A68: 44110 | B68: 18512727 | D68: 12.18 | F68: =B68 -> 18512727 | G68: =IF(MONTH(A68)=MONTH(A67),G67,F67) -> 18033797 | H68: =B68-C68-F67 -> -221013.53 | I68: =H68/B67 -> -0.011797619 | J68: =IF(MONTH(A68)=MONTH(A67),J67+H68,H68) -> -21070.31 | K68: -0.0011 | L68: =1+I68 -> 0.98820238 | M68: =PRODUCT($L$2:L68)-1 -> 0.1088414
A69: 44111 | B69: 18809864 | D69: -125.41 | F69: =B69 -> 18809864 | G69: =IF(MONTH(A69)=MONTH(A68),G68,F68) -> 18033797 | H69: =B69-C69-F68 -> 297137.54 | I69: =H69/B68 -> 0.016050447 | J69: =IF(MONTH(A69)=MONTH(A68),J68+H69,H69) -> 276067.23 | K69: =(1+K68)*(1+I69)-1 -> 0.014932791 | L69: =1+I69 -> 1.0160504 | M69: =PRODUCT($L$2:L69)-1 -> 0.1266388
A70: 44112 | B70: 18757107 | D70: -243.82 | F70: =B70 -> 18757107 | G70: =IF(MONTH(A70)=MONTH(A69),G69,F69) -> 18033797 | H70: =B70-C70-F69 -> -52757.55 | I70: =H70/B69 -> -0.002804781 | J70: =IF(MONTH(A70)=MONTH(A69),J69+H70,H70) -> 223309.68 | K70: 0.012 | L70: =1+I70 -> 0.99719522 | M70: =PRODUCT($L$2:L70)-1 -> 0.12347883
A71: 44113 | B71: 19081799 | D71: -417.1 | F71: =B71 -> 19081799 | G71: =IF(MONTH(A71)=MONTH(A70),G70,F70) -> 18033797 | H71: =B71-C71-F70 -> 324692.39 | I71: =H71/B70 -> 0.017310366 | J71: =IF(MONTH(A71)=MONTH(A70),J70+H71,H71) -> 548002.07 | K71: 0.0296 | L71: =1+I71 -> 1.0173104 | M71: =PRODUCT($L$2:L71)-1 -> 0.14292666
A72: 44116 | B72: 19576913 | D72: -898.11 | F72: =B72 -> 19576913 | G72: =IF(MONTH(A72)=MONTH(A71),G71,F71) -> 18033797 | H72: =B72-C72-F71 -> 495113.44 | I72: =H72/B71 -> 0.025946895 | J72: =IF(MONTH(A72)=MONTH(A71),J71+H72,H72) -> 1043115.5 | K72: 0.0563 | L72: =1+I72 -> 1.0259469 | M72: =PRODUCT($L$2:L72)-1 -> 0.17258206
A73: 44117 | B73: 19922765 | D73: -1061.52 | F73: =B73 -> 19922765 | G73: =IF(MONTH(A73)=MONTH(A72),G72,F72) -> 18033797 | H73: =B73-C73-F72 -> 345852.56 | I73: =H73/B72 -> 0.017666348 | J73: =IF(MONTH(A73)=MONTH(A72),J72+H73,H73) -> 1388968.1 | K73: 0.0749 | L73: =1+I73 -> 1.0176663 | M73: =PRODUCT($L$2:L73)-1 -> 0.1932973
A74: 44118 | B74: 19758823 | D74: -1286.95 | F74: =B74 -> 19758823 | G74: =IF(MONTH(A74)=MONTH(A73),G73,F73) -> 18033797 | H74: =B74-C74-F73 -> -163942.31 | I74: =H74/B73 -> -0.0082288933 | J74: =IF(MONTH(A74)=MONTH(A73),J73+H74,H74) -> 1225025.8 | K74: 0.0661 | L74: =1+I74 -> 0.99177111 | M74: =PRODUCT($L$2:L74)-1 -> 0.18347778
A75: 44119 | B75: 20054697 | D75: -1603.68 | F75: =B75 -> 20054697 | G75: =IF(MONTH(A75)=MONTH(A74),G74,F74) -> 18033797 | H75: =B75-C75-F74 -> 295873.79 | I75: =H75/B74 -> 0.014974262 | J75: =IF(MONTH(A75)=MONTH(A74),J74+H75,H75) -> 1520899.6 | K75: =(1+K74)*(1+I75)-1 -> 0.082064061 | L75: =1+I75 -> 1.0149743 | M75: =PRODUCT($L$2:L75)-1 -> 0.20119949
A76: 44120 | B76: 20040183 | D76: -1923.53 | F76: =B76 -> 20040183 | G76: =IF(MONTH(A76)=MONTH(A75),G75,F75) -> 18033797 | H76: =B76-C76-F75 -> -14514.18 | I76: =H76/B75 -> -0.00072372972 | J76: =IF(MONTH(A76)=MONTH(A75),J75+H76,H76) -> 1506385.4 | K76: 0.0813 | L76: =1+I76 -> 0.99927627 | M76: =PRODUCT($L$2:L76)-1 -> 0.20033015
A77: 44123 | B77: 19733475 | D77: -2908.2 | F77: =B77 -> 19733475 | G77: =IF(MONTH(A77)=MONTH(A76),G76,F76) -> 18033797 | H77: =B77-C77-F76 -> -306707.58 | I77: =H77/B76 -> -0.01530463 | J77: =IF(MONTH(A77)=MONTH(A76),J76+H77,H77) -> 1199677.8 | K77: 0.0647 | L77: =1+I77 -> 0.98469537 | M77: =PRODUCT($L$2:L77)-1 -> 0.18195954
A78: 44124 | B78: 19783649 | D78: -3240.7 | E78: 5585.58 | F78: =B78 -> 19783649 | G78: =IF(MONTH(A78)=MONTH(A77),G77,F77) -> 18033797 | H78: =B78-C78-F77 -> 50174.37 | I78: =H78/B77 -> 0.0025426018 | J78: =IF(MONTH(A78)=MONTH(A77),J77+H78,H78) -> 1249852.2 | K78: =(1+K77)*(1+I78)-1 -> 0.067407108 | L78: =1+I78 -> 1.0025426 | M78: =PRODUCT($L$2:L78)-1 -> 0.18496479
A79: 44125 | B79: 19288148 | D79: -3571.85 | E79: 5585.58 | F79: =B79 -> 19288148 | G79: =IF(MONTH(A79)=MONTH(A78),G78,F78) -> 18033797 | H79: =B79-C79-F78 -> -495501.49 | I79: =H79/B78 -> -0.025046011 | J79: =IF(MONTH(A79)=MONTH(A78),J78+H79,H79) -> 754350.67 | K79: =(1+K78)*(1+I79)-1 -> 0.040672819 | L79: =1+I79 -> 0.97495399 | M79: =PRODUCT($L$2:L79)-1 -> 0.15528615
A80: 44126 | B80: 18838068 | D80: -3919.06 | E80: 5585.58 | F80: =B80 -> 18838068 | G80: =IF(MONTH(A80)=MONTH(A79),G79,F79) -> 18033797 | H80: =B80-C80-F79 -> -450079.82 | I80: =H80/B79 -> -0.023334528 | J80: =IF(MONTH(A80)=MONTH(A79),J79+H80,H80) -> 304270.85 | K80: =(1+K79)*(1+I80)-1 -> 0.01638921 | L80: =1+I80 -> 0.97666547 | M80: =PRODUCT($L$2:L80)-1 -> 0.12832809
A81: 44127 | B81: 19120205 | D81: -4232.74 | E81: 5585.58 | F81: =B81 -> 19120205 | G81: =IF(MONTH(A81)=MONTH(A80),G80,F80) -> 18033797 | H81: =B81-C81-F80 -> 282136.97 | I81: =H81/B80 -> 0.014976959 | J81: =IF(MONTH(A81)=MONTH(A80),J80+H81,H81) -> 586407.82 | K81: =(1+K80)*(1+I81)-1 -> 0.031611629 | L81: =1+I81 -> 1.014977 | M81: =PRODUCT($L$2:L81)-1 -> 0.14522702
A82: 44130 | B82: 18895076 | D82: -4978.02 | E82: 5585.58 | F82: =B82 -> 18895076 | G82: =IF(MONTH(A82)=MONTH(A81),G81,F81) -> 18033797 | H82: =B82-C82-F81 -> -225129.48 | I82: =H82/B81 -> -0.011774428 | J82: =IF(MONTH(A82)=MONTH(A81),J81+H82,H82) -> 361278.34 | K82: =(1+K81)*(1+I82)-1 -> 0.019464992 | L82: =1+I82 -> 0.98822557 | M82: =PRODUCT($L$2:L82)-1 -> 0.13174262
A83: 44131 | B83: 19203986 | D83: -5243.69 | E83: 5585.58 | F83: =B83 -> 19203986 | G83: =IF(MONTH(A83)=MONTH(A82),G82,F82) -> 18033797 | H83: =B83-C83-F82 -> 308910.56 | I83: =H83/B82 -> 0.016348734 | J83: =IF(MONTH(A83)=MONTH(A82),J82+H83,H83) -> 670188.9 | K83: 0.0362 | L83: =1+I83 -> 1.0163487 | M83: =PRODUCT($L$2:L83)-1 -> 0.15024518
A84: 44132 | B84: 18424241 | D84: -5468.89 | E84: 5585.58 | F84: =B84 -> 18424241 | G84: =IF(MONTH(A84)=MONTH(A83),G83,F83) -> 18033797 | H84: =B84-C84-F83 -> -779745.06 | I84: =H84/B83 -> -0.040603292 | J84: =IF(MONTH(A84)=MONTH(A83),J83+H84,H84) -> -109556.16 | K84: =(1+K83)*(1+I84)-1 -> -0.0058731314 | L84: =1+I84 -> 0.95939671 | M84: =PRODUCT($L$2:L84)-1 -> 0.10354144
A85: 44133 | B85: 18483188 | D85: -5680.72 | E85: 8457.03 | F85: =B85 -> 18483188 | G85: =IF(MONTH(A85)=MONTH(A84),G84,F84) -> 18033797 | H85: =B85-C85-F84 -> 58946.82 | I85: =H85/B84 -> 0.0031994165 | J85: =IF(MONTH(A85)=MONTH(A84),J84+H85,H85) -> -50609.34 | K85: =(1+K84)*(1+I85)-1 -> -0.0026925055 | L85: =1+I85 -> 1.0031994 | M85: =PRODUCT($L$2:L85)-1 -> 0.10707213
A86: 44134 | B86: 17677657 | D86: -5844.23 | E86: 8457.04 | F86: =B86 -> 17677657 | G86: =IF(MONTH(A86)=MONTH(A85),G85,F85) -> 18033797 | H86: =B86-C86-F85 -> -805531.36 | I86: =H86/B85 -> -0.043581841 | J86: =IF(MONTH(A86)=MONTH(A85),J85+H86,H86) -> -856140.7 | K86: =(1+K85)*(1+I86)-1 -> -0.046157002 | L86: =1+I86 -> 0.95641816 | M86: =PRODUCT($L$2:L86)-1 -> 0.058823888
A87: 44137 | B87: 18652090 | C87: 500000 | D87: -488.15 | F87: =B87 -> 18652090 | G87: =IF(MONTH(A87)=MONTH(A86),G86,F86) -> 17677657 | H87: =B87-C87-F86 -> 474433.16 | I87: 0.0261 | J87: =IF(MONTH(A87)=MONTH(A86),J86+H87,H87) -> 474433.16 | K87: 0.0261 | L87: =1+I87 -> 1.0261 | M87: =PRODUCT($L$2:L87)-1 -> 0.086459191
A88: 44138 | B88: 25045656 | C88: 6000000 | D88: -656.25 | F88: =B88 -> 25045656 | G88: =IF(MONTH(A88)=MONTH(A87),G87,F87) -> 17677657 | H88: =B88-C88-F87 -> 393566.46 | I88: 0.016 | J88: =IF(MONTH(A88)=MONTH(A87),J87+H88,H88) -> 867999.62 | K88: =(1+K87)*(1+I88)-1 -> 0.0425176 | L88: =1+I88 -> 1.016 | M88: =PRODUCT($L$2:L88)-1 -> 0.10384254
A89: 44139 | B89: 25941870 | D89: 5950.2 | E89: -5585.58 | F89: =B89 -> 25941870 | G89: =IF(MONTH(A89)=MONTH(A88),G88,F88) -> 17677657 | H89: =B89-C89-F88 -> 896213.97 | I89: =H89/B88 -> 0.03578321 | J89: =IF(MONTH(A89)=MONTH(A88),J88+H89,H89) -> 1764213.6 | K89: =(1+K88)*(1+I89)-1 -> 0.079822226 | L89: =1+I89 -> 1.0357832 | M89: =PRODUCT($L$2:L89)-1 -> 0.14334157
A90: 44140 | B90: 27045285 | D90: 5942.68 | E90: -5585.58 | F90: =B90 -> 27045285 | G90: =IF(MONTH(A90)=MONTH(A89),G89,F89) -> 17677657 | H90: =B90-C90-F89 -> 1103414.9 | I90: =H90/B89 -> 0.042534131 | J90: =IF(MONTH(A90)=MONTH(A89),J89+H90,H90) -> 2867628.5 | K90: 0.1257 | L90: =1+I90 -> 1.0425341 | M90: =PRODUCT($L$2:L90)-1 -> 0.19197261
A91: 44141 | B91: 26856161 | D91: 5845.13 | E91: -5585.58 | F91: =B91 -> 26856161 | G91: =IF(MONTH(A91)=MONTH(A90),G90,F90) -> 17677657 | H91: =B91-C91-F90 -> -189123.9 | I91: =H91/B90 -> -0.0069928603 | J91: =IF(MONTH(A91)=MONTH(A90),J90+H91,H91) -> 2678504.6 | K91: =(1+K90)*(1+I91)-1 -> 0.11782814 | L91: =1+I91 -> 0.99300714 | M91: =PRODUCT($L$2:L91)-1 -> 0.18363731
A92: 44144 | B92: 24633130 | D92: 5133.15 | E92: -5585.58 | F92: =B92 -> 24633130 | G92: =IF(MONTH(A92)=MONTH(A91),G91,F91) -> 17677657 | H92: =B92-C92-F91 -> -2223030.8 | I92: =H92/B91 -> -0.082775449 | J92: =IF(MONTH(A92)=MONTH(A91),J91+H92,H92) -> 455473.8 | K92: =(1+K91)*(1+I92)-1 -> 0.025299411 | L92: =1+I92 -> 0.91722455 | M92: =PRODUCT($L$2:L92)-1 -> 0.0856612
A93: 44145 | B93: 24153859 | D93: 4890.53 | E93: -5585.58 | F93: =B93 -> 24153859 | G93: =IF(MONTH(A93)=MONTH(A92),G92,F92) -> 17677657 | H93: =B93-C93-F92 -> -479271.61 | I93: =H93/B92 -> -0.019456383 | J93: =IF(MONTH(A93)=MONTH(A92),J92+H93,H93) -> -23797.81 | K93: =(1+K92)*(1+I93)-1 -> 0.0053507933 | L93: =1+I93 -> 0.98054362 | M93: =PRODUCT($L$2:L93)-1 -> 0.06453816
A94: 44146 | B94: 24605653 | D94: 4634.09 | E94: -5585.58 | F94: =B94 -> 24605653 | G94: =IF(MONTH(A94)=MONTH(A93),G93,F93) -> 17677657 | H94: =B94-C94-F93 -> 451793.82 | I94: =H94/B93 -> 0.01870483 | J94: =IF(MONTH(A94)=MONTH(A93),J93+H94,H94) -> 427996.01 | K94: =(1+K93)*(1+I94)-1 -> 0.024155709 | L94: =1+I94 -> 1.0187048 | M94: =PRODUCT($L$2:L94)-1 -> 0.084450165
A95: 44147 | B95: 24818514 | D95: 4373.9 | E95: -5585.58 | F95: =B95 -> 24818514 | G95: =IF(MONTH(A95)=MONTH(A94),G94,F94) -> 17677657 | H95: =B95-C95-F94 -> 212861.94 | I95: =H95/B94 -> 0.0086509366 | J95: =IF(MONTH(A95)=MONTH(A94),J94+H95,H95) -> 640857.95 | K95: =(1+K94)*(1+I95)-1 -> 0.033015615 | L95: =1+I95 -> 1.0086509 | M95: =PRODUCT($L$2:L95)-1 -> 0.093831675
A96: 44148 | B96: 25055011 | D96: 4085.87 | E96: -5585.58 | F96: =B96 -> 25055011 | G96: =IF(MONTH(A96)=MONTH(A95),G95,F95) -> 17677657 | H96: =B96-C96-F95 -> 236496.14 | I96: =H96/B95 -> 0.0095290208 | J96: =IF(MONTH(A96)=MONTH(A95),J95+H96,H96) -> 877354.09 | K96: =(1+K95)*(1+I96)-1 -> 0.042859242 | L96: =1+I96 -> 1.009529 | M96: =PRODUCT($L$2:L96)-1 -> 0.10425482
A97: 44151 | B97: 25449314 | D97: 3802.45 | E97: -5585.58 | F97: =B97 -> 25449314 | G97: =IF(MONTH(A97)=MONTH(A96),G96,F96) -> 17677657 | H97: =B97-C97-F96 -> 394303.5 | I97: =H97/B96 -> 0.015737511 | J97: =IF(MONTH(A97)=MONTH(A96),J96+H97,H97) -> 1271657.6 | K97: =(1+K96)*(1+I97)-1 -> 0.059271251 | L97: =1+I97 -> 1.0157375 | M97: =PRODUCT($L$2:L97)-1 -> 0.12163304
A98: 44152 | B98: 25793136 | D98: 3674.93 | E98: -5585.58 | F98: =B98 -> 25793136 | G98: =IF(MONTH(A98)=MONTH(A97),G97,F97) -> 17677657 | H98: =B98-C98-F97 -> 343822.24 | I98: =H98/B97 -> 0.013510079 | J98: =IF(MONTH(A98)=MONTH(A97),J97+H98,H98) -> 1615479.8 | K98: =(1+K97)*(1+I98)-1 -> 0.073582089 | L98: =1+I98 -> 1.0135101 | M98: =PRODUCT($L$2:L98)-1 -> 0.13678639
A99: 44153 | B99: 25818408 | D99: 3495.63 | E99: -5585.58 | F99: =B99 -> 25818408 | G99: =IF(MONTH(A99)=MONTH(A98),G98,F98) -> 17677657 | H99: =B99-C99-F98 -> 25271.74 | I99: =H99/B98 -> 0.00097978546 | J99: =IF(MONTH(A99)=MONTH(A98),J98+H99,H99) -> 1640751.6 | K99: =(1+K98)*(1+I99)-1 -> 0.074633969 | L99: =1+I99 -> 1.0009798 | M99: =PRODUCT($L$2:L99)-1 -> 0.1379002
A100: 44154 | B100: 26452344 | D100: 3258.88 | E100: -5585.58 | F100: =B100 -> 26452344 | G100: =IF(MONTH(A100)=MONTH(A99),G99,F99) -> 17677657 | H100: =B100-C100-F99 -> 633936.39 | I100: =H100/B99 -> 0.024553659 | J100: =IF(MONTH(A100)=MONTH(A99),J99+H100,H100) -> 2274688 | K100: =(1+K99)*(1+I100)-1 -> 0.10102017 | L100: =1+I100 -> 1.0245537 | M100: =PRODUCT($L$2:L100)-1 -> 0.16583981
A101: 44155 | B101: 26839523 | D101: 2953.54 | E101: -5585.58 | F101: =B101 -> 26839523 | G101: =IF(MONTH(A101)=MONTH(A100),G100,F100) -> 17677657 | H101: =B101-C101-F100 -> 387178.77 | I101: =H101/B100 -> 0.014636841 | J101: =IF(MONTH(A101)=MONTH(A100),J100+H101,H101) -> 2661866.7 | K101: =(1+K100)*(1+I101)-1 -> 0.11713562 | L101: =1+I101 -> 1.0146368 | M101: =PRODUCT($L$2:L101)-1 -> 0.18290403
A102: 44158 | B102: 27430907 | D102: 1802.85 | E102: -8457.04 | F102: =B102 -> 27430907 | G102: =IF(MONTH(A102)=MONTH(A101),G101,F101) -> 17677657 | H102: =B102-C102-F101 -> 591383.71 | I102: =H102/B101 -> 0.022034062 | J102: =IF(MONTH(A102)=MONTH(A101),J101+H102,H102) -> 3253250.4 | K102: =(1+K101)*(1+I102)-1 -> 0.14175066 | L102: =1+I102 -> 1.0220341 | M102: =PRODUCT($L$2:L102)-1 -> 0.20896821
... A104: 44160 | B104: 27698159 | D104: 972.95 | E104: -8457.04 | F104: =B104 -> 27698159 | G104: =IF(MONTH(A104)=MONTH(A103),G103,F103) -> 17677657 | H104: =B104-C104-F103 -> -275104.26 | I104: =H104/B103 -> -0.0098345429 | J104: =IF(MONTH(A104)=MONTH(A103),J103+H104,H104) -> 3520502.9 | K104: =(1+K103)*(1+I104)-1 -> 0.15287445 | L104: =1+I104 -> 0.99016546 | M104: =PRODUCT($L$2:L104)-1 -> 0.22074688
A105: 44161 | B105: 27769610 | D105: 973.04 | E105: -8457.04 | F105: =B105 -> 27769610 | G105: =IF(MONTH(A105)=MONTH(A104),G104,F104) -> 17677657 | H105: =B105-C105-F104 -> 71450.24 | I105: =H105/B104 -> 0.0025796025 | J105: =IF(MONTH(A105)=MONTH(A104),J104+H105,H105) -> 3591953.1 | K105: 0.1559 | L105: =1+I105 -> 1.0025796 | M105: =PRODUCT($L$2:L105)-1 -> 0.22389592
A106: 44162 | B106: 28339483 | D106: 57.92 | E106: -8457.04 | F106: =B106 -> 28339483 | G106: =IF(MONTH(A106)=MONTH(A105),G105,F105) -> 17677657 | H106: =B106-C106-F105 -> 569873.77 | I106: =H106/B105 -> 0.02052149 | J106: =IF(MONTH(A106)=MONTH(A105),J105+H106,H106) -> 4161826.9 | K106: =(1+K105)*(1+I106)-1 -> 0.17962079 | L106: =1+I106 -> 1.0205215 | M106: =PRODUCT($L$2:L106)-1 -> 0.24901209
A107: 44165 | B107: 27946966 | D107: -1278.06 | E107: -8457.04 | F107: =B107 -> 27946966 | G107: =IF(MONTH(A107)=MONTH(A106),G106,F106) -> 17677657 | H107: =B107-C107-F106 -> -392517.59 | I107: =H107/B106 -> -0.013850556 | J107: =IF(MONTH(A107)=MONTH(A106),J106+H107,H107) -> 3769309.3 | K107: 0.1632 | L107: =1+I107 -> 0.98614944 | M107: =PRODUCT($L$2:L107)-1 -> 0.23171258
A108: 44166 | B108: 27413132 | C108: 75000 | D108: -477.6 | F108: =B108 -> 27413132 | G108: =IF(MONTH(A108)=MONTH(A107),G107,F107) -> 27946966 | H108: =B108-C108-F107 -> -608834.16 | I108: -0.0217 | J108: =IF(MONTH(A108)=MONTH(A107),J107+H108,H108) -> -608834.16 | K108: =I108 -> -0.0217 | L108: =1+I108 -> 0.9783 | M108: =PRODUCT($L$2:L108)-1 -> 0.20498441
A109: 44167 | B109: 27385883 | D109: -949.66 | F109: =B109 -> 27385883 | G109: =IF(MONTH(A109)=MONTH(A108),G108,F108) -> 27946966 | H109: =B109-C109-F108 -> -27248.39 | I109: =H109/B108 -> -0.00099399041 | J109: =IF(MONTH(A109)=MONTH(A108),J108+H109,H109) -> -636082.55 | K109: =(1+K108)*(1+I109)-1 -> -0.022672421 | L109: =1+I109 -> 0.99900601 | M109: =PRODUCT($L$2:L109)-1 -> 0.20378667
A110: 44168 | B110: 27866525 | D110: 6610.66 | F110: =B110 -> 27866525 | G110: =IF(MONTH(A110)=MONTH(A109),G109,F109) -> 27946966 | H110: =B110-C110-F109 -> 480641.52 | I110: =H110/B109 -> 0.017550704 | J110: =IF(MONTH(A110)=MONTH(A109),J109+H110,H110) -> -155441.03 | K110: =(1+K109)*(1+I110)-1 -> -0.0055196341 | L110: =1+I110 -> 1.0175507 | M110: =PRODUCT($L$2:L110)-1 -> 0.22491397
A111: 44169 | B111: 27947341 | D111: 6184.46 | F111: =B111 -> 27947341 | G111: =IF(MONTH(A111)=MONTH(A110),G110,F110) -> 27946966 | H111: =B111-C111-F110 -> 80816.2 | I111: =H111/B110 -> 0.0029001176 | J111: =IF(MONTH(A111)=MONTH(A110),J110+H111,H111) -> -74624.83 | K111: -0.0027 | L111: =1+I111 -> 1.0029001 | M111: =PRODUCT($L$2:L111)-1 -> 0.22846637
A112: 44172 | B112: 28435336 | D112: 4608.38 | F112: =B112 -> 28435336 | G112: =IF(MONTH(A112)=MONTH(A111),G111,F111) -> 27946966 | H112: =B112-C112-F111 -> 487995.33 | I112: =H112/B111 -> 0.017461244 | J112: =IF(MONTH(A112)=MONTH(A111),J111+H112,H112) -> 413370.5 | K112: 0.0148 | L112: =1+I112 -> 1.0174612 | M112: =PRODUCT($L$2:L112)-1 -> 0.24991692
A113: 44173 | B113: 28815379 | D113: 4125.99 | F113: =B113 -> 28815379 | G113: =IF(MONTH(A113)=MONTH(A112),G112,F112) -> 27946966 | H113: =B113-C113-F112 -> 380042.8 | I113: =H113/B112 -> 0.013365159 | J113: =IF(MONTH(A113)=MONTH(A112),J112+H113,H113) -> 793413.3 | K113: 0.0283 | L113: =1+I113 -> 1.0133652 | M113: =PRODUCT($L$2:L113)-1 -> 0.26662226
A114: 44174 | B114: 27726628 | D114: 3583.61 | F114: =B114 -> 27726628 | G114: =IF(MONTH(A114)=MONTH(A113),G113,F113) -> 27946966 | H114: =B114-C114-F113 -> -1088750.7 | I114: =H114/B113 -> -0.037783667 | J114: =IF(MONTH(A114)=MONTH(A113),J113+H114,H114) -> -295337.4 | K114: -0.0105 | L114: =1+I114 -> 0.96221633 | M114: =PRODUCT($L$2:L114)-1 -> 0.21876462
...

Sheet Filter Equity Tickers
A1: Equity Tickers
A2: Stocks | B2: Total
A3: =IB_html!B2 -> 0 | B3: Determining Tickers | C3: Tickers | D3: Position Size
A4: =IB_html!B3 -> Symbol | B4: =IF(OR(A3=$A$2, AND(B3=1, A4<>$B$2)), 1,IF(OR(A4=$B$2, B3=0), 0,0)) -> 0 | C4: =IF(B4=1,A4, "") | D4: =INDEX(IB_html!D:D, MATCH('Filter Equity Tickers'!C4,IB_html!B:B,0)) -> #N/A
A5: =IB_html!B4 -> Stocks | B5: =IF(OR(A4=$A$2, AND(B4=1, A5<>$B$2)), 1,IF(OR(A5=$B$2, B4=0), 0,0)) -> 0 | C5: =IF(B5=1,A5, "") | D5: =INDEX(IB_html!D:D, MATCH('Filter Equity Tickers'!C5,IB_html!B:B,0)) -> #N/A
A6: =IB_html!B5 -> 333 | B6: =IF(OR(A5=$A$2, AND(B5=1, A6<>$B$2)), 1,IF(OR(A6=$B$2, B5=0), 0,0)) -> 1 | C6: =IF(B6=1,A6, "") -> 333 | D6: =INDEX(IB_html!D:D, MATCH('Filter Equity Tickers'!C6,IB_html!B:B,0)) -> 28000
A7: =IB_html!B6 -> 921 | B7: =IF(OR(A6=$A$2, AND(B6=1, A7<>$B$2)), 1,IF(OR(A7=$B$2, B6=0), 0,0)) -> 1 | C7: =IF(B7=1,A7, "") -> 921 | D7: =INDEX(IB_html!D:D, MATCH('Filter Equity Tickers'!C7,IB_html!B:B,0)) -> 34100
A8: =IB_html!B7 -> 1109 | B8: =IF(OR(A7=$A$2, AND(B7=1, A8<>$B$2)), 1,IF(OR(A8=$B$2, B7=0), 0,0)) -> 1 | C8: =IF(B8=1,A8, "") -> 1109 | D8: =INDEX(IB_html!D:D, MATCH('Filter Equity Tickers'!C8,IB_html!B:B,0)) -> 220000
A9: =IB_html!B8 -> 1288 | B9: =IF(OR(A8=$A$2, AND(B8=1, A9<>$B$2)), 1,IF(OR(A9=$B$2, B8=0), 0,0)) -> 1 | C9: =IF(B9=1,A9, "") -> 1288 | D9: =INDEX(IB_html!D:D, MATCH('Filter Equity Tickers'!C9,IB_html!B:B,0)) -> 2325000
A10: =IB_html!B9 -> 2020 | B10: =IF(OR(A9=$A$2, AND(B9=1, A10<>$B$2)), 1,IF(OR(A10=$B$2, B9=0), 0,0)) -> 1 | C10: =IF(B10=1,A10, "") -> 2020 | D10: =INDEX(IB_html!D:D, MATCH('Filter Equity Tickers'!C10,IB_html!B:B,0)) -> 104800
A11: =IB_html!B10 -> 2823 | B11: =IF(OR(A10=$A$2, AND(B10=1, A11<>$B$2)), 1,IF(OR(A11=$B$2, B10=0), 0,0)) -> 1 | C11: =IF(B11=1,A11, "") -> 2823 | D11: =INDEX(IB_html!D:D, MATCH('Filter Equity Tickers'!C11,IB_html!B:B,0)) -> 618900
A12: =IB_html!B11 -> 2828 | B12: =IF(OR(A11=$A$2, AND(B11=1, A12<>$B$2)), 1,IF(OR(A12=$B$2, B11=0), 0,0)) -> 1 | C12: =IF(B12=1,A12, "") -> 2828 | D12: =INDEX(IB_html!D:D, MATCH('Filter Equity Tickers'!C12,IB_html!B:B,0)) -> 553000
A13: =IB_html!B12 -> 2899 | B13: =IF(OR(A12=$A$2, AND(B12=1, A13<>$B$2)), 1,IF(OR(A13=$B$2, B12=0), 0,0)) -> 1 | C13: =IF(B13=1,A13, "") -> 2899 | D13: =INDEX(IB_html!D:D, MATCH('Filter Equity Tickers'!C13,IB_html!B:B,0)) -> 1360000
A14: =IB_html!B13 -> 600519 | B14: =IF(OR(A13=$A$2, AND(B13=1, A14<>$B$2)), 1,IF(OR(A14=$B$2, B13=0), 0,0)) -> 1 | C14: =IF(B14=1,A14, "") -> 600519 | D14: =INDEX(IB_html!D:D, MATCH('Filter Equity Tickers'!C14,IB_html!B:B,0)) -> 900
A15: =IB_html!B14 -> 600690 | B15: =IF(OR(A14=$A$2, AND(B14=1, A15<>$B$2)), 1,IF(OR(A15=$B$2, B14=0), 0,0)) -> 1 | C15: =IF(B15=1,A15, "") -> 600690 | D15: =INDEX(IB_html!D:D, MATCH('Filter Equity Tickers'!C15,IB_html!B:B,0)) -> 22600
... A22: =IB_html!B21 -> 9988 | B22: =IF(OR(A21=$A$2, AND(B21=1, A22<>$B$2)), 1,IF(OR(A22=$B$2, B21=0), 0,0)) -> 1 | C22: =IF(B22=1,A22, "") -> 9988 | D22: =INDEX(IB_html!D:D, MATCH('Filter Equity Tickers'!C22,IB_html!B:B,0)) -> 22000
A30: 2791
A31: AAPL
A32: AMD
A33: DXCM
A34: IAU
A35: JD
A36: NEM
A37: NTES
A38: NVDA
A39: REGN
A40: SGEN
A41: TSLA

Sheet Daily NAV
C5: Total | F5: In-House Buy & Hold | G5: QuantEdge | H5: Global Sigma | J5: NOTE: | K5: To update "Month Start NAV" of QuantEdge & Global Sigma on 2ND TRADING DATE.
A6: Month Start NAV | C6: =SUM(F6:H6) -> 82114681 | F6: =OFFSET('Historical NAV'!E1, COUNT('Historical NAV'!A:A),,,) -> 66647366 | G6: 15365477 | H6: 101838.42
A8: Percentage | C8: =SUM(F8:H8) -> 1 | F8: =F6/$C$6 -> 0.81163763 | G8: =G6/$C$6 -> 0.18712217 | H8: =H6/$C$6 -> 0.0012401975
A10: Portfolio NAV | C10: =SUM(F10:H10) -> #REF! | F10: =OFFSET('Historical NAV'!B1, COUNT('Historical NAV'!A:A),,,) -> 20985069 | G10: =G6+G12 -> #REF! | H10: =H6+H12 -> #REF!
A12: MTD P&L | C12: =SUM(F12:H12) -> #REF! | F12: =OFFSET('Historical NAV'!J1, COUNT('Historical NAV'!A:A),,,) -> -45662297 | G12: =G14*G6 -> #REF! | H12: =H14*H6 -> #REF!
A14: MTD Return | C14: =C12/C6 -> #REF! | F14: =OFFSET('Historical NAV'!K1, COUNT('Historical NAV'!A:A),,,) -> -0.68349276 | G14: =IB_html!#REF! -> #REF! | H14: =IB_html!#REF! -> #REF!
G15: =IB_html!#REF! -> #REF! | H15: =IB_html!#REF! -> #REF!
A16: Daily P&L | F16: =OFFSET('Historical NAV'!F1, COUNT('Historical NAV'!A:A),,,) -> -45662297
A18: Daily Change | F18: =OFFSET('Historical NAV'!G1, COUNT('Historical NAV'!A:A),,,) -> -0.6851328
A21: Comparing to | C21: S&P 500 | D21: NASDAQ | E21: DJI | F21: 10-year US Treasury Yield | G21: Bloomberg Commodities Index | H21: Dollar Index
A22: Daily Change | C22: =_xll.BDP(C27,$A27)/100 -> 0.02913117 | D22: =_xll.BDP(D27,$A27)/100 -> 0.03827861 | E22: =_xll.BDP(E27,$A27)/100 -> 0.02488868 | F22: =_xll.BDP(F27,$A27)/100 -> -0.010054 | G22: =_xll.BDP(G27,$A27)/100 -> -0.006231608 | H22: =_xll.BDP(H27,$A27)/100 -> -0.004932023
A23: MTD | C23: =_xll.BDP(C27,$A28)/100 -> 0 | D23: =_xll.BDP(D27,$A28)/100 -> 0 | E23: =_xll.BDP(E27,$A28)/100 -> 0 | F23: =_xll.BDP(F27,$A28)/100 -> -0.010054 | G23: =_xll.BDP(G27,$A28)/100 -> -0.006231637 | H23: =_xll.BDP(H27,$A28)/100 -> -0.004932023
C24: =_xll.BDP("") -> #N/A Mandatory parameter [FIELD] not provided | E24: PX_LAST | F24: CHG_PCT_1D | G24: CHG_PCT_MTD
A27: CHG_PCT_1D | C27: SPX INDEX | D27: CCMP INDEX | E27: DJI INDEX | F27: USGG10YR INDEX | G27: BCOM INDEX | H27: DXY CURNCY
A28: CHG_PCT_MTD
